Workbook
Name Print_Area_Reset: OFFSET(Full_Print,0,0,Last_Row)
Name Print_Area_Reset: OFFSET(Full_Print,0,0,Last_Row)
Name Print_Area_Reset: OFFSET(Full_Print,0,0,Last_Row)
Name Print_Area_Reset: OFFSET(Full_Print,0,0,Last_Row)
Name Print_Area_Reset: OFFSET(Full_Print,0,0,Last_Row)
Name Print_Area_Reset: OFFSET(Full_Print,0,0,Last_Row)
Name Print_Area_Reset: OFFSET(Full_Print,0,0,Last_Row)
Name PrintRange1: [0]!IQRCIQIDH405("Chart of Accounts","F",2,"J")
Name PrintRange2: [0]!IQRCIQIDH405("Account Balances","F",2,"J")
Name PrintRange6: [0]!IQRCIQIDH405("Debtors Inquiry","F",2,"L")
Name PrintRange8: [0]!IQRCIQIDH405("P&L Forecast","F",2,"T")
Name PrintRange9: [0]!IQRCIQIDH405("Trial Balance","F",2,"M")

Sheet RPL>>
D8: Project X
D9: CLIENT
D10: Recast Statement of Operations

Sheet RPL1
A1: =IF(ROUND(SUM(E37:AR37),1)<>0,"NO","Yes") -> Yes | C1: Project X
A2: =IF(COUNTIF(E37:AR37,">0.5")+COUNTIF(E37:AR37,"<-0.5")<1,"Yes","No") -> Yes | C2: CLIENT
A3: =2-COUNTIF(A1:A2,"Yes") -> 0 | C3: ($ in 000s)
C4: Recast Statement of Operations
C7: =C4 -> Recast Statement of Operations | E7: FY24 | Q7: FY25 | AC7: FY26 | AM7: =AI8 -> 45961 | AO7: % of revenue
C8: =C3 -> ($ in 000s) | D8: Ref | E8: 45046 | F8: 45077 | G8: 45107 | H8: 45138 | I8: 45169 | J8: 45199 | K8: 45230 | L8: 45260 | M8: 45291 | N8: 45322 | O8: 45351 | P8: 45382 | Q8: 45412 | R8: 45443 | S8: 45473 | T8: 45504 | U8: 45535 | V8: 45565 | W8: 45596 | X8: 45626 | Y8: 45657 | Z8: 45688 | AA8: 45716 | AB8: 45747 | AC8: 45777 | AD8: 45808 | AE8: 45838 | AF8: 45869 | AG8: 45900 | AH8: 45930 | AI8: 45961 | AK8: FY24 | AL8: FY25 | AM8: TTM26 | AO8: =+AK8 -> FY24 | AP8: =+AL8 -> FY25 | AQ8: =+AM8 -> TTM26
C9: Service revenue | E9: =_xlfn.XLOOKUP($C9,'PL1'!$C:$C,'PL1'!E:E)+SUMIFS(ADJ!G:G,ADJ!$E:$E,'RPL1'!$C9) -> 193.127 | F9: =_xlfn.XLOOKUP($C9,'PL1'!$C:$C,'PL1'!F:F)+SUMIFS(ADJ!H:H,ADJ!$E:$E,'RPL1'!$C9) -> 429.4435 | G9: =_xlfn.XLOOKUP($C9,'PL1'!$C:$C,'PL1'!G:G)+SUMIFS(ADJ!I:I,ADJ!$E:$E,'RPL1'!$C9) -> 731.815 | H9: =_xlfn.XLOOKUP($C9,'PL1'!$C:$C,'PL1'!H:H)+SUMIFS(ADJ!J:J,ADJ!$E:$E,'RPL1'!$C9) -> 430.355 | I9: =_xlfn.XLOOKUP($C9,'PL1'!$C:$C,'PL1'!I:I)+SUMIFS(ADJ!K:K,ADJ!$E:$E,'RPL1'!$C9) -> 623.429 | J9: =_xlfn.XLOOKUP($C9,'PL1'!$C:$C,'PL1'!J:J)+SUMIFS(ADJ!L:L,ADJ!$E:$E,'RPL1'!$C9) -> 480.831 | K9: =_xlfn.XLOOKUP($C9,'PL1'!$C:$C,'PL1'!K:K)+SUMIFS(ADJ!M:M,ADJ!$E:$E,'RPL1'!$C9) -> 688.468 | L9: =_xlfn.XLOOKUP($C9,'PL1'!$C:$C,'PL1'!L:L)+SUMIFS(ADJ!N:N,ADJ!$E:$E,'RPL1'!$C9) -> 1267.3995 | M9: =_xlfn.XLOOKUP($C9,'PL1'!$C:$C,'PL1'!M:M)+SUMIFS(ADJ!O:O,ADJ!$E:$E,'RPL1'!$C9) -> 1276.176 | N9: =_xlfn.XLOOKUP($C9,'PL1'!$C:$C,'PL1'!N:N)+SUMIFS(ADJ!P:P,ADJ!$E:$E,'RPL1'!$C9) -> 238.7015 | O9: =_xlfn.XLOOKUP($C9,'PL1'!$C:$C,'PL1'!O:O)+SUMIFS(ADJ!Q:Q,ADJ!$E:$E,'RPL1'!$C9) -> 550.8931 | P9: =_xlfn.XLOOKUP($C9,'PL1'!$C:$C,'PL1'!P:P)+SUMIFS(ADJ!R:R,ADJ!$E:$E,'RPL1'!$C9) -> 736.783 | Q9: =_xlfn.XLOOKUP($C9,'PL1'!$C:$C,'PL1'!Q:Q)+SUMIFS(ADJ!S:S,ADJ!$E:$E,'RPL1'!$C9) -> 422.044 | R9: =_xlfn.XLOOKUP($C9,'PL1'!$C:$C,'PL1'!R:R)+SUMIFS(ADJ!T:T,ADJ!$E:$E,'RPL1'!$C9) -> 525.65 | S9: =_xlfn.XLOOKUP($C9,'PL1'!$C:$C,'PL1'!S:S)+SUMIFS(ADJ!U:U,ADJ!$E:$E,'RPL1'!$C9) -> 371.348 | T9: =_xlfn.XLOOKUP($C9,'PL1'!$C:$C,'PL1'!T:T)+SUMIFS(ADJ!V:V,ADJ!$E:$E,'RPL1'!$C9) -> 381.634 | U9: =_xlfn.XLOOKUP($C9,'PL1'!$C:$C,'PL1'!U:U)+SUMIFS(ADJ!W:W,ADJ!$E:$E,'RPL1'!$C9) -> 537.179 | V9: =_xlfn.XLOOKUP($C9,'PL1'!$C:$C,'PL1'!V:V)+SUMIFS(ADJ!X:X,ADJ!$E:$E,'RPL1'!$C9) -> 356.904 | W9: =_xlfn.XLOOKUP($C9,'PL1'!$C:$C,'PL1'!W:W)+SUMIFS(ADJ!Y:Y,ADJ!$E:$E,'RPL1'!$C9) -> 365.614 | X9: =_xlfn.XLOOKUP($C9,'PL1'!$C:$C,'PL1'!X:X)+SUMIFS(ADJ!Z:Z,ADJ!$E:$E,'RPL1'!$C9) -> 1132.402 | Y9: =_xlfn.XLOOKUP($C9,'PL1'!$C:$C,'PL1'!Y:Y)+SUMIFS(ADJ!AA:AA,ADJ!$E:$E,'RPL1'!$C9) -> 1135.1701 | Z9: =_xlfn.XLOOKUP($C9,'PL1'!$C:$C,'PL1'!Z:Z)+SUMIFS(ADJ!AB:AB,ADJ!$E:$E,'RPL1'!$C9) -> 329.65101 | AA9: =_xlfn.XLOOKUP($C9,'PL1'!$C:$C,'PL1'!AA:AA)+SUMIFS(ADJ!AC:AC,ADJ!$E:$E,'RPL1'!$C9) -> 807.929 | AB9: =_xlfn.XLOOKUP($C9,'PL1'!$C:$C,'PL1'!AB:AB)+SUMIFS(ADJ!AD:AD,ADJ!$E:$E,'RPL1'!$C9) -> 413.22601 | AC9: =_xlfn.XLOOKUP($C9,'PL1'!$C:$C,'PL1'!AC:AC)+SUMIFS(ADJ!AE:AE,ADJ!$E:$E,'RPL1'!$C9) -> 351.473 | AD9: =_xlfn.XLOOKUP($C9,'PL1'!$C:$C,'PL1'!AD:AD)+SUMIFS(ADJ!AF:AF,ADJ!$E:$E,'RPL1'!$C9) -> 543.607 | AE9: =_xlfn.XLOOKUP($C9,'PL1'!$C:$C,'PL1'!AE:AE)+SUMIFS(ADJ!AG:AG,ADJ!$E:$E,'RPL1'!$C9) -> 736.5651 | AF9: =_xlfn.XLOOKUP($C9,'PL1'!$C:$C,'PL1'!AF:AF)+SUMIFS(ADJ!AH:AH,ADJ!$E:$E,'RPL1'!$C9) -> 425.647 | AG9: =_xlfn.XLOOKUP($C9,'PL1'!$C:$C,'PL1'!AG:AG)+SUMIFS(ADJ!AI:AI,ADJ!$E:$E,'RPL1'!$C9) -> 284.19 | AH9: =_xlfn.XLOOKUP($C9,'PL1'!$C:$C,'PL1'!AH:AH)+SUMIFS(ADJ!AJ:AJ,ADJ!$E:$E,'RPL1'!$C9) -> 760.366 | AI9: =_xlfn.XLOOKUP($C9,'PL1'!$C:$C,'PL1'!AI:AI)+SUMIFS(ADJ!AK:AK,ADJ!$E:$E,'RPL1'!$C9) -> 423.188 | AK9: =SUM(E9:P9) -> 7647.4216 | AL9: =SUM(Q9:AB9) -> 6778.7512 | AM9: =SUM(X9:AI9) -> 7343.4143 | AO9: =IFERROR(AK9/AK$10%,0) -> 100 | AP9: =IFERROR(AL9/AL$10%,0) -> 100 | AQ9: =IFERROR(AM9/AM$10%,0) -> 100
C10: Net revenue | E10: =SUM(E9:E9) -> 193.127 | F10: =SUM(F9:F9) -> 429.4435 | G10: =SUM(G9:G9) -> 731.815 | H10: =SUM(H9:H9) -> 430.355 | I10: =SUM(I9:I9) -> 623.429 | J10: =SUM(J9:J9) -> 480.831 | K10: =SUM(K9:K9) -> 688.468 | L10: =SUM(L9:L9) -> 1267.3995 | ... AI10: =SUM(AI9:AI9) -> 423.188 | AK10: =SUM(AK9:AK9) -> 7647.4216 | AL10: =SUM(AL9:AL9) -> 6778.7512 | AM10: =SUM(AM9:AM9) -> 7343.4143 | AO10: =IFERROR(AK10/AK$10%,0) -> 100 | AP10: =IFERROR(AL10/AL$10%,0) -> 100 | AQ10: =IFERROR(AM10/AM$10%,0) -> 100
C12: YoY Growth (%) | E12: n/a | F12: n/a | G12: n/a | H12: n/a | I12: n/a | J12: n/a | K12: n/a | L12: n/a | M12: n/a | N12: n/a | O12: n/a | P12: n/a | Q12: =IFERROR(Q10/E10%-100,0) -> 118.53185 | R12: =IFERROR(R10/F10%-100,0) -> 22.402598 | S12: =IFERROR(S10/G10%-100,0) -> -49.256574 | T12: =IFERROR(T10/H10%-100,0) -> -11.321119 | U12: =IFERROR(U10/I10%-100,0) -> -13.834775 | V12: =IFERROR(V10/J10%-100,0) -> -25.773505 | W12: =IFERROR(W10/K10%-100,0) -> -46.894554 | X12: =IFERROR(X10/L10%-100,0) -> -10.651535 | ... AI12: =IFERROR(AI10/W10%-100,0) -> 15.747209 | AK12: n/a | AL12: =IFERROR(AL10/AK10%-100,0) -> -11.358998 | AM12: =IFERROR(AM10/SUM(L10:W10)%-100,0) -> 4.4533946
C14: Cost of goods sold | E14: 0 | F14: 0 | G14: 0 | H14: 0 | I14: 0 | J14: 0 | K14: 0 | L14: 0 | M14: 0 | N14: 0 | O14: 0 | P14: 0 | Q14: 0 | R14: 0 | S14: 0 | T14: 0 | U14: 0 | V14: 0 | W14: 0 | X14: 0 | Y14: 0 | Z14: 0 | AA14: 0 | AB14: 0 | AC14: 0 | AD14: 0 | AE14: 0 | AF14: 0 | AG14: 0 | AH14: 0 | AI14: 0 | AK14: =SUM(E14:P14) -> 0 | AL14: =SUM(Q14:AB14) -> 0 | AM14: =SUM(X14:AI14) -> 0 | AO14: =IFERROR(AK14/AK$10%,0) -> 0 | AP14: =IFERROR(AL14/AL$10%,0) -> 0 | AQ14: =IFERROR(AM14/AM$10%,0) -> 0
C15: Gross profit | E15: =E10-E14 -> 193.127 | F15: =F10-F14 -> 429.4435 | G15: =G10-G14 -> 731.815 | H15: =H10-H14 -> 430.355 | I15: =I10-I14 -> 623.429 | J15: =J10-J14 -> 480.831 | K15: =K10-K14 -> 688.468 | L15: =L10-L14 -> 1267.3995 | ... AI15: =AI10-AI14 -> 423.188 | AK15: =AK10-AK14 -> 7647.4216 | AL15: =AL10-AL14 -> 6778.7512 | AM15: =AM10-AM14 -> 7343.4143 | AO15: =IFERROR(AK15/AK$10%,0) -> 100 | AP15: =IFERROR(AL15/AL$10%,0) -> 100 | AQ15: =IFERROR(AM15/AM$10%,0) -> 100
C17: Payroll and benefits | E17: =_xlfn.XLOOKUP($C17,'PL1'!$C:$C,'PL1'!E:E)-SUMIFS(ADJ!G:G,ADJ!$E:$E,'RPL1'!$C17) -> 298.69046 | F17: =_xlfn.XLOOKUP($C17,'PL1'!$C:$C,'PL1'!F:F)-SUMIFS(ADJ!H:H,ADJ!$E:$E,'RPL1'!$C17) -> 298.48344 | G17: =_xlfn.XLOOKUP($C17,'PL1'!$C:$C,'PL1'!G:G)-SUMIFS(ADJ!I:I,ADJ!$E:$E,'RPL1'!$C17) -> 284.31467 | H17: =_xlfn.XLOOKUP($C17,'PL1'!$C:$C,'PL1'!H:H)-SUMIFS(ADJ!J:J,ADJ!$E:$E,'RPL1'!$C17) -> 276.68906 | I17: =_xlfn.XLOOKUP($C17,'PL1'!$C:$C,'PL1'!I:I)-SUMIFS(ADJ!K:K,ADJ!$E:$E,'RPL1'!$C17) -> 268.97223 | J17: =_xlfn.XLOOKUP($C17,'PL1'!$C:$C,'PL1'!J:J)-SUMIFS(ADJ!L:L,ADJ!$E:$E,'RPL1'!$C17) -> 266.65804 | K17: =_xlfn.XLOOKUP($C17,'PL1'!$C:$C,'PL1'!K:K)-SUMIFS(ADJ!M:M,ADJ!$E:$E,'RPL1'!$C17) -> 268.30101 | L17: =_xlfn.XLOOKUP($C17,'PL1'!$C:$C,'PL1'!L:L)-SUMIFS(ADJ!N:N,ADJ!$E:$E,'RPL1'!$C17) -> 266.73588 | M17: =_xlfn.XLOOKUP($C17,'PL1'!$C:$C,'PL1'!M:M)-SUMIFS(ADJ!O:O,ADJ!$E:$E,'RPL1'!$C17) -> 265.08172 | N17: =_xlfn.XLOOKUP($C17,'PL1'!$C:$C,'PL1'!N:N)-SUMIFS(ADJ!P:P,ADJ!$E:$E,'RPL1'!$C17) -> 281.37695 | O17: =_xlfn.XLOOKUP($C17,'PL1'!$C:$C,'PL1'!O:O)-SUMIFS(ADJ!Q:Q,ADJ!$E:$E,'RPL1'!$C17) -> 275.32041 | P17: =_xlfn.XLOOKUP($C17,'PL1'!$C:$C,'PL1'!P:P)-SUMIFS(ADJ!R:R,ADJ!$E:$E,'RPL1'!$C17) -> 375.49239 | Q17: =_xlfn.XLOOKUP($C17,'PL1'!$C:$C,'PL1'!Q:Q)-SUMIFS(ADJ!S:S,ADJ!$E:$E,'RPL1'!$C17) -> 271.91109 | R17: =_xlfn.XLOOKUP($C17,'PL1'!$C:$C,'PL1'!R:R)-SUMIFS(ADJ!T:T,ADJ!$E:$E,'RPL1'!$C17) -> 271.61953 | S17: =_xlfn.XLOOKUP($C17,'PL1'!$C:$C,'PL1'!S:S)-SUMIFS(ADJ!U:U,ADJ!$E:$E,'RPL1'!$C17) -> 293.90775 | T17: =_xlfn.XLOOKUP($C17,'PL1'!$C:$C,'PL1'!T:T)-SUMIFS(ADJ!V:V,ADJ!$E:$E,'RPL1'!$C17) -> 301.94597 | U17: =_xlfn.XLOOKUP($C17,'PL1'!$C:$C,'PL1'!U:U)-SUMIFS(ADJ!W:W,ADJ!$E:$E,'RPL1'!$C17) -> 296.50785 | V17: =_xlfn.XLOOKUP($C17,'PL1'!$C:$C,'PL1'!V:V)-SUMIFS(ADJ!X:X,ADJ!$E:$E,'RPL1'!$C17) -> 292.17041 | W17: =_xlfn.XLOOKUP($C17,'PL1'!$C:$C,'PL1'!W:W)-SUMIFS(ADJ!Y:Y,ADJ!$E:$E,'RPL1'!$C17) -> 290.4759 | X17: =_xlfn.XLOOKUP($C17,'PL1'!$C:$C,'PL1'!X:X)-SUMIFS(ADJ!Z:Z,ADJ!$E:$E,'RPL1'!$C17) -> 291.3456 | Y17: =_xlfn.XLOOKUP($C17,'PL1'!$C:$C,'PL1'!Y:Y)-SUMIFS(ADJ!AA:AA,ADJ!$E:$E,'RPL1'!$C17) -> 287.43833 | Z17: =_xlfn.XLOOKUP($C17,'PL1'!$C:$C,'PL1'!Z:Z)-SUMIFS(ADJ!AB:AB,ADJ!$E:$E,'RPL1'!$C17) -> -219.3722 | AA17: =_xlfn.XLOOKUP($C17,'PL1'!$C:$C,'PL1'!AA:AA)-SUMIFS(ADJ!AC:AC,ADJ!$E:$E,'RPL1'!$C17) -> 244.77622 | AB17: =_xlfn.XLOOKUP($C17,'PL1'!$C:$C,'PL1'!AB:AB)-SUMIFS(ADJ!AD:AD,ADJ!$E:$E,'RPL1'!$C17) -> 152.51136 | AC17: =_xlfn.XLOOKUP($C17,'PL1'!$C:$C,'PL1'!AC:AC)-SUMIFS(ADJ!AE:AE,ADJ!$E:$E,'RPL1'!$C17) -> 232.1368 | AD17: =_xlfn.XLOOKUP($C17,'PL1'!$C:$C,'PL1'!AD:AD)-SUMIFS(ADJ!AF:AF,ADJ!$E:$E,'RPL1'!$C17) -> 333.07219 | AE17: =_xlfn.XLOOKUP($C17,'PL1'!$C:$C,'PL1'!AE:AE)-SUMIFS(ADJ!AG:AG,ADJ!$E:$E,'RPL1'!$C17) -> 281.43373 | AF17: =_xlfn.XLOOKUP($C17,'PL1'!$C:$C,'PL1'!AF:AF)-SUMIFS(ADJ!AH:AH,ADJ!$E:$E,'RPL1'!$C17) -> 281.47455 | AG17: =_xlfn.XLOOKUP($C17,'PL1'!$C:$C,'PL1'!AG:AG)-SUMIFS(ADJ!AI:AI,ADJ!$E:$E,'RPL1'!$C17) -> 281.31166 | AH17: =_xlfn.XLOOKUP($C17,'PL1'!$C:$C,'PL1'!AH:AH)-SUMIFS(ADJ!AJ:AJ,ADJ!$E:$E,'RPL1'!$C17) -> 280.26423 | AI17: =_xlfn.XLOOKUP($C17,'PL1'!$C:$C,'PL1'!AI:AI)-SUMIFS(ADJ!AK:AK,ADJ!$E:$E,'RPL1'!$C17) -> 287.17413 | AK17: =SUM(E17:P17) -> 3426.1163 | AL17: =SUM(Q17:AB17) -> 2775.2378 | AM17: =SUM(X17:AI17) -> 2733.5666 | AO17: =IFERROR(AK17/AK$10%,0) -> 44.800933 | AP17: =IFERROR(AL17/AL$10%,0) -> 40.940252 | AQ17: =IFERROR(AM17/AM$10%,0) -> 37.224736
C18: Subcontractor expense | E18: =_xlfn.XLOOKUP($C18,'PL1'!$C:$C,'PL1'!E:E)-SUMIFS(ADJ!G:G,ADJ!$E:$E,'RPL1'!$C18) -> 137.43364 | F18: =_xlfn.XLOOKUP($C18,'PL1'!$C:$C,'PL1'!F:F)-SUMIFS(ADJ!H:H,ADJ!$E:$E,'RPL1'!$C18) -> 193.54791 | G18: =_xlfn.XLOOKUP($C18,'PL1'!$C:$C,'PL1'!G:G)-SUMIFS(ADJ!I:I,ADJ!$E:$E,'RPL1'!$C18) -> 224.92213 | H18: =_xlfn.XLOOKUP($C18,'PL1'!$C:$C,'PL1'!H:H)-SUMIFS(ADJ!J:J,ADJ!$E:$E,'RPL1'!$C18) -> 125.26819 | I18: =_xlfn.XLOOKUP($C18,'PL1'!$C:$C,'PL1'!I:I)-SUMIFS(ADJ!K:K,ADJ!$E:$E,'RPL1'!$C18) -> 176.70462 | J18: =_xlfn.XLOOKUP($C18,'PL1'!$C:$C,'PL1'!J:J)-SUMIFS(ADJ!L:L,ADJ!$E:$E,'RPL1'!$C18) -> 178.79571 | K18: =_xlfn.XLOOKUP($C18,'PL1'!$C:$C,'PL1'!K:K)-SUMIFS(ADJ!M:M,ADJ!$E:$E,'RPL1'!$C18) -> 270.18698 | L18: =_xlfn.XLOOKUP($C18,'PL1'!$C:$C,'PL1'!L:L)-SUMIFS(ADJ!N:N,ADJ!$E:$E,'RPL1'!$C18) -> 287.13071 | M18: =_xlfn.XLOOKUP($C18,'PL1'!$C:$C,'PL1'!M:M)-SUMIFS(ADJ!O:O,ADJ!$E:$E,'RPL1'!$C18) -> 147.99318 | N18: =_xlfn.XLOOKUP($C18,'PL1'!$C:$C,'PL1'!N:N)-SUMIFS(ADJ!P:P,ADJ!$E:$E,'RPL1'!$C18) -> 165.18797 | O18: =_xlfn.XLOOKUP($C18,'PL1'!$C:$C,'PL1'!O:O)-SUMIFS(ADJ!Q:Q,ADJ!$E:$E,'RPL1'!$C18) -> 337.44583 | P18: =_xlfn.XLOOKUP($C18,'PL1'!$C:$C,'PL1'!P:P)-SUMIFS(ADJ!R:R,ADJ!$E:$E,'RPL1'!$C18) -> 319.66356 | Q18: =_xlfn.XLOOKUP($C18,'PL1'!$C:$C,'PL1'!Q:Q)-SUMIFS(ADJ!S:S,ADJ!$E:$E,'RPL1'!$C18) -> 168.82725 | R18: =_xlfn.XLOOKUP($C18,'PL1'!$C:$C,'PL1'!R:R)-SUMIFS(ADJ!T:T,ADJ!$E:$E,'RPL1'!$C18) -> 120.0455 | S18: =_xlfn.XLOOKUP($C18,'PL1'!$C:$C,'PL1'!S:S)-SUMIFS(ADJ!U:U,ADJ!$E:$E,'RPL1'!$C18) -> 172.70988 | T18: =_xlfn.XLOOKUP($C18,'PL1'!$C:$C,'PL1'!T:T)-SUMIFS(ADJ!V:V,ADJ!$E:$E,'RPL1'!$C18) -> 148.45572 | U18: =_xlfn.XLOOKUP($C18,'PL1'!$C:$C,'PL1'!U:U)-SUMIFS(ADJ!W:W,ADJ!$E:$E,'RPL1'!$C18) -> 179.57611 | V18: =_xlfn.XLOOKUP($C18,'PL1'!$C:$C,'PL1'!V:V)-SUMIFS(ADJ!X:X,ADJ!$E:$E,'RPL1'!$C18) -> 152.01988 | W18: =_xlfn.XLOOKUP($C18,'PL1'!$C:$C,'PL1'!W:W)-SUMIFS(ADJ!Y:Y,ADJ!$E:$E,'RPL1'!$C18) -> 223.98869 | X18: =_xlfn.XLOOKUP($C18,'PL1'!$C:$C,'PL1'!X:X)-SUMIFS(ADJ!Z:Z,ADJ!$E:$E,'RPL1'!$C18) -> 213.07865 | Y18: =_xlfn.XLOOKUP($C18,'PL1'!$C:$C,'PL1'!Y:Y)-SUMIFS(ADJ!AA:AA,ADJ!$E:$E,'RPL1'!$C18) -> 202.70499 | Z18: =_xlfn.XLOOKUP($C18,'PL1'!$C:$C,'PL1'!Z:Z)-SUMIFS(ADJ!AB:AB,ADJ!$E:$E,'RPL1'!$C18) -> 285.08553 | AA18: =_xlfn.XLOOKUP($C18,'PL1'!$C:$C,'PL1'!AA:AA)-SUMIFS(ADJ!AC:AC,ADJ!$E:$E,'RPL1'!$C18) -> 114.44835 | AB18: =_xlfn.XLOOKUP($C18,'PL1'!$C:$C,'PL1'!AB:AB)-SUMIFS(ADJ!AD:AD,ADJ!$E:$E,'RPL1'!$C18) -> 188.95704 | AC18: =_xlfn.XLOOKUP($C18,'PL1'!$C:$C,'PL1'!AC:AC)-SUMIFS(ADJ!AE:AE,ADJ!$E:$E,'RPL1'!$C18) -> 199.86529 | AD18: =_xlfn.XLOOKUP($C18,'PL1'!$C:$C,'PL1'!AD:AD)-SUMIFS(ADJ!AF:AF,ADJ!$E:$E,'RPL1'!$C18) -> 178.72288 | AE18: =_xlfn.XLOOKUP($C18,'PL1'!$C:$C,'PL1'!AE:AE)-SUMIFS(ADJ!AG:AG,ADJ!$E:$E,'RPL1'!$C18) -> 266.13393 | AF18: =_xlfn.XLOOKUP($C18,'PL1'!$C:$C,'PL1'!AF:AF)-SUMIFS(ADJ!AH:AH,ADJ!$E:$E,'RPL1'!$C18) -> 115.1346 | AG18: =_xlfn.XLOOKUP($C18,'PL1'!$C:$C,'PL1'!AG:AG)-SUMIFS(ADJ!AI:AI,ADJ!$E:$E,'RPL1'!$C18) -> 207.44051 | AH18: =_xlfn.XLOOKUP($C18,'PL1'!$C:$C,'PL1'!AH:AH)-SUMIFS(ADJ!AJ:AJ,ADJ!$E:$E,'RPL1'!$C18) -> 184.72747 | AI18: =_xlfn.XLOOKUP($C18,'PL1'!$C:$C,'PL1'!AI:AI)-SUMIFS(ADJ!AK:AK,ADJ!$E:$E,'RPL1'!$C18) -> 191.75563 | AK18: =SUM(E18:P18) -> 2564.2804 | AL18: =SUM(Q18:AB18) -> 2169.8976 | AM18: =SUM(X18:AI18) -> 2348.0549 | AO18: =IFERROR(AK18/AK$10%,0) -> 33.531307 | AP18: =IFERROR(AL18/AL$10%,0) -> 32.010285 | AQ18: =IFERROR(AM18/AM$10%,0) -> 31.974975
C19: Insurance expenses | E19: =_xlfn.XLOOKUP($C19,'PL1'!$C:$C,'PL1'!E:E)-SUMIFS(ADJ!G:G,ADJ!$E:$E,'RPL1'!$C19) -> 38.03793 | F19: =_xlfn.XLOOKUP($C19,'PL1'!$C:$C,'PL1'!F:F)-SUMIFS(ADJ!H:H,ADJ!$E:$E,'RPL1'!$C19) -> 29.35666 | G19: =_xlfn.XLOOKUP($C19,'PL1'!$C:$C,'PL1'!G:G)-SUMIFS(ADJ!I:I,ADJ!$E:$E,'RPL1'!$C19) -> 34.11322 | H19: =_xlfn.XLOOKUP($C19,'PL1'!$C:$C,'PL1'!H:H)-SUMIFS(ADJ!J:J,ADJ!$E:$E,'RPL1'!$C19) -> 41.28279 | I19: =_xlfn.XLOOKUP($C19,'PL1'!$C:$C,'PL1'!I:I)-SUMIFS(ADJ!K:K,ADJ!$E:$E,'RPL1'!$C19) -> 58.56752 | J19: =_xlfn.XLOOKUP($C19,'PL1'!$C:$C,'PL1'!J:J)-SUMIFS(ADJ!L:L,ADJ!$E:$E,'RPL1'!$C19) -> 39.98386 | K19: =_xlfn.XLOOKUP($C19,'PL1'!$C:$C,'PL1'!K:K)-SUMIFS(ADJ!M:M,ADJ!$E:$E,'RPL1'!$C19) -> 22.85944 | L19: =_xlfn.XLOOKUP($C19,'PL1'!$C:$C,'PL1'!L:L)-SUMIFS(ADJ!N:N,ADJ!$E:$E,'RPL1'!$C19) -> 25.82988 | M19: =_xlfn.XLOOKUP($C19,'PL1'!$C:$C,'PL1'!M:M)-SUMIFS(ADJ!O:O,ADJ!$E:$E,'RPL1'!$C19) -> 29.66964 | N19: =_xlfn.XLOOKUP($C19,'PL1'!$C:$C,'PL1'!N:N)-SUMIFS(ADJ!P:P,ADJ!$E:$E,'RPL1'!$C19) -> 23.20154 | O19: =_xlfn.XLOOKUP($C19,'PL1'!$C:$C,'PL1'!O:O)-SUMIFS(ADJ!Q:Q,ADJ!$E:$E,'RPL1'!$C19) -> 29.62384 | P19: =_xlfn.XLOOKUP($C19,'PL1'!$C:$C,'PL1'!P:P)-SUMIFS(ADJ!R:R,ADJ!$E:$E,'RPL1'!$C19) -> -98.05435 | Q19: =_xlfn.XLOOKUP($C19,'PL1'!$C:$C,'PL1'!Q:Q)-SUMIFS(ADJ!S:S,ADJ!$E:$E,'RPL1'!$C19) -> 30.08207 | R19: =_xlfn.XLOOKUP($C19,'PL1'!$C:$C,'PL1'!R:R)-SUMIFS(ADJ!T:T,ADJ!$E:$E,'RPL1'!$C19) -> 28.76204 | S19: =_xlfn.XLOOKUP($C19,'PL1'!$C:$C,'PL1'!S:S)-SUMIFS(ADJ!U:U,ADJ!$E:$E,'RPL1'!$C19) -> 29.71568 | T19: =_xlfn.XLOOKUP($C19,'PL1'!$C:$C,'PL1'!T:T)-SUMIFS(ADJ!V:V,ADJ!$E:$E,'RPL1'!$C19) -> 21.52508 | U19: =_xlfn.XLOOKUP($C19,'PL1'!$C:$C,'PL1'!U:U)-SUMIFS(ADJ!W:W,ADJ!$E:$E,'RPL1'!$C19) -> 35.72831 | V19: =_xlfn.XLOOKUP($C19,'PL1'!$C:$C,'PL1'!V:V)-SUMIFS(ADJ!X:X,ADJ!$E:$E,'RPL1'!$C19) -> 2.27021 | W19: =_xlfn.XLOOKUP($C19,'PL1'!$C:$C,'PL1'!W:W)-SUMIFS(ADJ!Y:Y,ADJ!$E:$E,'RPL1'!$C19) -> 1.37946 | X19: =_xlfn.XLOOKUP($C19,'PL1'!$C:$C,'PL1'!X:X)-SUMIFS(ADJ!Z:Z,ADJ!$E:$E,'RPL1'!$C19) -> 1.37946 | Y19: =_xlfn.XLOOKUP($C19,'PL1'!$C:$C,'PL1'!Y:Y)-SUMIFS(ADJ!AA:AA,ADJ!$E:$E,'RPL1'!$C19) -> 2.27021 | Z19: =_xlfn.XLOOKUP($C19,'PL1'!$C:$C,'PL1'!Z:Z)-SUMIFS(ADJ!AB:AB,ADJ!$E:$E,'RPL1'!$C19) -> 5.12946 | AA19: =_xlfn.XLOOKUP($C19,'PL1'!$C:$C,'PL1'!AA:AA)-SUMIFS(ADJ!AC:AC,ADJ!$E:$E,'RPL1'!$C19) -> 3.87946 | AB19: =_xlfn.XLOOKUP($C19,'PL1'!$C:$C,'PL1'!AB:AB)-SUMIFS(ADJ!AD:AD,ADJ!$E:$E,'RPL1'!$C19) -> 161.87645 | AC19: =_xlfn.XLOOKUP($C19,'PL1'!$C:$C,'PL1'!AC:AC)-SUMIFS(ADJ!AE:AE,ADJ!$E:$E,'RPL1'!$C19) -> 1.37946 | AD19: =_xlfn.XLOOKUP($C19,'PL1'!$C:$C,'PL1'!AD:AD)-SUMIFS(ADJ!AF:AF,ADJ!$E:$E,'RPL1'!$C19) -> 1.37946 | AE19: =_xlfn.XLOOKUP($C19,'PL1'!$C:$C,'PL1'!AE:AE)-SUMIFS(ADJ!AG:AG,ADJ!$E:$E,'RPL1'!$C19) -> 1.37946 | AF19: =_xlfn.XLOOKUP($C19,'PL1'!$C:$C,'PL1'!AF:AF)-SUMIFS(ADJ!AH:AH,ADJ!$E:$E,'RPL1'!$C19) -> 19.41746 | AG19: =_xlfn.XLOOKUP($C19,'PL1'!$C:$C,'PL1'!AG:AG)-SUMIFS(ADJ!AI:AI,ADJ!$E:$E,'RPL1'!$C19) -> 1.37946 | AH19: =_xlfn.XLOOKUP($C19,'PL1'!$C:$C,'PL1'!AH:AH)-SUMIFS(ADJ!AJ:AJ,ADJ!$E:$E,'RPL1'!$C19) -> 32.10602 | AI19: =_xlfn.XLOOKUP($C19,'PL1'!$C:$C,'PL1'!AI:AI)-SUMIFS(ADJ!AK:AK,ADJ!$E:$E,'RPL1'!$C19) -> 4.77156 | AK19: =SUM(E19:P19) -> 274.47197 | AL19: =SUM(Q19:AB19) -> 323.99789 | AM19: =SUM(X19:AI19) -> 236.34792 | AO19: =IFERROR(AK19/AK$10%,0) -> 3.5890786 | AP19: =IFERROR(AL19/AL$10%,0) -> 4.7796103 | AQ19: =IFERROR(AM19/AM$10%,0) -> 3.2185018
C20: Professional fees | E20: =_xlfn.XLOOKUP($C20,'PL1'!$C:$C,'PL1'!E:E)-SUMIFS(ADJ!G:G,ADJ!$E:$E,'RPL1'!$C20) -> 8.555 | F20: =_xlfn.XLOOKUP($C20,'PL1'!$C:$C,'PL1'!F:F)-SUMIFS(ADJ!H:H,ADJ!$E:$E,'RPL1'!$C20) -> 7.6875 | G20: =_xlfn.XLOOKUP($C20,'PL1'!$C:$C,'PL1'!G:G)-SUMIFS(ADJ!I:I,ADJ!$E:$E,'RPL1'!$C20) -> 5.6 | H20: =_xlfn.XLOOKUP($C20,'PL1'!$C:$C,'PL1'!H:H)-SUMIFS(ADJ!J:J,ADJ!$E:$E,'RPL1'!$C20) -> 11.74 | I20: =_xlfn.XLOOKUP($C20,'PL1'!$C:$C,'PL1'!I:I)-SUMIFS(ADJ!K:K,ADJ!$E:$E,'RPL1'!$C20) -> 0 | J20: =_xlfn.XLOOKUP($C20,'PL1'!$C:$C,'PL1'!J:J)-SUMIFS(ADJ!L:L,ADJ!$E:$E,'RPL1'!$C20) -> 15.34 | K20: =_xlfn.XLOOKUP($C20,'PL1'!$C:$C,'PL1'!K:K)-SUMIFS(ADJ!M:M,ADJ!$E:$E,'RPL1'!$C20) -> 9.9475 | L20: =_xlfn.XLOOKUP($C20,'PL1'!$C:$C,'PL1'!L:L)-SUMIFS(ADJ!N:N,ADJ!$E:$E,'RPL1'!$C20) -> 8 | M20: =_xlfn.XLOOKUP($C20,'PL1'!$C:$C,'PL1'!M:M)-SUMIFS(ADJ!O:O,ADJ!$E:$E,'RPL1'!$C20) -> 8.565 | N20: =_xlfn.XLOOKUP($C20,'PL1'!$C:$C,'PL1'!N:N)-SUMIFS(ADJ!P:P,ADJ!$E:$E,'RPL1'!$C20) -> 8 | O20: =_xlfn.XLOOKUP($C20,'PL1'!$C:$C,'PL1'!O:O)-SUMIFS(ADJ!Q:Q,ADJ!$E:$E,'RPL1'!$C20) -> 11.02 | P20: =_xlfn.XLOOKUP($C20,'PL1'!$C:$C,'PL1'!P:P)-SUMIFS(ADJ!R:R,ADJ!$E:$E,'RPL1'!$C20) -> 8.895 | Q20: =_xlfn.XLOOKUP($C20,'PL1'!$C:$C,'PL1'!Q:Q)-SUMIFS(ADJ!S:S,ADJ!$E:$E,'RPL1'!$C20) -> 9.63307 | R20: =_xlfn.XLOOKUP($C20,'PL1'!$C:$C,'PL1'!R:R)-SUMIFS(ADJ!T:T,ADJ!$E:$E,'RPL1'!$C20) -> 8 | S20: =_xlfn.XLOOKUP($C20,'PL1'!$C:$C,'PL1'!S:S)-SUMIFS(ADJ!U:U,ADJ!$E:$E,'RPL1'!$C20) -> 14.865 | T20: =_xlfn.XLOOKUP($C20,'PL1'!$C:$C,'PL1'!T:T)-SUMIFS(ADJ!V:V,ADJ!$E:$E,'RPL1'!$C20) -> 18.3315 | U20: =_xlfn.XLOOKUP($C20,'PL1'!$C:$C,'PL1'!U:U)-SUMIFS(ADJ!W:W,ADJ!$E:$E,'RPL1'!$C20) -> 0 | V20: =_xlfn.XLOOKUP($C20,'PL1'!$C:$C,'PL1'!V:V)-SUMIFS(ADJ!X:X,ADJ!$E:$E,'RPL1'!$C20) -> 10.4 | W20: =_xlfn.XLOOKUP($C20,'PL1'!$C:$C,'PL1'!W:W)-SUMIFS(ADJ!Y:Y,ADJ!$E:$E,'RPL1'!$C20) -> 11.395 | X20: =_xlfn.XLOOKUP($C20,'PL1'!$C:$C,'PL1'!X:X)-SUMIFS(ADJ!Z:Z,ADJ!$E:$E,'RPL1'!$C20) -> 15.605 | Y20: =_xlfn.XLOOKUP($C20,'PL1'!$C:$C,'PL1'!Y:Y)-SUMIFS(ADJ!AA:AA,ADJ!$E:$E,'RPL1'!$C20) -> 15.5445 | Z20: =_xlfn.XLOOKUP($C20,'PL1'!$C:$C,'PL1'!Z:Z)-SUMIFS(ADJ!AB:AB,ADJ!$E:$E,'RPL1'!$C20) -> 8.75 | AA20: =_xlfn.XLOOKUP($C20,'PL1'!$C:$C,'PL1'!AA:AA)-SUMIFS(ADJ!AC:AC,ADJ!$E:$E,'RPL1'!$C20) -> 30.472 | AB20: =_xlfn.XLOOKUP($C20,'PL1'!$C:$C,'PL1'!AB:AB)-SUMIFS(ADJ!AD:AD,ADJ!$E:$E,'RPL1'!$C20) -> 10.5485 | AC20: =_xlfn.XLOOKUP($C20,'PL1'!$C:$C,'PL1'!AC:AC)-SUMIFS(ADJ!AE:AE,ADJ!$E:$E,'RPL1'!$C20) -> 11.5333 | AD20: =_xlfn.XLOOKUP($C20,'PL1'!$C:$C,'PL1'!AD:AD)-SUMIFS(ADJ!AF:AF,ADJ!$E:$E,'RPL1'!$C20) -> 11.735 | AE20: =_xlfn.XLOOKUP($C20,'PL1'!$C:$C,'PL1'!AE:AE)-SUMIFS(ADJ!AG:AG,ADJ!$E:$E,'RPL1'!$C20) -> 8.2 | AF20: =_xlfn.XLOOKUP($C20,'PL1'!$C:$C,'PL1'!AF:AF)-SUMIFS(ADJ!AH:AH,ADJ!$E:$E,'RPL1'!$C20) -> 18.68 | AG20: =_xlfn.XLOOKUP($C20,'PL1'!$C:$C,'PL1'!AG:AG)-SUMIFS(ADJ!AI:AI,ADJ!$E:$E,'RPL1'!$C20) -> 8 | AH20: =_xlfn.XLOOKUP($C20,'PL1'!$C:$C,'PL1'!AH:AH)-SUMIFS(ADJ!AJ:AJ,ADJ!$E:$E,'RPL1'!$C20) -> 16.975 | AI20: =_xlfn.XLOOKUP($C20,'PL1'!$C:$C,'PL1'!AI:AI)-SUMIFS(ADJ!AK:AK,ADJ!$E:$E,'RPL1'!$C20) -> 30.6465 | AK20: =SUM(E20:P20) -> 103.35 | AL20: =SUM(Q20:AB20) -> 153.54457 | AM20: =SUM(X20:AI20) -> 186.6898 | AO20: =IFERROR(AK20/AK$10%,0) -> 1.3514359 | AP20: =IFERROR(AL20/AL$10%,0) -> 2.2650864 | AQ20: =IFERROR(AM20/AM$10%,0) -> 2.5422752
C21: Other operating expenses | E21: =_xlfn.XLOOKUP($C21,'PL1'!$C:$C,'PL1'!E:E)-SUMIFS(ADJ!G:G,ADJ!$E:$E,'RPL1'!$C21) -> 17.17885 | F21: =_xlfn.XLOOKUP($C21,'PL1'!$C:$C,'PL1'!F:F)-SUMIFS(ADJ!H:H,ADJ!$E:$E,'RPL1'!$C21) -> 3.84806 | G21: =_xlfn.XLOOKUP($C21,'PL1'!$C:$C,'PL1'!G:G)-SUMIFS(ADJ!I:I,ADJ!$E:$E,'RPL1'!$C21) -> 14.08236 | H21: =_xlfn.XLOOKUP($C21,'PL1'!$C:$C,'PL1'!H:H)-SUMIFS(ADJ!J:J,ADJ!$E:$E,'RPL1'!$C21) -> 9.39415 | I21: =_xlfn.XLOOKUP($C21,'PL1'!$C:$C,'PL1'!I:I)-SUMIFS(ADJ!K:K,ADJ!$E:$E,'RPL1'!$C21) -> 8.24328 | J21: =_xlfn.XLOOKUP($C21,'PL1'!$C:$C,'PL1'!J:J)-SUMIFS(ADJ!L:L,ADJ!$E:$E,'RPL1'!$C21) -> 15.33891 | K21: =_xlfn.XLOOKUP($C21,'PL1'!$C:$C,'PL1'!K:K)-SUMIFS(ADJ!M:M,ADJ!$E:$E,'RPL1'!$C21) -> 8.81472 | L21: =_xlfn.XLOOKUP($C21,'PL1'!$C:$C,'PL1'!L:L)-SUMIFS(ADJ!N:N,ADJ!$E:$E,'RPL1'!$C21) -> 4.33986 | M21: =_xlfn.XLOOKUP($C21,'PL1'!$C:$C,'PL1'!M:M)-SUMIFS(ADJ!O:O,ADJ!$E:$E,'RPL1'!$C21) -> 8.56791 | N21: =_xlfn.XLOOKUP($C21,'PL1'!$C:$C,'PL1'!N:N)-SUMIFS(ADJ!P:P,ADJ!$E:$E,'RPL1'!$C21) -> 6.50756 | O21: =_xlfn.XLOOKUP($C21,'PL1'!$C:$C,'PL1'!O:O)-SUMIFS(ADJ!Q:Q,ADJ!$E:$E,'RPL1'!$C21) -> 5.84441 | P21: =_xlfn.XLOOKUP($C21,'PL1'!$C:$C,'PL1'!P:P)-SUMIFS(ADJ!R:R,ADJ!$E:$E,'RPL1'!$C21) -> 11.80133 | Q21: =_xlfn.XLOOKUP($C21,'PL1'!$C:$C,'PL1'!Q:Q)-SUMIFS(ADJ!S:S,ADJ!$E:$E,'RPL1'!$C21) -> 14.06012 | R21: =_xlfn.XLOOKUP($C21,'PL1'!$C:$C,'PL1'!R:R)-SUMIFS(ADJ!T:T,ADJ!$E:$E,'RPL1'!$C21) -> 9.06727 | S21: =_xlfn.XLOOKUP($C21,'PL1'!$C:$C,'PL1'!S:S)-SUMIFS(ADJ!U:U,ADJ!$E:$E,'RPL1'!$C21) -> 7.78589 | T21: =_xlfn.XLOOKUP($C21,'PL1'!$C:$C,'PL1'!T:T)-SUMIFS(ADJ!V:V,ADJ!$E:$E,'RPL1'!$C21) -> 4.29555 | U21: =_xlfn.XLOOKUP($C21,'PL1'!$C:$C,'PL1'!U:U)-SUMIFS(ADJ!W:W,ADJ!$E:$E,'RPL1'!$C21) -> 8.93703 | V21: =_xlfn.XLOOKUP($C21,'PL1'!$C:$C,'PL1'!V:V)-SUMIFS(ADJ!X:X,ADJ!$E:$E,'RPL1'!$C21) -> 11.02111 | W21: =_xlfn.XLOOKUP($C21,'PL1'!$C:$C,'PL1'!W:W)-SUMIFS(ADJ!Y:Y,ADJ!$E:$E,'RPL1'!$C21) -> 6.69698 | X21: =_xlfn.XLOOKUP($C21,'PL1'!$C:$C,'PL1'!X:X)-SUMIFS(ADJ!Z:Z,ADJ!$E:$E,'RPL1'!$C21) -> 4.26963 | Y21: =_xlfn.XLOOKUP($C21,'PL1'!$C:$C,'PL1'!Y:Y)-SUMIFS(ADJ!AA:AA,ADJ!$E:$E,'RPL1'!$C21) -> 9.7357 | Z21: =_xlfn.XLOOKUP($C21,'PL1'!$C:$C,'PL1'!Z:Z)-SUMIFS(ADJ!AB:AB,ADJ!$E:$E,'RPL1'!$C21) -> 7.30678 | AA21: =_xlfn.XLOOKUP($C21,'PL1'!$C:$C,'PL1'!AA:AA)-SUMIFS(ADJ!AC:AC,ADJ!$E:$E,'RPL1'!$C21) -> 8.49059 | AB21: =_xlfn.XLOOKUP($C21,'PL1'!$C:$C,'PL1'!AB:AB)-SUMIFS(ADJ!AD:AD,ADJ!$E:$E,'RPL1'!$C21) -> 11.91501 | AC21: =_xlfn.XLOOKUP($C21,'PL1'!$C:$C,'PL1'!AC:AC)-SUMIFS(ADJ!AE:AE,ADJ!$E:$E,'RPL1'!$C21) -> 6.7009 | AD21: =_xlfn.XLOOKUP($C21,'PL1'!$C:$C,'PL1'!AD:AD)-SUMIFS(ADJ!AF:AF,ADJ!$E:$E,'RPL1'!$C21) -> 12.54305 | AE21: =_xlfn.XLOOKUP($C21,'PL1'!$C:$C,'PL1'!AE:AE)-SUMIFS(ADJ!AG:AG,ADJ!$E:$E,'RPL1'!$C21) -> 8.95995 | AF21: =_xlfn.XLOOKUP($C21,'PL1'!$C:$C,'PL1'!AF:AF)-SUMIFS(ADJ!AH:AH,ADJ!$E:$E,'RPL1'!$C21) -> 10.2829 | AG21: =_xlfn.XLOOKUP($C21,'PL1'!$C:$C,'PL1'!AG:AG)-SUMIFS(ADJ!AI:AI,ADJ!$E:$E,'RPL1'!$C21) -> 9.99205 | AH21: =_xlfn.XLOOKUP($C21,'PL1'!$C:$C,'PL1'!AH:AH)-SUMIFS(ADJ!AJ:AJ,ADJ!$E:$E,'RPL1'!$C21) -> 10.18761 | AI21: =_xlfn.XLOOKUP($C21,'PL1'!$C:$C,'PL1'!AI:AI)-SUMIFS(ADJ!AK:AK,ADJ!$E:$E,'RPL1'!$C21) -> 10.79615 | AK21: =SUM(E21:P21) -> 113.9614 | AL21: =SUM(Q21:AB21) -> 103.58166 | AM21: =SUM(X21:AI21) -> 111.18032 | AO21: =IFERROR(AK21/AK$10%,0) -> 1.4901938 | AP21: =IFERROR(AL21/AL$10%,0) -> 1.5280346 | AQ21: =IFERROR(AM21/AM$10%,0) -> 1.514014
C22: Travel, meals, and entertainment | E22: =_xlfn.XLOOKUP($C22,'PL1'!$C:$C,'PL1'!E:E)-SUMIFS(ADJ!G:G,ADJ!$E:$E,'RPL1'!$C22) -> 1.7244 | F22: =_xlfn.XLOOKUP($C22,'PL1'!$C:$C,'PL1'!F:F)-SUMIFS(ADJ!H:H,ADJ!$E:$E,'RPL1'!$C22) -> 3.10804 | G22: =_xlfn.XLOOKUP($C22,'PL1'!$C:$C,'PL1'!G:G)-SUMIFS(ADJ!I:I,ADJ!$E:$E,'RPL1'!$C22) -> 4.45087 | H22: =_xlfn.XLOOKUP($C22,'PL1'!$C:$C,'PL1'!H:H)-SUMIFS(ADJ!J:J,ADJ!$E:$E,'RPL1'!$C22) -> 2.62126 | I22: =_xlfn.XLOOKUP($C22,'PL1'!$C:$C,'PL1'!I:I)-SUMIFS(ADJ!K:K,ADJ!$E:$E,'RPL1'!$C22) -> 2.08538 | J22: =_xlfn.XLOOKUP($C22,'PL1'!$C:$C,'PL1'!J:J)-SUMIFS(ADJ!L:L,ADJ!$E:$E,'RPL1'!$C22) -> 2.66488 | K22: =_xlfn.XLOOKUP($C22,'PL1'!$C:$C,'PL1'!K:K)-SUMIFS(ADJ!M:M,ADJ!$E:$E,'RPL1'!$C22) -> 0.81089 | L22: =_xlfn.XLOOKUP($C22,'PL1'!$C:$C,'PL1'!L:L)-SUMIFS(ADJ!N:N,ADJ!$E:$E,'RPL1'!$C22) -> 0.89428 | M22: =_xlfn.XLOOKUP($C22,'PL1'!$C:$C,'PL1'!M:M)-SUMIFS(ADJ!O:O,ADJ!$E:$E,'RPL1'!$C22) -> 0.164 | N22: =_xlfn.XLOOKUP($C22,'PL1'!$C:$C,'PL1'!N:N)-SUMIFS(ADJ!P:P,ADJ!$E:$E,'RPL1'!$C22) -> 0.12366 | O22: =_xlfn.XLOOKUP($C22,'PL1'!$C:$C,'PL1'!O:O)-SUMIFS(ADJ!Q:Q,ADJ!$E:$E,'RPL1'!$C22) -> 0.5617 | P22: =_xlfn.XLOOKUP($C22,'PL1'!$C:$C,'PL1'!P:P)-SUMIFS(ADJ!R:R,ADJ!$E:$E,'RPL1'!$C22) -> 4.15851 | Q22: =_xlfn.XLOOKUP($C22,'PL1'!$C:$C,'PL1'!Q:Q)-SUMIFS(ADJ!S:S,ADJ!$E:$E,'RPL1'!$C22) -> 4.18701 | R22: =_xlfn.XLOOKUP($C22,'PL1'!$C:$C,'PL1'!R:R)-SUMIFS(ADJ!T:T,ADJ!$E:$E,'RPL1'!$C22) -> 3.82491 | S22: =_xlfn.XLOOKUP($C22,'PL1'!$C:$C,'PL1'!S:S)-SUMIFS(ADJ!U:U,ADJ!$E:$E,'RPL1'!$C22) -> 1.39135 | T22: =_xlfn.XLOOKUP($C22,'PL1'!$C:$C,'PL1'!T:T)-SUMIFS(ADJ!V:V,ADJ!$E:$E,'RPL1'!$C22) -> 0.99821 | U22: =_xlfn.XLOOKUP($C22,'PL1'!$C:$C,'PL1'!U:U)-SUMIFS(ADJ!W:W,ADJ!$E:$E,'RPL1'!$C22) -> 1.34516 | V22: =_xlfn.XLOOKUP($C22,'PL1'!$C:$C,'PL1'!V:V)-SUMIFS(ADJ!X:X,ADJ!$E:$E,'RPL1'!$C22) -> 1.8914 | W22: =_xlfn.XLOOKUP($C22,'PL1'!$C:$C,'PL1'!W:W)-SUMIFS(ADJ!Y:Y,ADJ!$E:$E,'RPL1'!$C22) -> 0.36012 | X22: =_xlfn.XLOOKUP($C22,'PL1'!$C:$C,'PL1'!X:X)-SUMIFS(ADJ!Z:Z,ADJ!$E:$E,'RPL1'!$C22) -> 0 | Y22: =_xlfn.XLOOKUP($C22,'PL1'!$C:$C,'PL1'!Y:Y)-SUMIFS(ADJ!AA:AA,ADJ!$E:$E,'RPL1'!$C22) -> 0.04273 | Z22: =_xlfn.XLOOKUP($C22,'PL1'!$C:$C,'PL1'!Z:Z)-SUMIFS(ADJ!AB:AB,ADJ!$E:$E,'RPL1'!$C22) -> 1.09359 | AA22: =_xlfn.XLOOKUP($C22,'PL1'!$C:$C,'PL1'!AA:AA)-SUMIFS(ADJ!AC:AC,ADJ!$E:$E,'RPL1'!$C22) -> 4.18668 | AB22: =_xlfn.XLOOKUP($C22,'PL1'!$C:$C,'PL1'!AB:AB)-SUMIFS(ADJ!AD:AD,ADJ!$E:$E,'RPL1'!$C22) -> 1.12317 | AC22: =_xlfn.XLOOKUP($C22,'PL1'!$C:$C,'PL1'!AC:AC)-SUMIFS(ADJ!AE:AE,ADJ!$E:$E,'RPL1'!$C22) -> 4.84297 | AD22: =_xlfn.XLOOKUP($C22,'PL1'!$C:$C,'PL1'!AD:AD)-SUMIFS(ADJ!AF:AF,ADJ!$E:$E,'RPL1'!$C22) -> 2.33461 | AE22: =_xlfn.XLOOKUP($C22,'PL1'!$C:$C,'PL1'!AE:AE)-SUMIFS(ADJ!AG:AG,ADJ!$E:$E,'RPL1'!$C22) -> 4.28287 | AF22: =_xlfn.XLOOKUP($C22,'PL1'!$C:$C,'PL1'!AF:AF)-SUMIFS(ADJ!AH:AH,ADJ!$E:$E,'RPL1'!$C22) -> 3.13152 | AG22: =_xlfn.XLOOKUP($C22,'PL1'!$C:$C,'PL1'!AG:AG)-SUMIFS(ADJ!AI:AI,ADJ!$E:$E,'RPL1'!$C22) -> 8.85938 | AH22: =_xlfn.XLOOKUP($C22,'PL1'!$C:$C,'PL1'!AH:AH)-SUMIFS(ADJ!AJ:AJ,ADJ!$E:$E,'RPL1'!$C22) -> 0.91452 | AI22: =_xlfn.XLOOKUP($C22,'PL1'!$C:$C,'PL1'!AI:AI)-SUMIFS(ADJ!AK:AK,ADJ!$E:$E,'RPL1'!$C22) -> 0.25565 | AK22: =SUM(E22:P22) -> 23.36787 | AL22: =SUM(Q22:AB22) -> 20.44433 | AM22: =SUM(X22:AI22) -> 31.06769 | AO22: =IFERROR(AK22/AK$10%,0) -> 0.30556534 | AP22: =IFERROR(AL22/AL$10%,0) -> 0.30159434 | AQ22: =IFERROR(AM22/AM$10%,0) -> 0.42306874
C23: Operating expenses | E23: =SUM(E17:E22) -> 501.62028 | F23: =SUM(F17:F22) -> 536.03161 | G23: =SUM(G17:G22) -> 567.48325 | H23: =SUM(H17:H22) -> 466.99545 | I23: =SUM(I17:I22) -> 514.57303 | J23: =SUM(J17:J22) -> 518.7814 | K23: =SUM(K17:K22) -> 580.92054 | L23: =SUM(L17:L22) -> 592.93061 | ... AI23: =SUM(AI17:AI22) -> 525.39962 | AK23: =SUM(AK17:AK22) -> 6505.5479 | AL23: =SUM(AL17:AL22) -> 5546.7039 | AM23: =SUM(AM17:AM22) -> 5646.9072 | AO23: =IFERROR(AK23/AK$10%,0) -> 85.068514 | AP23: =IFERROR(AL23/AL$10%,0) -> 81.824863 | AQ23: =IFERROR(AM23/AM$10%,0) -> 76.897571
C24: Operating profit | E24: =E15-E23 -> -308.49328 | F24: =F15-F23 -> -106.58811 | G24: =G15-G23 -> 164.33175 | H24: =H15-H23 -> -36.64045 | I24: =I15-I23 -> 108.85597 | J24: =J15-J23 -> -37.9504 | K24: =K15-K23 -> 107.54746 | L24: =L15-L23 -> 674.46889 | ... AI24: =AI15-AI23 -> -102.21162 | AK24: =AK15-AK23 -> 1141.8737 | AL24: =AL15-AL23 -> 1232.0473 | AM24: =AM15-AM23 -> 1696.5071 | AO24: =IFERROR(AK24/AK$10%,0) -> 14.931486 | AP24: =IFERROR(AL24/AL$10%,0) -> 18.175137 | AQ24: =IFERROR(AM24/AM$10%,0) -> 23.102429
C26: Income taxes | E26: =_xlfn.XLOOKUP($C26,'PL1'!$C:$C,'PL1'!E:E)-SUMIFS(ADJ!G:G,ADJ!$E:$E,'RPL1'!$C26) -> 0 | F26: =_xlfn.XLOOKUP($C26,'PL1'!$C:$C,'PL1'!F:F)-SUMIFS(ADJ!H:H,ADJ!$E:$E,'RPL1'!$C26) -> 0 | G26: =_xlfn.XLOOKUP($C26,'PL1'!$C:$C,'PL1'!G:G)-SUMIFS(ADJ!I:I,ADJ!$E:$E,'RPL1'!$C26) -> 0 | H26: =_xlfn.XLOOKUP($C26,'PL1'!$C:$C,'PL1'!H:H)-SUMIFS(ADJ!J:J,ADJ!$E:$E,'RPL1'!$C26) -> 0 | I26: =_xlfn.XLOOKUP($C26,'PL1'!$C:$C,'PL1'!I:I)-SUMIFS(ADJ!K:K,ADJ!$E:$E,'RPL1'!$C26) -> 0 | J26: =_xlfn.XLOOKUP($C26,'PL1'!$C:$C,'PL1'!J:J)-SUMIFS(ADJ!L:L,ADJ!$E:$E,'RPL1'!$C26) -> 0 | K26: =_xlfn.XLOOKUP($C26,'PL1'!$C:$C,'PL1'!K:K)-SUMIFS(ADJ!M:M,ADJ!$E:$E,'RPL1'!$C26) -> 0 | L26: =_xlfn.XLOOKUP($C26,'PL1'!$C:$C,'PL1'!L:L)-SUMIFS(ADJ!N:N,ADJ!$E:$E,'RPL1'!$C26) -> 0 | M26: =_xlfn.XLOOKUP($C26,'PL1'!$C:$C,'PL1'!M:M)-SUMIFS(ADJ!O:O,ADJ!$E:$E,'RPL1'!$C26) -> 0 | N26: =_xlfn.XLOOKUP($C26,'PL1'!$C:$C,'PL1'!N:N)-SUMIFS(ADJ!P:P,ADJ!$E:$E,'RPL1'!$C26) -> 0 | O26: =_xlfn.XLOOKUP($C26,'PL1'!$C:$C,'PL1'!O:O)-SUMIFS(ADJ!Q:Q,ADJ!$E:$E,'RPL1'!$C26) -> 0 | P26: =_xlfn.XLOOKUP($C26,'PL1'!$C:$C,'PL1'!P:P)-SUMIFS(ADJ!R:R,ADJ!$E:$E,'RPL1'!$C26) -> 0 | Q26: =_xlfn.XLOOKUP($C26,'PL1'!$C:$C,'PL1'!Q:Q)-SUMIFS(ADJ!S:S,ADJ!$E:$E,'RPL1'!$C26) -> 0 | R26: =_xlfn.XLOOKUP($C26,'PL1'!$C:$C,'PL1'!R:R)-SUMIFS(ADJ!T:T,ADJ!$E:$E,'RPL1'!$C26) -> 0 | S26: =_xlfn.XLOOKUP($C26,'PL1'!$C:$C,'PL1'!S:S)-SUMIFS(ADJ!U:U,ADJ!$E:$E,'RPL1'!$C26) -> 0 | T26: =_xlfn.XLOOKUP($C26,'PL1'!$C:$C,'PL1'!T:T)-SUMIFS(ADJ!V:V,ADJ!$E:$E,'RPL1'!$C26) -> 0 | U26: =_xlfn.XLOOKUP($C26,'PL1'!$C:$C,'PL1'!U:U)-SUMIFS(ADJ!W:W,ADJ!$E:$E,'RPL1'!$C26) -> 0 | V26: =_xlfn.XLOOKUP($C26,'PL1'!$C:$C,'PL1'!V:V)-SUMIFS(ADJ!X:X,ADJ!$E:$E,'RPL1'!$C26) -> 0 | W26: =_xlfn.XLOOKUP($C26,'PL1'!$C:$C,'PL1'!W:W)-SUMIFS(ADJ!Y:Y,ADJ!$E:$E,'RPL1'!$C26) -> 0 | X26: =_xlfn.XLOOKUP($C26,'PL1'!$C:$C,'PL1'!X:X)-SUMIFS(ADJ!Z:Z,ADJ!$E:$E,'RPL1'!$C26) -> 0 | Y26: =_xlfn.XLOOKUP($C26,'PL1'!$C:$C,'PL1'!Y:Y)-SUMIFS(ADJ!AA:AA,ADJ!$E:$E,'RPL1'!$C26) -> 0 | Z26: =_xlfn.XLOOKUP($C26,'PL1'!$C:$C,'PL1'!Z:Z)-SUMIFS(ADJ!AB:AB,ADJ!$E:$E,'RPL1'!$C26) -> 0 | AA26: =_xlfn.XLOOKUP($C26,'PL1'!$C:$C,'PL1'!AA:AA)-SUMIFS(ADJ!AC:AC,ADJ!$E:$E,'RPL1'!$C26) -> 0 | AB26: =_xlfn.XLOOKUP($C26,'PL1'!$C:$C,'PL1'!AB:AB)-SUMIFS(ADJ!AD:AD,ADJ!$E:$E,'RPL1'!$C26) -> 0 | AC26: =_xlfn.XLOOKUP($C26,'PL1'!$C:$C,'PL1'!AC:AC)-SUMIFS(ADJ!AE:AE,ADJ!$E:$E,'RPL1'!$C26) -> 0 | AD26: =_xlfn.XLOOKUP($C26,'PL1'!$C:$C,'PL1'!AD:AD)-SUMIFS(ADJ!AF:AF,ADJ!$E:$E,'RPL1'!$C26) -> 0 | AE26: =_xlfn.XLOOKUP($C26,'PL1'!$C:$C,'PL1'!AE:AE)-SUMIFS(ADJ!AG:AG,ADJ!$E:$E,'RPL1'!$C26) -> 0 | AF26: =_xlfn.XLOOKUP($C26,'PL1'!$C:$C,'PL1'!AF:AF)-SUMIFS(ADJ!AH:AH,ADJ!$E:$E,'RPL1'!$C26) -> 0 | AG26: =_xlfn.XLOOKUP($C26,'PL1'!$C:$C,'PL1'!AG:AG)-SUMIFS(ADJ!AI:AI,ADJ!$E:$E,'RPL1'!$C26) -> 0 | AH26: =_xlfn.XLOOKUP($C26,'PL1'!$C:$C,'PL1'!AH:AH)-SUMIFS(ADJ!AJ:AJ,ADJ!$E:$E,'RPL1'!$C26) -> 0 | AI26: =_xlfn.XLOOKUP($C26,'PL1'!$C:$C,'PL1'!AI:AI)-SUMIFS(ADJ!AK:AK,ADJ!$E:$E,'RPL1'!$C26) -> 0 | AK26: =SUM(E26:P26) -> 0 | AL26: =SUM(Q26:AB26) -> 0 | AM26: =SUM(X26:AI26) -> 0 | AO26: =IFERROR(AK26/AK$10%,0) -> 0 | AP26: =IFERROR(AL26/AL$10%,0) -> 0 | AQ26: =IFERROR(AM26/AM$10%,0) -> 0
C27: Depreciation and amortization | E27: =_xlfn.XLOOKUP($C27,'PL1'!$C:$C,'PL1'!E:E)-SUMIFS(ADJ!G:G,ADJ!$E:$E,'RPL1'!$C27) -> 0 | F27: =_xlfn.XLOOKUP($C27,'PL1'!$C:$C,'PL1'!F:F)-SUMIFS(ADJ!H:H,ADJ!$E:$E,'RPL1'!$C27) -> 0 | G27: =_xlfn.XLOOKUP($C27,'PL1'!$C:$C,'PL1'!G:G)-SUMIFS(ADJ!I:I,ADJ!$E:$E,'RPL1'!$C27) -> 0 | H27: =_xlfn.XLOOKUP($C27,'PL1'!$C:$C,'PL1'!H:H)-SUMIFS(ADJ!J:J,ADJ!$E:$E,'RPL1'!$C27) -> 0 | I27: =_xlfn.XLOOKUP($C27,'PL1'!$C:$C,'PL1'!I:I)-SUMIFS(ADJ!K:K,ADJ!$E:$E,'RPL1'!$C27) -> 0 | J27: =_xlfn.XLOOKUP($C27,'PL1'!$C:$C,'PL1'!J:J)-SUMIFS(ADJ!L:L,ADJ!$E:$E,'RPL1'!$C27) -> 0 | K27: =_xlfn.XLOOKUP($C27,'PL1'!$C:$C,'PL1'!K:K)-SUMIFS(ADJ!M:M,ADJ!$E:$E,'RPL1'!$C27) -> 0 | L27: =_xlfn.XLOOKUP($C27,'PL1'!$C:$C,'PL1'!L:L)-SUMIFS(ADJ!N:N,ADJ!$E:$E,'RPL1'!$C27) -> 0 | M27: =_xlfn.XLOOKUP($C27,'PL1'!$C:$C,'PL1'!M:M)-SUMIFS(ADJ!O:O,ADJ!$E:$E,'RPL1'!$C27) -> 0 | N27: =_xlfn.XLOOKUP($C27,'PL1'!$C:$C,'PL1'!N:N)-SUMIFS(ADJ!P:P,ADJ!$E:$E,'RPL1'!$C27) -> 0 | O27: =_xlfn.XLOOKUP($C27,'PL1'!$C:$C,'PL1'!O:O)-SUMIFS(ADJ!Q:Q,ADJ!$E:$E,'RPL1'!$C27) -> 0 | P27: =_xlfn.XLOOKUP($C27,'PL1'!$C:$C,'PL1'!P:P)-SUMIFS(ADJ!R:R,ADJ!$E:$E,'RPL1'!$C27) -> 0 | Q27: =_xlfn.XLOOKUP($C27,'PL1'!$C:$C,'PL1'!Q:Q)-SUMIFS(ADJ!S:S,ADJ!$E:$E,'RPL1'!$C27) -> 0 | R27: =_xlfn.XLOOKUP($C27,'PL1'!$C:$C,'PL1'!R:R)-SUMIFS(ADJ!T:T,ADJ!$E:$E,'RPL1'!$C27) -> 0 | S27: =_xlfn.XLOOKUP($C27,'PL1'!$C:$C,'PL1'!S:S)-SUMIFS(ADJ!U:U,ADJ!$E:$E,'RPL1'!$C27) -> 0 | T27: =_xlfn.XLOOKUP($C27,'PL1'!$C:$C,'PL1'!T:T)-SUMIFS(ADJ!V:V,ADJ!$E:$E,'RPL1'!$C27) -> 0 | U27: =_xlfn.XLOOKUP($C27,'PL1'!$C:$C,'PL1'!U:U)-SUMIFS(ADJ!W:W,ADJ!$E:$E,'RPL1'!$C27) -> 0 | V27: =_xlfn.XLOOKUP($C27,'PL1'!$C:$C,'PL1'!V:V)-SUMIFS(ADJ!X:X,ADJ!$E:$E,'RPL1'!$C27) -> 0 | W27: =_xlfn.XLOOKUP($C27,'PL1'!$C:$C,'PL1'!W:W)-SUMIFS(ADJ!Y:Y,ADJ!$E:$E,'RPL1'!$C27) -> 0 | X27: =_xlfn.XLOOKUP($C27,'PL1'!$C:$C,'PL1'!X:X)-SUMIFS(ADJ!Z:Z,ADJ!$E:$E,'RPL1'!$C27) -> 0 | Y27: =_xlfn.XLOOKUP($C27,'PL1'!$C:$C,'PL1'!Y:Y)-SUMIFS(ADJ!AA:AA,ADJ!$E:$E,'RPL1'!$C27) -> 0 | Z27: =_xlfn.XLOOKUP($C27,'PL1'!$C:$C,'PL1'!Z:Z)-SUMIFS(ADJ!AB:AB,ADJ!$E:$E,'RPL1'!$C27) -> 0 | AA27: =_xlfn.XLOOKUP($C27,'PL1'!$C:$C,'PL1'!AA:AA)-SUMIFS(ADJ!AC:AC,ADJ!$E:$E,'RPL1'!$C27) -> 0 | AB27: =_xlfn.XLOOKUP($C27,'PL1'!$C:$C,'PL1'!AB:AB)-SUMIFS(ADJ!AD:AD,ADJ!$E:$E,'RPL1'!$C27) -> 0 | AC27: =_xlfn.XLOOKUP($C27,'PL1'!$C:$C,'PL1'!AC:AC)-SUMIFS(ADJ!AE:AE,ADJ!$E:$E,'RPL1'!$C27) -> 0 | AD27: =_xlfn.XLOOKUP($C27,'PL1'!$C:$C,'PL1'!AD:AD)-SUMIFS(ADJ!AF:AF,ADJ!$E:$E,'RPL1'!$C27) -> 0 | AE27: =_xlfn.XLOOKUP($C27,'PL1'!$C:$C,'PL1'!AE:AE)-SUMIFS(ADJ!AG:AG,ADJ!$E:$E,'RPL1'!$C27) -> 0 | AF27: =_xlfn.XLOOKUP($C27,'PL1'!$C:$C,'PL1'!AF:AF)-SUMIFS(ADJ!AH:AH,ADJ!$E:$E,'RPL1'!$C27) -> 0 | AG27: =_xlfn.XLOOKUP($C27,'PL1'!$C:$C,'PL1'!AG:AG)-SUMIFS(ADJ!AI:AI,ADJ!$E:$E,'RPL1'!$C27) -> 0 | AH27: =_xlfn.XLOOKUP($C27,'PL1'!$C:$C,'PL1'!AH:AH)-SUMIFS(ADJ!AJ:AJ,ADJ!$E:$E,'RPL1'!$C27) -> 0 | AI27: =_xlfn.XLOOKUP($C27,'PL1'!$C:$C,'PL1'!AI:AI)-SUMIFS(ADJ!AK:AK,ADJ!$E:$E,'RPL1'!$C27) -> 0 | AK27: =SUM(E27:P27) -> 0 | AL27: =SUM(Q27:AB27) -> 0 | AM27: =SUM(X27:AI27) -> 0 | AO27: =IFERROR(AK27/AK$10%,0) -> 0 | AP27: =IFERROR(AL27/AL$10%,0) -> 0 | AQ27: =IFERROR(AM27/AM$10%,0) -> 0
C28: Other non-operating expenses / (income) | E28: =_xlfn.XLOOKUP($C28,'PL1'!$C:$C,'PL1'!E:E)-SUMIFS(ADJ!G:G,ADJ!$E:$E,'RPL1'!$C28) -> 0.4 | F28: =_xlfn.XLOOKUP($C28,'PL1'!$C:$C,'PL1'!F:F)-SUMIFS(ADJ!H:H,ADJ!$E:$E,'RPL1'!$C28) -> 0.4 | G28: =_xlfn.XLOOKUP($C28,'PL1'!$C:$C,'PL1'!G:G)-SUMIFS(ADJ!I:I,ADJ!$E:$E,'RPL1'!$C28) -> 0.4 | H28: =_xlfn.XLOOKUP($C28,'PL1'!$C:$C,'PL1'!H:H)-SUMIFS(ADJ!J:J,ADJ!$E:$E,'RPL1'!$C28) -> -355.14435 | I28: =_xlfn.XLOOKUP($C28,'PL1'!$C:$C,'PL1'!I:I)-SUMIFS(ADJ!K:K,ADJ!$E:$E,'RPL1'!$C28) -> 0.4 | J28: =_xlfn.XLOOKUP($C28,'PL1'!$C:$C,'PL1'!J:J)-SUMIFS(ADJ!L:L,ADJ!$E:$E,'RPL1'!$C28) -> -2 | K28: =_xlfn.XLOOKUP($C28,'PL1'!$C:$C,'PL1'!K:K)-SUMIFS(ADJ!M:M,ADJ!$E:$E,'RPL1'!$C28) -> 0 | L28: =_xlfn.XLOOKUP($C28,'PL1'!$C:$C,'PL1'!L:L)-SUMIFS(ADJ!N:N,ADJ!$E:$E,'RPL1'!$C28) -> 0.1 | M28: =_xlfn.XLOOKUP($C28,'PL1'!$C:$C,'PL1'!M:M)-SUMIFS(ADJ!O:O,ADJ!$E:$E,'RPL1'!$C28) -> 0 | N28: =_xlfn.XLOOKUP($C28,'PL1'!$C:$C,'PL1'!N:N)-SUMIFS(ADJ!P:P,ADJ!$E:$E,'RPL1'!$C28) -> 0 | O28: =_xlfn.XLOOKUP($C28,'PL1'!$C:$C,'PL1'!O:O)-SUMIFS(ADJ!Q:Q,ADJ!$E:$E,'RPL1'!$C28) -> 0 | P28: =_xlfn.XLOOKUP($C28,'PL1'!$C:$C,'PL1'!P:P)-SUMIFS(ADJ!R:R,ADJ!$E:$E,'RPL1'!$C28) -> -76.4 | Q28: =_xlfn.XLOOKUP($C28,'PL1'!$C:$C,'PL1'!Q:Q)-SUMIFS(ADJ!S:S,ADJ!$E:$E,'RPL1'!$C28) -> 0 | R28: =_xlfn.XLOOKUP($C28,'PL1'!$C:$C,'PL1'!R:R)-SUMIFS(ADJ!T:T,ADJ!$E:$E,'RPL1'!$C28) -> 0 | S28: =_xlfn.XLOOKUP($C28,'PL1'!$C:$C,'PL1'!S:S)-SUMIFS(ADJ!U:U,ADJ!$E:$E,'RPL1'!$C28) -> 0 | T28: =_xlfn.XLOOKUP($C28,'PL1'!$C:$C,'PL1'!T:T)-SUMIFS(ADJ!V:V,ADJ!$E:$E,'RPL1'!$C28) -> 0 | U28: =_xlfn.XLOOKUP($C28,'PL1'!$C:$C,'PL1'!U:U)-SUMIFS(ADJ!W:W,ADJ!$E:$E,'RPL1'!$C28) -> 0 | V28: =_xlfn.XLOOKUP($C28,'PL1'!$C:$C,'PL1'!V:V)-SUMIFS(ADJ!X:X,ADJ!$E:$E,'RPL1'!$C28) -> 0 | W28: =_xlfn.XLOOKUP($C28,'PL1'!$C:$C,'PL1'!W:W)-SUMIFS(ADJ!Y:Y,ADJ!$E:$E,'RPL1'!$C28) -> 0 | X28: =_xlfn.XLOOKUP($C28,'PL1'!$C:$C,'PL1'!X:X)-SUMIFS(ADJ!Z:Z,ADJ!$E:$E,'RPL1'!$C28) -> -50 | Y28: =_xlfn.XLOOKUP($C28,'PL1'!$C:$C,'PL1'!Y:Y)-SUMIFS(ADJ!AA:AA,ADJ!$E:$E,'RPL1'!$C28) -> -2.26402 | Z28: =_xlfn.XLOOKUP($C28,'PL1'!$C:$C,'PL1'!Z:Z)-SUMIFS(ADJ!AB:AB,ADJ!$E:$E,'RPL1'!$C28) -> 0 | AA28: =_xlfn.XLOOKUP($C28,'PL1'!$C:$C,'PL1'!AA:AA)-SUMIFS(ADJ!AC:AC,ADJ!$E:$E,'RPL1'!$C28) -> 0 | AB28: =_xlfn.XLOOKUP($C28,'PL1'!$C:$C,'PL1'!AB:AB)-SUMIFS(ADJ!AD:AD,ADJ!$E:$E,'RPL1'!$C28) -> 0 | AC28: =_xlfn.XLOOKUP($C28,'PL1'!$C:$C,'PL1'!AC:AC)-SUMIFS(ADJ!AE:AE,ADJ!$E:$E,'RPL1'!$C28) -> 0 | AD28: =_xlfn.XLOOKUP($C28,'PL1'!$C:$C,'PL1'!AD:AD)-SUMIFS(ADJ!AF:AF,ADJ!$E:$E,'RPL1'!$C28) -> 0 | AE28: =_xlfn.XLOOKUP($C28,'PL1'!$C:$C,'PL1'!AE:AE)-SUMIFS(ADJ!AG:AG,ADJ!$E:$E,'RPL1'!$C28) -> 0 | AF28: =_xlfn.XLOOKUP($C28,'PL1'!$C:$C,'PL1'!AF:AF)-SUMIFS(ADJ!AH:AH,ADJ!$E:$E,'RPL1'!$C28) -> 0 | AG28: =_xlfn.XLOOKUP($C28,'PL1'!$C:$C,'PL1'!AG:AG)-SUMIFS(ADJ!AI:AI,ADJ!$E:$E,'RPL1'!$C28) -> 0 | AH28: =_xlfn.XLOOKUP($C28,'PL1'!$C:$C,'PL1'!AH:AH)-SUMIFS(ADJ!AJ:AJ,ADJ!$E:$E,'RPL1'!$C28) -> 0 | AI28: =_xlfn.XLOOKUP($C28,'PL1'!$C:$C,'PL1'!AI:AI)-SUMIFS(ADJ!AK:AK,ADJ!$E:$E,'RPL1'!$C28) -> 0.10556 | AK28: =SUM(E28:P28) -> -431.84435 | AL28: =SUM(Q28:AB28) -> -52.26402 | AM28: =SUM(X28:AI28) -> -52.15846 | AO28: =IFERROR(AK28/AK$10%,0) -> -5.6469275 | AP28: =IFERROR(AL28/AL$10%,0) -> -0.77099777 | AQ28: =IFERROR(AM28/AM$10%,0) -> -0.71027533
C29: Non-operating expenses / (income) | E29: =SUM(E26:E28) -> 0.4 | F29: =SUM(F26:F28) -> 0.4 | G29: =SUM(G26:G28) -> 0.4 | H29: =SUM(H26:H28) -> -355.14435 | I29: =SUM(I26:I28) -> 0.4 | J29: =SUM(J26:J28) -> -2 | K29: =SUM(K26:K28) -> 0 | L29: =SUM(L26:L28) -> 0.1 | ... AI29: =SUM(AI26:AI28) -> 0.10556 | AK29: =SUM(AK26:AK28) -> -431.84435 | AL29: =SUM(AL26:AL28) -> -52.26402 | AM29: =SUM(AM26:AM28) -> -52.15846 | AO29: =IFERROR(AK29/AK$10%,0) -> -5.6469275 | AP29: =IFERROR(AL29/AL$10%,0) -> -0.77099777 | AQ29: =IFERROR(AM29/AM$10%,0) -> -0.71027533
C30: Adjusted EBITDA | E30: =E24-E29 -> -308.89328 | F30: =F24-F29 -> -106.98811 | G30: =G24-G29 -> 163.93175 | H30: =H24-H29 -> 318.5039 | I30: =I24-I29 -> 108.45597 | J30: =J24-J29 -> -35.9504 | K30: =K24-K29 -> 107.54746 | L30: =L24-L29 -> 674.36889 | ... AI30: =AI24-AI29 -> -102.31718 | AK30: =AK24-AK29 -> 1573.718 | AL30: =AL24-AL29 -> 1284.3113 | AM30: =AM24-AM29 -> 1748.6655 | AO30: =IFERROR(AK30/AK$10%,0) -> 20.578413 | AP30: =IFERROR(AL30/AL$10%,0) -> 18.946135 | AQ30: =IFERROR(AM30/AM$10%,0) -> 23.812704
C32: Gross margin, adjusted (%) | E32: =IFERROR(E15/E$10%,0) -> 100 | F32: =IFERROR(F15/F$10%,0) -> 100 | G32: =IFERROR(G15/G$10%,0) -> 100 | H32: =IFERROR(H15/H$10%,0) -> 100 | I32: =IFERROR(I15/I$10%,0) -> 100 | J32: =IFERROR(J15/J$10%,0) -> 100 | K32: =IFERROR(K15/K$10%,0) -> 100 | L32: =IFERROR(L15/L$10%,0) -> 100 | ... AI32: =IFERROR(AI15/AI$10%,0) -> 100 | AK32: =IFERROR(AK15/AK$10%,0) -> 100 | AL32: =IFERROR(AL15/AL$10%,0) -> 100 | AM32: =IFERROR(AM15/AM$10%,0) -> 100
C33: Operating margin, adjusted (%) | E33: =IFERROR(E24/E$10%,0) -> -159.73597 | F33: =IFERROR(F24/F$10%,0) -> -24.820054 | G33: =IFERROR(G24/G$10%,0) -> 22.455368 | H33: =IFERROR(H24/H$10%,0) -> -8.5140059 | I33: =IFERROR(I24/I$10%,0) -> 17.460845 | J33: =IFERROR(J24/J$10%,0) -> -7.8926691 | K33: =IFERROR(K24/K$10%,0) -> 15.621272 | L33: =IFERROR(L24/L$10%,0) -> 53.216755 | ... AI33: =IFERROR(AI24/AI$10%,0) -> -24.152769 | AK33: =IFERROR(AK24/AK$10%,0) -> 14.931486 | AL33: =IFERROR(AL24/AL$10%,0) -> 18.175137 | AM33: =IFERROR(AM24/AM$10%,0) -> 23.102429
C34: EBITDA margin, adjusted (%) | E34: =IFERROR(E30/E$10%,0) -> -159.94308 | F34: =IFERROR(F30/F$10%,0) -> -24.913198 | G34: =IFERROR(G30/G$10%,0) -> 22.400709 | H34: =IFERROR(H30/H$10%,0) -> 74.009573 | I34: =IFERROR(I30/I$10%,0) -> 17.396684 | J34: =IFERROR(J30/J$10%,0) -> -7.4767226 | K34: =IFERROR(K30/K$10%,0) -> 15.621272 | L34: =IFERROR(L30/L$10%,0) -> 53.208865 | ... AI34: =IFERROR(AI30/AI$10%,0) -> -24.177713 | AK34: =IFERROR(AK30/AK$10%,0) -> 20.578413 | AL34: =IFERROR(AL30/AL$10%,0) -> 18.946135 | AM34: =IFERROR(AM30/AM$10%,0) -> 23.812704
C37: Check QE1 | E37: =+'QE1'!E51-E30 -> 0 | F37: =+'QE1'!F51-F30 -> 0 | G37: =+'QE1'!G51-G30 -> 0 | H37: =+'QE1'!H51-H30 -> 0 | I37: =+'QE1'!I51-I30 -> 0 | J37: =+'QE1'!J51-J30 -> 0 | K37: =+'QE1'!K51-K30 -> 0 | L37: =+'QE1'!L51-L30 -> 0 | ... AI37: =+'QE1'!AI51-AI30 -> 0 | AK37: =+'QE1'!AK51-AK30 -> 0 | AL37: =+'QE1'!AL51-AL30 -> 0 | AM37: =+'QE1'!AM51-AM30 -> 0
C40: Adjusted EBITDA Bridge
C41: FY24 EBITDA | D41: =AK30 -> 1573.718
C42: Gross profit | D42: =AL15-AK15 -> -868.67044
C43: Opex | D43: =AK23-AL23 -> 958.84408
C44: NOE/I | D44: =AK29-AL29 -> -379.58033
C45: FY25 EBITDA | D45: =SUM(D41:D44) -> 1284.3113
C46: Gross profit | D46: =AM15-AL15 -> 564.6631
C47: Opex | D47: =AL23-AM23 -> -100.20335
C48: NOE/I | D48: =AL29-AM29 -> -0.10556
C49: TTM26 EBITDA | D49: =SUM(D45:D48) -> 1748.6655 | E49: =D49-AM30 -> 0

Sheet RPL2
A1: =IF(ROUND(SUM(E31:X35),1)<>0,"NO","Yes") -> Yes | C1: Project X
A2: =IF(COUNTIF(E31:X35,">0.5")+COUNTIF(E31:X35,"<-0.5")<1,"Yes","No") -> Yes | C2: CLIENT
A3: =2-COUNTIF(A1:A2,"Yes") -> 0 | C3: ($ in 000s)
C4: Reported to Adjusted Bridge
I6: Management | J6: Management | K6: Management | M6: Diligence | N6: Diligence | O6: Diligence | Q6: Pro Forma | R6: Pro Forma | S6: Pro Forma
C7: =C4 -> Reported to Adjusted Bridge | E7: Reported Earnings | I7: Management adjustments | M7: Diligence adjustments | Q7: Pro Forma adjustments | U7: Adjusted Earnings
C8: =C3 -> ($ in 000s) | D8: Ref | E8: ='PL1'!AK8 -> FY24 | F8: ='PL1'!AL8 -> FY25 | G8: ='PL1'!AM8 -> TTM26 | I8: =E8 -> FY24 | J8: =F8 -> FY25 | K8: =G8 -> TTM26 | M8: =E8 -> FY24 | N8: =F8 -> FY25 | O8: =G8 -> TTM26 | Q8: =E8 -> FY24 | R8: =F8 -> FY25 | S8: =G8 -> TTM26 | U8: =E8 -> FY24 | V8: =F8 -> FY25 | W8: =G8 -> TTM26
C9: Service revenue | E9: =_xlfn.XLOOKUP($C9,'PL1'!$C:$C,'PL1'!AK:AK) -> 7647.4216 | F9: =_xlfn.XLOOKUP($C9,'PL1'!$C:$C,'PL1'!AL:AL) -> 6778.7512 | G9: =_xlfn.XLOOKUP($C9,'PL1'!$C:$C,'PL1'!AM:AM) -> 7343.4143 | I9: =SUMIFS(ADJ!$AM:$AM,ADJ!$E:$E,'RPL2'!$C9,ADJ!$D:$D,'RPL2'!I$6) -> 0 | J9: =SUMIFS(ADJ!$AN:$AN,ADJ!$E:$E,'RPL2'!$C9,ADJ!$D:$D,'RPL2'!J$6) -> 0 | K9: =SUMIFS(ADJ!$AO:$AO,ADJ!$E:$E,'RPL2'!$C9,ADJ!$D:$D,'RPL2'!K$6) -> 0 | M9: =SUMIFS(ADJ!$AM:$AM,ADJ!$E:$E,'RPL2'!$C9,ADJ!$D:$D,'RPL2'!M$6) -> 0 | N9: =SUMIFS(ADJ!$AN:$AN,ADJ!$E:$E,'RPL2'!$C9,ADJ!$D:$D,'RPL2'!N$6) -> 0 | O9: =SUMIFS(ADJ!$AO:$AO,ADJ!$E:$E,'RPL2'!$C9,ADJ!$D:$D,'RPL2'!O$6) -> 0 | Q9: =SUMIFS(ADJ!$AM:$AM,ADJ!$E:$E,'RPL2'!$C9,ADJ!$D:$D,'RPL2'!Q$6) -> 0 | R9: =SUMIFS(ADJ!$AN:$AN,ADJ!$E:$E,'RPL2'!$C9,ADJ!$D:$D,'RPL2'!R$6) -> 0 | S9: =SUMIFS(ADJ!$AO:$AO,ADJ!$E:$E,'RPL2'!$C9,ADJ!$D:$D,'RPL2'!S$6) -> 0 | U9: =E9+I9+M9+Q9 -> 7647.4216 | V9: =F9+J9+N9+R9 -> 6778.7512 | W9: =G9+K9+O9+S9 -> 7343.4143
C10: Net revenue | E10: =SUM(E9:E9) -> 7647.4216 | F10: =SUM(F9:F9) -> 6778.7512 | G10: =SUM(G9:G9) -> 7343.4143 | I10: =SUM(I9:I9) -> 0 | J10: =SUM(J9:J9) -> 0 | K10: =SUM(K9:K9) -> 0 | M10: =SUM(M9:M9) -> 0 | N10: =SUM(N9:N9) -> 0 | O10: =SUM(O9:O9) -> 0 | Q10: =SUM(Q9:Q9) -> 0 | R10: =SUM(R9:R9) -> 0 | S10: =SUM(S9:S9) -> 0 | U10: =SUM(U9:U9) -> 7647.4216 | V10: =SUM(V9:V9) -> 6778.7512 | W10: =SUM(W9:W9) -> 7343.4143
C12: Cost of goods sold | E12: 0 | F12: 0 | G12: 0 | I12: 0 | J12: 0 | K12: 0 | M12: 0 | N12: 0 | O12: 0 | Q12: 0 | R12: 0 | S12: 0 | U12: =E12+I12+M12+Q12 -> 0 | V12: =F12+J12+N12+R12 -> 0 | W12: =G12+K12+O12+S12 -> 0
C13: Gross profit | E13: =E10-E12 -> 7647.4216 | F13: =F10-F12 -> 6778.7512 | G13: =G10-G12 -> 7343.4143 | I13: =I10-I12 -> 0 | J13: =J10-J12 -> 0 | K13: =K10-K12 -> 0 | M13: =M10-M12 -> 0 | N13: =N10-N12 -> 0 | O13: =O10-O12 -> 0 | Q13: =Q10-Q12 -> 0 | R13: =R10-R12 -> 0 | S13: =S10-S12 -> 0 | U13: =U10-U12 -> 7647.4216 | V13: =V10-V12 -> 6778.7512 | W13: =W10-W12 -> 7343.4143
C15: Payroll and benefits | E15: =_xlfn.XLOOKUP($C15,'PL1'!$C:$C,'PL1'!AK:AK) -> 3426.1163 | F15: =_xlfn.XLOOKUP($C15,'PL1'!$C:$C,'PL1'!AL:AL) -> 2775.2378 | G15: =_xlfn.XLOOKUP($C15,'PL1'!$C:$C,'PL1'!AM:AM) -> 2733.5666 | I15: =-SUMIFS(ADJ!$AM:$AM,ADJ!$E:$E,'RPL2'!$C15,ADJ!$D:$D,'RPL2'!I$6) -> 0 | J15: =-SUMIFS(ADJ!$AN:$AN,ADJ!$E:$E,'RPL2'!$C15,ADJ!$D:$D,'RPL2'!J$6) -> 0 | K15: =-SUMIFS(ADJ!$AO:$AO,ADJ!$E:$E,'RPL2'!$C15,ADJ!$D:$D,'RPL2'!K$6) -> 0 | M15: =-SUMIFS(ADJ!$AM:$AM,ADJ!$E:$E,'RPL2'!$C15,ADJ!$D:$D,'RPL2'!M$6) -> 0 | N15: =-SUMIFS(ADJ!$AN:$AN,ADJ!$E:$E,'RPL2'!$C15,ADJ!$D:$D,'RPL2'!N$6) -> 0 | O15: =-SUMIFS(ADJ!$AO:$AO,ADJ!$E:$E,'RPL2'!$C15,ADJ!$D:$D,'RPL2'!O$6) -> 0 | Q15: =-SUMIFS(ADJ!$AM:$AM,ADJ!$E:$E,'RPL2'!$C15,ADJ!$D:$D,'RPL2'!Q$6) -> 0 | R15: =-SUMIFS(ADJ!$AN:$AN,ADJ!$E:$E,'RPL2'!$C15,ADJ!$D:$D,'RPL2'!R$6) -> 0 | S15: =-SUMIFS(ADJ!$AO:$AO,ADJ!$E:$E,'RPL2'!$C15,ADJ!$D:$D,'RPL2'!S$6) -> 0 | U15: =E15+I15+M15+Q15 -> 3426.1163 | V15: =F15+J15+N15+R15 -> 2775.2378 | W15: =G15+K15+O15+S15 -> 2733.5666
C16: Subcontractor expense | E16: =_xlfn.XLOOKUP($C16,'PL1'!$C:$C,'PL1'!AK:AK) -> 2564.2804 | F16: =_xlfn.XLOOKUP($C16,'PL1'!$C:$C,'PL1'!AL:AL) -> 2169.8976 | G16: =_xlfn.XLOOKUP($C16,'PL1'!$C:$C,'PL1'!AM:AM) -> 2348.0549 | I16: =-SUMIFS(ADJ!$AM:$AM,ADJ!$E:$E,'RPL2'!$C16,ADJ!$D:$D,'RPL2'!I$6) -> 0 | J16: =-SUMIFS(ADJ!$AN:$AN,ADJ!$E:$E,'RPL2'!$C16,ADJ!$D:$D,'RPL2'!J$6) -> 0 | K16: =-SUMIFS(ADJ!$AO:$AO,ADJ!$E:$E,'RPL2'!$C16,ADJ!$D:$D,'RPL2'!K$6) -> 0 | M16: =-SUMIFS(ADJ!$AM:$AM,ADJ!$E:$E,'RPL2'!$C16,ADJ!$D:$D,'RPL2'!M$6) -> 0 | N16: =-SUMIFS(ADJ!$AN:$AN,ADJ!$E:$E,'RPL2'!$C16,ADJ!$D:$D,'RPL2'!N$6) -> 0 | O16: =-SUMIFS(ADJ!$AO:$AO,ADJ!$E:$E,'RPL2'!$C16,ADJ!$D:$D,'RPL2'!O$6) -> 0 | Q16: =-SUMIFS(ADJ!$AM:$AM,ADJ!$E:$E,'RPL2'!$C16,ADJ!$D:$D,'RPL2'!Q$6) -> 0 | R16: =-SUMIFS(ADJ!$AN:$AN,ADJ!$E:$E,'RPL2'!$C16,ADJ!$D:$D,'RPL2'!R$6) -> 0 | S16: =-SUMIFS(ADJ!$AO:$AO,ADJ!$E:$E,'RPL2'!$C16,ADJ!$D:$D,'RPL2'!S$6) -> 0 | U16: =E16+I16+M16+Q16 -> 2564.2804 | V16: =F16+J16+N16+R16 -> 2169.8976 | W16: =G16+K16+O16+S16 -> 2348.0549
C17: Insurance expenses | E17: =_xlfn.XLOOKUP($C17,'PL1'!$C:$C,'PL1'!AK:AK) -> 274.47197 | F17: =_xlfn.XLOOKUP($C17,'PL1'!$C:$C,'PL1'!AL:AL) -> 323.99789 | G17: =_xlfn.XLOOKUP($C17,'PL1'!$C:$C,'PL1'!AM:AM) -> 236.34792 | I17: =-SUMIFS(ADJ!$AM:$AM,ADJ!$E:$E,'RPL2'!$C17,ADJ!$D:$D,'RPL2'!I$6) -> 0 | J17: =-SUMIFS(ADJ!$AN:$AN,ADJ!$E:$E,'RPL2'!$C17,ADJ!$D:$D,'RPL2'!J$6) -> 0 | K17: =-SUMIFS(ADJ!$AO:$AO,ADJ!$E:$E,'RPL2'!$C17,ADJ!$D:$D,'RPL2'!K$6) -> 0 | M17: =-SUMIFS(ADJ!$AM:$AM,ADJ!$E:$E,'RPL2'!$C17,ADJ!$D:$D,'RPL2'!M$6) -> 0 | N17: =-SUMIFS(ADJ!$AN:$AN,ADJ!$E:$E,'RPL2'!$C17,ADJ!$D:$D,'RPL2'!N$6) -> 0 | O17: =-SUMIFS(ADJ!$AO:$AO,ADJ!$E:$E,'RPL2'!$C17,ADJ!$D:$D,'RPL2'!O$6) -> 0 | Q17: =-SUMIFS(ADJ!$AM:$AM,ADJ!$E:$E,'RPL2'!$C17,ADJ!$D:$D,'RPL2'!Q$6) -> 0 | R17: =-SUMIFS(ADJ!$AN:$AN,ADJ!$E:$E,'RPL2'!$C17,ADJ!$D:$D,'RPL2'!R$6) -> 0 | S17: =-SUMIFS(ADJ!$AO:$AO,ADJ!$E:$E,'RPL2'!$C17,ADJ!$D:$D,'RPL2'!S$6) -> 0 | U17: =E17+I17+M17+Q17 -> 274.47197 | V17: =F17+J17+N17+R17 -> 323.99789 | W17: =G17+K17+O17+S17 -> 236.34792
C18: Professional fees | E18: =_xlfn.XLOOKUP($C18,'PL1'!$C:$C,'PL1'!AK:AK) -> 103.35 | F18: =_xlfn.XLOOKUP($C18,'PL1'!$C:$C,'PL1'!AL:AL) -> 153.54457 | G18: =_xlfn.XLOOKUP($C18,'PL1'!$C:$C,'PL1'!AM:AM) -> 186.6898 | I18: =-SUMIFS(ADJ!$AM:$AM,ADJ!$E:$E,'RPL2'!$C18,ADJ!$D:$D,'RPL2'!I$6) -> 0 | J18: =-SUMIFS(ADJ!$AN:$AN,ADJ!$E:$E,'RPL2'!$C18,ADJ!$D:$D,'RPL2'!J$6) -> 0 | K18: =-SUMIFS(ADJ!$AO:$AO,ADJ!$E:$E,'RPL2'!$C18,ADJ!$D:$D,'RPL2'!K$6) -> 0 | M18: =-SUMIFS(ADJ!$AM:$AM,ADJ!$E:$E,'RPL2'!$C18,ADJ!$D:$D,'RPL2'!M$6) -> 0 | N18: =-SUMIFS(ADJ!$AN:$AN,ADJ!$E:$E,'RPL2'!$C18,ADJ!$D:$D,'RPL2'!N$6) -> 0 | O18: =-SUMIFS(ADJ!$AO:$AO,ADJ!$E:$E,'RPL2'!$C18,ADJ!$D:$D,'RPL2'!O$6) -> 0 | Q18: =-SUMIFS(ADJ!$AM:$AM,ADJ!$E:$E,'RPL2'!$C18,ADJ!$D:$D,'RPL2'!Q$6) -> 0 | R18: =-SUMIFS(ADJ!$AN:$AN,ADJ!$E:$E,'RPL2'!$C18,ADJ!$D:$D,'RPL2'!R$6) -> 0 | S18: =-SUMIFS(ADJ!$AO:$AO,ADJ!$E:$E,'RPL2'!$C18,ADJ!$D:$D,'RPL2'!S$6) -> 0 | U18: =E18+I18+M18+Q18 -> 103.35 | V18: =F18+J18+N18+R18 -> 153.54457 | W18: =G18+K18+O18+S18 -> 186.6898
C19: Other operating expenses | E19: =_xlfn.XLOOKUP($C19,'PL1'!$C:$C,'PL1'!AK:AK) -> 113.9614 | F19: =_xlfn.XLOOKUP($C19,'PL1'!$C:$C,'PL1'!AL:AL) -> 103.58166 | G19: =_xlfn.XLOOKUP($C19,'PL1'!$C:$C,'PL1'!AM:AM) -> 111.18032 | I19: =-SUMIFS(ADJ!$AM:$AM,ADJ!$E:$E,'RPL2'!$C19,ADJ!$D:$D,'RPL2'!I$6) -> 0 | J19: =-SUMIFS(ADJ!$AN:$AN,ADJ!$E:$E,'RPL2'!$C19,ADJ!$D:$D,'RPL2'!J$6) -> 0 | K19: =-SUMIFS(ADJ!$AO:$AO,ADJ!$E:$E,'RPL2'!$C19,ADJ!$D:$D,'RPL2'!K$6) -> 0 | M19: =-SUMIFS(ADJ!$AM:$AM,ADJ!$E:$E,'RPL2'!$C19,ADJ!$D:$D,'RPL2'!M$6) -> 0 | N19: =-SUMIFS(ADJ!$AN:$AN,ADJ!$E:$E,'RPL2'!$C19,ADJ!$D:$D,'RPL2'!N$6) -> 0 | O19: =-SUMIFS(ADJ!$AO:$AO,ADJ!$E:$E,'RPL2'!$C19,ADJ!$D:$D,'RPL2'!O$6) -> 0 | Q19: =-SUMIFS(ADJ!$AM:$AM,ADJ!$E:$E,'RPL2'!$C19,ADJ!$D:$D,'RPL2'!Q$6) -> 0 | R19: =-SUMIFS(ADJ!$AN:$AN,ADJ!$E:$E,'RPL2'!$C19,ADJ!$D:$D,'RPL2'!R$6) -> 0 | S19: =-SUMIFS(ADJ!$AO:$AO,ADJ!$E:$E,'RPL2'!$C19,ADJ!$D:$D,'RPL2'!S$6) -> 0 | U19: =E19+I19+M19+Q19 -> 113.9614 | V19: =F19+J19+N19+R19 -> 103.58166 | W19: =G19+K19+O19+S19 -> 111.18032
C20: Travel, meals, and entertainment | E20: =_xlfn.XLOOKUP($C20,'PL1'!$C:$C,'PL1'!AK:AK) -> 23.36787 | F20: =_xlfn.XLOOKUP($C20,'PL1'!$C:$C,'PL1'!AL:AL) -> 20.44433 | G20: =_xlfn.XLOOKUP($C20,'PL1'!$C:$C,'PL1'!AM:AM) -> 31.06769 | I20: =-SUMIFS(ADJ!$AM:$AM,ADJ!$E:$E,'RPL2'!$C20,ADJ!$D:$D,'RPL2'!I$6) -> 0 | J20: =-SUMIFS(ADJ!$AN:$AN,ADJ!$E:$E,'RPL2'!$C20,ADJ!$D:$D,'RPL2'!J$6) -> 0 | K20: =-SUMIFS(ADJ!$AO:$AO,ADJ!$E:$E,'RPL2'!$C20,ADJ!$D:$D,'RPL2'!K$6) -> 0 | M20: =-SUMIFS(ADJ!$AM:$AM,ADJ!$E:$E,'RPL2'!$C20,ADJ!$D:$D,'RPL2'!M$6) -> 0 | N20: =-SUMIFS(ADJ!$AN:$AN,ADJ!$E:$E,'RPL2'!$C20,ADJ!$D:$D,'RPL2'!N$6) -> 0 | O20: =-SUMIFS(ADJ!$AO:$AO,ADJ!$E:$E,'RPL2'!$C20,ADJ!$D:$D,'RPL2'!O$6) -> 0 | Q20: =-SUMIFS(ADJ!$AM:$AM,ADJ!$E:$E,'RPL2'!$C20,ADJ!$D:$D,'RPL2'!Q$6) -> 0 | R20: =-SUMIFS(ADJ!$AN:$AN,ADJ!$E:$E,'RPL2'!$C20,ADJ!$D:$D,'RPL2'!R$6) -> 0 | S20: =-SUMIFS(ADJ!$AO:$AO,ADJ!$E:$E,'RPL2'!$C20,ADJ!$D:$D,'RPL2'!S$6) -> 0 | U20: =E20+I20+M20+Q20 -> 23.36787 | V20: =F20+J20+N20+R20 -> 20.44433 | W20: =G20+K20+O20+S20 -> 31.06769
C21: Operating expenses | E21: =SUM(E15:E20) -> 6505.5479 | F21: =SUM(F15:F20) -> 5546.7039 | G21: =SUM(G15:G20) -> 5646.9072 | I21: =SUM(I15:I20) -> 0 | J21: =SUM(J15:J20) -> 0 | K21: =SUM(K15:K20) -> 0 | M21: =SUM(M15:M20) -> 0 | N21: =SUM(N15:N20) -> 0 | O21: =SUM(O15:O20) -> 0 | Q21: =SUM(Q15:Q20) -> 0 | R21: =SUM(R15:R20) -> 0 | S21: =SUM(S15:S20) -> 0 | U21: =SUM(U15:U20) -> 6505.5479 | V21: =SUM(V15:V20) -> 5546.7039 | W21: =SUM(W15:W20) -> 5646.9072
C22: Operating profit | E22: =E13-E21 -> 1141.8737 | F22: =F13-F21 -> 1232.0473 | G22: =G13-G21 -> 1696.5071 | I22: =I13-I21 -> 0 | J22: =J13-J21 -> 0 | K22: =K13-K21 -> 0 | M22: =M13-M21 -> 0 | N22: =N13-N21 -> 0 | O22: =O13-O21 -> 0 | Q22: =Q13-Q21 -> 0 | R22: =R13-R21 -> 0 | S22: =S13-S21 -> 0 | U22: =U13-U21 -> 1141.8737 | V22: =V13-V21 -> 1232.0473 | W22: =W13-W21 -> 1696.5071
C24: Income taxes | E24: =_xlfn.XLOOKUP($C24,'PL1'!$C:$C,'PL1'!AK:AK) -> 1.5 | F24: =_xlfn.XLOOKUP($C24,'PL1'!$C:$C,'PL1'!AL:AL) -> 182.064 | G24: =_xlfn.XLOOKUP($C24,'PL1'!$C:$C,'PL1'!AM:AM) -> 167.11 | I24: =-SUMIFS(ADJ!$AM:$AM,ADJ!$E:$E,'RPL2'!$C24,ADJ!$D:$D,'RPL2'!I$6) -> -1.5 | J24: =-SUMIFS(ADJ!$AN:$AN,ADJ!$E:$E,'RPL2'!$C24,ADJ!$D:$D,'RPL2'!J$6) -> -182.064 | K24: =-SUMIFS(ADJ!$AO:$AO,ADJ!$E:$E,'RPL2'!$C24,ADJ!$D:$D,'RPL2'!K$6) -> -167.11 | M24: =-SUMIFS(ADJ!$AM:$AM,ADJ!$E:$E,'RPL2'!$C24,ADJ!$D:$D,'RPL2'!M$6) -> 0 | N24: =-SUMIFS(ADJ!$AN:$AN,ADJ!$E:$E,'RPL2'!$C24,ADJ!$D:$D,'RPL2'!N$6) -> 0 | O24: =-SUMIFS(ADJ!$AO:$AO,ADJ!$E:$E,'RPL2'!$C24,ADJ!$D:$D,'RPL2'!O$6) -> 0 | Q24: =-SUMIFS(ADJ!$AM:$AM,ADJ!$E:$E,'RPL2'!$C24,ADJ!$D:$D,'RPL2'!Q$6) -> 0 | R24: =-SUMIFS(ADJ!$AN:$AN,ADJ!$E:$E,'RPL2'!$C24,ADJ!$D:$D,'RPL2'!R$6) -> 0 | S24: =-SUMIFS(ADJ!$AO:$AO,ADJ!$E:$E,'RPL2'!$C24,ADJ!$D:$D,'RPL2'!S$6) -> 0 | U24: =E24+I24+M24+Q24 -> 0 | V24: =F24+J24+N24+R24 -> 0 | W24: =G24+K24+O24+S24 -> 0
C25: Depreciation and amortization | E25: =_xlfn.XLOOKUP($C25,'PL1'!$C:$C,'PL1'!AK:AK) -> 4.448 | F25: =_xlfn.XLOOKUP($C25,'PL1'!$C:$C,'PL1'!AL:AL) -> 3.516 | G25: =_xlfn.XLOOKUP($C25,'PL1'!$C:$C,'PL1'!AM:AM) -> 3.516 | I25: =-SUMIFS(ADJ!$AM:$AM,ADJ!$E:$E,'RPL2'!$C25,ADJ!$D:$D,'RPL2'!I$6) -> -4.448 | J25: =-SUMIFS(ADJ!$AN:$AN,ADJ!$E:$E,'RPL2'!$C25,ADJ!$D:$D,'RPL2'!J$6) -> -3.516 | K25: =-SUMIFS(ADJ!$AO:$AO,ADJ!$E:$E,'RPL2'!$C25,ADJ!$D:$D,'RPL2'!K$6) -> -3.516 | M25: =-SUMIFS(ADJ!$AM:$AM,ADJ!$E:$E,'RPL2'!$C25,ADJ!$D:$D,'RPL2'!M$6) -> 0 | N25: =-SUMIFS(ADJ!$AN:$AN,ADJ!$E:$E,'RPL2'!$C25,ADJ!$D:$D,'RPL2'!N$6) -> 0 | O25: =-SUMIFS(ADJ!$AO:$AO,ADJ!$E:$E,'RPL2'!$C25,ADJ!$D:$D,'RPL2'!O$6) -> 0 | Q25: =-SUMIFS(ADJ!$AM:$AM,ADJ!$E:$E,'RPL2'!$C25,ADJ!$D:$D,'RPL2'!Q$6) -> 0 | R25: =-SUMIFS(ADJ!$AN:$AN,ADJ!$E:$E,'RPL2'!$C25,ADJ!$D:$D,'RPL2'!R$6) -> 0 | S25: =-SUMIFS(ADJ!$AO:$AO,ADJ!$E:$E,'RPL2'!$C25,ADJ!$D:$D,'RPL2'!S$6) -> 0 | U25: =E25+I25+M25+Q25 -> 0 | V25: =F25+J25+N25+R25 -> 0 | W25: =G25+K25+O25+S25 -> 0
C26: Other non-operating expenses / (income) | E26: =_xlfn.XLOOKUP($C26,'PL1'!$C:$C,'PL1'!AK:AK) -> -431.84435 | F26: =_xlfn.XLOOKUP($C26,'PL1'!$C:$C,'PL1'!AL:AL) -> -52.26402 | G26: =_xlfn.XLOOKUP($C26,'PL1'!$C:$C,'PL1'!AM:AM) -> -52.15846 | I26: =-SUMIFS(ADJ!$AM:$AM,ADJ!$E:$E,'RPL2'!$C26,ADJ!$D:$D,'RPL2'!I$6) -> 0 | J26: =-SUMIFS(ADJ!$AN:$AN,ADJ!$E:$E,'RPL2'!$C26,ADJ!$D:$D,'RPL2'!J$6) -> 0 | K26: =-SUMIFS(ADJ!$AO:$AO,ADJ!$E:$E,'RPL2'!$C26,ADJ!$D:$D,'RPL2'!K$6) -> 0 | M26: =-SUMIFS(ADJ!$AM:$AM,ADJ!$E:$E,'RPL2'!$C26,ADJ!$D:$D,'RPL2'!M$6) -> 0 | N26: =-SUMIFS(ADJ!$AN:$AN,ADJ!$E:$E,'RPL2'!$C26,ADJ!$D:$D,'RPL2'!N$6) -> 0 | O26: =-SUMIFS(ADJ!$AO:$AO,ADJ!$E:$E,'RPL2'!$C26,ADJ!$D:$D,'RPL2'!O$6) -> 0 | Q26: =-SUMIFS(ADJ!$AM:$AM,ADJ!$E:$E,'RPL2'!$C26,ADJ!$D:$D,'RPL2'!Q$6) -> 0 | R26: =-SUMIFS(ADJ!$AN:$AN,ADJ!$E:$E,'RPL2'!$C26,ADJ!$D:$D,'RPL2'!R$6) -> 0 | S26: =-SUMIFS(ADJ!$AO:$AO,ADJ!$E:$E,'RPL2'!$C26,ADJ!$D:$D,'RPL2'!S$6) -> 0 | U26: =E26+I26+M26+Q26 -> -431.84435 | V26: =F26+J26+N26+R26 -> -52.26402 | W26: =G26+K26+O26+S26 -> -52.15846
C27: Non-operating expenses / (income) | E27: =SUM(E24:E26) -> -425.89635 | F27: =SUM(F24:F26) -> 133.31598 | G27: =SUM(G24:G26) -> 118.46754 | I27: =SUM(I24:I26) -> -5.948 | J27: =SUM(J24:J26) -> -185.58 | K27: =SUM(K24:K26) -> -170.626 | M27: =SUM(M24:M26) -> 0 | N27: =SUM(N24:N26) -> 0 | O27: =SUM(O24:O26) -> 0 | Q27: =SUM(Q24:Q26) -> 0 | R27: =SUM(R24:R26) -> 0 | S27: =SUM(S24:S26) -> 0 | U27: =SUM(U24:U26) -> -431.84435 | V27: =SUM(V24:V26) -> -52.26402 | W27: =SUM(W24:W26) -> -52.15846
C28: Net Income to Adjusted EBITDA | E28: =E22-E27 -> 1567.77 | F28: =F22-F27 -> 1098.7313 | G28: =G22-G27 -> 1578.0395 | I28: =I22-I27 -> 5.948 | J28: =J22-J27 -> 185.58 | K28: =K22-K27 -> 170.626 | M28: =M22-M27 -> 0 | N28: =N22-N27 -> 0 | O28: =O22-O27 -> 0 | Q28: =Q22-Q27 -> 0 | R28: =R22-R27 -> 0 | S28: =S22-S27 -> 0 | U28: =U22-U27 -> 1573.718 | V28: =V22-V27 -> 1284.3113 | W28: =W22-W27 -> 1748.6655
C31: Check Net income | E31: ='PL1'!AK30-E28 -> 0 | F31: ='PL1'!AL30-F28 -> 0 | G31: ='PL1'!AM30-G28 -> 0
C32: Check EBITDA, management | I32: =('QE1'!AK21+SUM('QE1'!AK10:AK12))-I28 -> 0 | J32: =('QE1'!AL21+SUM('QE1'!AL10:AL12))-J28 -> 0 | K32: =('QE1'!AM21+SUM('QE1'!AM10:AM12))-K28 -> 0
C33: Check EBITDA, diligence | M33: ='QE1'!AK41-M28 -> 0 | N33: ='QE1'!AL41-N28 -> 0 | O33: ='QE1'!AM41-O28 -> 0
C34: Check EBITDA, pro forma | Q34: ='QE1'!AK50-Q28 -> 0 | R34: ='QE1'!AL50-R28 -> 0 | S34: ='QE1'!AM50-S28 -> 0
C35: Check EBITDA, adjusted | U35: ='QE1'!AK51-U28 -> 0 | V35: ='QE1'!AL51-V28 -> 0 | W35: ='QE1'!AM51-W28 -> 0

Sheet QE>>
D8: Project X
D9: CLIENT
D10: Quality of Earnings Analysis

Sheet QE1
A1: =IF(ROUND(SUM(E103:AN105),1)<>0,"NO","Yes") -> Yes | C1: Project X | AX1: Open
A2: =IF(COUNTIF(E103:AN105,">0.5")+COUNTIF(E103:AN105,"<-0.5")<1,"Yes","No") -> Yes | C2: CLIENT | AX2: Completed
A3: =2-COUNTIF(A1:A2,"Yes") -> 0 | C3: ($ in 000s) | AX3: Needs Review
C4: Quality of Earnings Analysis | AX4: In Progress
C7: =C4 -> Quality of Earnings Analysis | E7: FY24 | Q7: FY25 | AC7: FY26 | AM7: =AI8 -> 45961
C8: =C3 -> ($ in 000s) | D8: Ref | E8: =TB!K1 -> 45046 | F8: =TB!L1 -> 45077 | G8: =TB!M1 -> 45107 | H8: =TB!N1 -> 45138 | I8: =TB!O1 -> 45169 | J8: =TB!P1 -> 45199 | K8: =TB!Q1 -> 45230 | L8: =TB!R1 -> 45260 | ... AI8: =TB!AO1 -> 45961 | AK8: ='PL1'!AK8 -> FY24 | AL8: ='PL1'!AL8 -> FY25 | AM8: ='PL1'!AM8 -> TTM26 | AO8: Status | AP8: Owner | AQ8: Due Date | AR8: Reviewer | AS8: Notes
C9: Net income | E9: =+'PL1'!E30 -> -308.89328 | F9: =+'PL1'!F30 -> -106.98811 | G9: =+'PL1'!G30 -> 163.55675 | H9: =+'PL1'!H30 -> 318.5039 | I9: =+'PL1'!I30 -> 108.45597 | J9: =+'PL1'!J30 -> -36.3254 | K9: =+'PL1'!K30 -> 107.54746 | L9: =+'PL1'!L30 -> 674.36889 | ... AI9: =+'PL1'!AI30 -> -102.31718 | AK9: =SUM(E9:P9) -> 1567.77 | AL9: =SUM(Q9:AB9) -> 1098.7313 | AM9: =SUM(X9:AI9) -> 1578.0395
C10: Interest expense, net | E10: =+'PL1'!E33 -> 0 | F10: =+'PL1'!F33 -> 0 | G10: =+'PL1'!G33 -> 0 | H10: =+'PL1'!H33 -> 0 | I10: =+'PL1'!I33 -> 0 | J10: =+'PL1'!J33 -> 0 | K10: =+'PL1'!K33 -> 0 | L10: =+'PL1'!L33 -> 0 | ... AI10: =+'PL1'!AI33 -> 0 | AK10: =SUM(E10:P10) -> 0 | AL10: =SUM(Q10:AB10) -> 0 | AM10: =SUM(X10:AI10) -> 0
C11: Income taxes | E11: =+'PL1'!E34 -> 0 | F11: =+'PL1'!F34 -> 0 | G11: =+'PL1'!G34 -> 0.375 | H11: =+'PL1'!H34 -> 0 | I11: =+'PL1'!I34 -> 0 | J11: =+'PL1'!J34 -> 0.375 | K11: =+'PL1'!K34 -> 0 | L11: =+'PL1'!L34 -> 0 | ... AI11: =+'PL1'!AI34 -> 0 | AK11: =SUM(E11:P11) -> 1.5 | AL11: =SUM(Q11:AB11) -> 182.064 | AM11: =SUM(X11:AI11) -> 167.11
C12: Depreciation and amortization | E12: =+'PL1'!E35 -> 0 | F12: =+'PL1'!F35 -> 0 | G12: =+'PL1'!G35 -> 0 | H12: =+'PL1'!H35 -> 0 | I12: =+'PL1'!I35 -> 0 | J12: =+'PL1'!J35 -> 0 | K12: =+'PL1'!K35 -> 0 | L12: =+'PL1'!L35 -> 0 | ... AI12: =+'PL1'!AI35 -> 0 | AK12: =SUM(E12:P12) -> 4.448 | AL12: =SUM(Q12:AB12) -> 3.516 | AM12: =SUM(X12:AI12) -> 3.516
C13: EBITDA, reported | E13: =SUM(E9:E12) -> -308.89328 | F13: =SUM(F9:F12) -> -106.98811 | G13: =SUM(G9:G12) -> 163.93175 | H13: =SUM(H9:H12) -> 318.5039 | I13: =SUM(I9:I12) -> 108.45597 | J13: =SUM(J9:J12) -> -35.9504 | K13: =SUM(K9:K12) -> 107.54746 | L13: =SUM(L9:L12) -> 674.36889 | ... AI13: =SUM(AI9:AI12) -> -102.31718 | AK13: =SUM(AK9:AK12) -> 1573.718 | AL13: =SUM(AL9:AL12) -> 1284.3113 | AM13: =SUM(AM9:AM12) -> 1748.6655
C15: Management adjustments:
C16: [open] | D16: [A] | AK16: =SUM(E16:P16) -> 0 | AL16: =SUM(Q16:AB16) -> 0 | AM16: =SUM(X16:AI16) -> 0 | AO16: Open
C17: [open] | D17: [B] | AK17: =SUM(E17:P17) -> 0 | AL17: =SUM(Q17:AB17) -> 0 | AM17: =SUM(X17:AI17) -> 0 | AO17: Open
C18: [open] | D18: [C] | AK18: =SUM(E18:P18) -> 0 | AL18: =SUM(Q18:AB18) -> 0 | AM18: =SUM(X18:AI18) -> 0 | AO18: Open
C19: [open] | D19: [D] | AK19: =SUM(E19:P19) -> 0 | AL19: =SUM(Q19:AB19) -> 0 | AM19: =SUM(X19:AI19) -> 0 | AO19: Open
C20: [open] | D20: [E] | AK20: =SUM(E20:P20) -> 0 | AL20: =SUM(Q20:AB20) -> 0 | AM20: =SUM(X20:AI20) -> 0 | AO20: Open
C21: Total Management adjustments | E21: =SUM(E16:E20) -> 0 | F21: =SUM(F16:F20) -> 0 | G21: =SUM(G16:G20) -> 0 | H21: =SUM(H16:H20) -> 0 | I21: =SUM(I16:I20) -> 0 | J21: =SUM(J16:J20) -> 0 | K21: =SUM(K16:K20) -> 0 | L21: =SUM(L16:L20) -> 0 | ... AI21: =SUM(AI16:AI20) -> 0 | AK21: =SUM(AK16:AK20) -> 0 | AL21: =SUM(AL16:AL20) -> 0 | AM21: =SUM(AM16:AM20) -> 0
C22: EBITDA, Management | E22: =E13+E21 -> -308.89328 | F22: =F13+F21 -> -106.98811 | G22: =G13+G21 -> 163.93175 | H22: =H13+H21 -> 318.5039 | I22: =I13+I21 -> 108.45597 | J22: =J13+J21 -> -35.9504 | K22: =K13+K21 -> 107.54746 | L22: =L13+L21 -> 674.36889 | ... AI22: =AI13+AI21 -> -102.31718 | AK22: =AK13+AK21 -> 1573.718 | AL22: =AL13+AL21 -> 1284.3113 | AM22: =AM13+AM21 -> 1748.6655
C24: Adjustments to Management adjustments:
C25: [open] | D25: [A] | AK25: =SUM(E25:P25) -> 0 | AL25: =SUM(Q25:AB25) -> 0 | AM25: =SUM(X25:AI25) -> 0 | AO25: Open
C26: [open] | D26: [B] | AK26: =SUM(E26:P26) -> 0 | AL26: =SUM(Q26:AB26) -> 0 | AM26: =SUM(X26:AI26) -> 0 | AO26: Open
C27: [open] | D27: [C] | AK27: =SUM(E27:P27) -> 0 | AL27: =SUM(Q27:AB27) -> 0 | AM27: =SUM(X27:AI27) -> 0 | AO27: Open
C28: [open] | D28: [D] | AK28: =SUM(E28:P28) -> 0 | AL28: =SUM(Q28:AB28) -> 0 | AM28: =SUM(X28:AI28) -> 0 | AO28: Open
C29: [open] | D29: [E] | AK29: =SUM(E29:P29) -> 0 | AL29: =SUM(Q29:AB29) -> 0 | AM29: =SUM(X29:AI29) -> 0 | AO29: Open
C31: Other diligence adjustments:
C32: [open] | AK32: =SUM(E32:P32) -> 0 | AL32: =SUM(Q32:AB32) -> 0 | AM32: =SUM(X32:AI32) -> 0 | AO32: Open
C33: [open] | AK33: =SUM(E33:P33) -> 0 | AL33: =SUM(Q33:AB33) -> 0 | AM33: =SUM(X33:AI33) -> 0 | AO33: Open
C34: [open] | AK34: =SUM(E34:P34) -> 0 | AL34: =SUM(Q34:AB34) -> 0 | AM34: =SUM(X34:AI34) -> 0 | AO34: Open
C35: [open] | AK35: =SUM(E35:P35) -> 0 | AL35: =SUM(Q35:AB35) -> 0 | AM35: =SUM(X35:AI35) -> 0 | AO35: Open
C36: [open] | AK36: =SUM(E36:P36) -> 0 | AL36: =SUM(Q36:AB36) -> 0 | AM36: =SUM(X36:AI36) -> 0 | AO36: Open
C37: [open] | AK37: =SUM(E37:P37) -> 0 | AL37: =SUM(Q37:AB37) -> 0 | AM37: =SUM(X37:AI37) -> 0 | AO37: Open
C38: [open] | AK38: =SUM(E38:P38) -> 0 | AL38: =SUM(Q38:AB38) -> 0 | AM38: =SUM(X38:AI38) -> 0 | AO38: Open
C39: [open] | AK39: =SUM(E39:P39) -> 0 | AL39: =SUM(Q39:AB39) -> 0 | AM39: =SUM(X39:AI39) -> 0 | AO39: Open
C40: [open] | AK40: =SUM(E40:P40) -> 0 | AL40: =SUM(Q40:AB40) -> 0 | AM40: =SUM(X40:AI40) -> 0 | AO40: Open
C41: Total diligence adjustments | E41: =SUM(E25:E40) -> 0 | F41: =SUM(F25:F40) -> 0 | G41: =SUM(G25:G40) -> 0 | H41: =SUM(H25:H40) -> 0 | I41: =SUM(I25:I40) -> 0 | J41: =SUM(J25:J40) -> 0 | K41: =SUM(K25:K40) -> 0 | L41: =SUM(L25:L40) -> 0 | ... AI41: =SUM(AI25:AI40) -> 0 | AK41: =SUM(AK25:AK40) -> 0 | AL41: =SUM(AL25:AL40) -> 0 | AM41: =SUM(AM25:AM40) -> 0
C42: EBITDA, adjusted | E42: =E22+E41 -> -308.89328 | F42: =F22+F41 -> -106.98811 | G42: =G22+G41 -> 163.93175 | H42: =H22+H41 -> 318.5039 | I42: =I22+I41 -> 108.45597 | J42: =J22+J41 -> -35.9504 | K42: =K22+K41 -> 107.54746 | L42: =L22+L41 -> 674.36889 | ... AI42: =AI22+AI41 -> -102.31718 | AK42: =AK22+AK41 -> 1573.718 | AL42: =AL22+AL41 -> 1284.3113 | AM42: =AM22+AM41 -> 1748.6655
C43: EBITDA margin, reported | E43: =+IFERROR(E13/'PL1'!E10%,0) -> -159.94308 | F43: =+IFERROR(F13/'PL1'!F10%,0) -> -24.913198 | G43: =+IFERROR(G13/'PL1'!G10%,0) -> 22.400709 | H43: =+IFERROR(H13/'PL1'!H10%,0) -> 74.009573 | I43: =+IFERROR(I13/'PL1'!I10%,0) -> 17.396684 | J43: =+IFERROR(J13/'PL1'!J10%,0) -> -7.4767226 | K43: =+IFERROR(K13/'PL1'!K10%,0) -> 15.621272 | L43: =+IFERROR(L13/'PL1'!L10%,0) -> 53.208865 | ... AI43: =+IFERROR(AI13/'PL1'!AI10%,0) -> -24.177713 | AK43: =+IFERROR(AK13/'PL1'!AK10%,0) -> 20.578413 | AL43: =+IFERROR(AL13/'PL1'!AL10%,0) -> 18.946135 | AM43: =+IFERROR(AM13/'PL1'!AM10%,0) -> 23.812704
C44: EBITDA margin, adjusted | E44: =+IFERROR(E42/'RPL1'!E10%,0) -> -159.94308 | F44: =+IFERROR(F42/'RPL1'!F10%,0) -> -24.913198 | G44: =+IFERROR(G42/'RPL1'!G10%,0) -> 22.400709 | H44: =+IFERROR(H42/'RPL1'!H10%,0) -> 74.009573 | I44: =+IFERROR(I42/'RPL1'!I10%,0) -> 17.396684 | J44: =+IFERROR(J42/'RPL1'!J10%,0) -> -7.4767226 | K44: =+IFERROR(K42/'RPL1'!K10%,0) -> 15.621272 | L44: =+IFERROR(L42/'RPL1'!L10%,0) -> 53.208865 | ... AI44: =+IFERROR(AI42/'RPL1'!AI10%,0) -> -24.177713 | AK44: =+IFERROR(AK42/'RPL1'!AK10%,0) -> 20.578413 | AL44: =+IFERROR(AL42/'RPL1'!AL10%,0) -> 18.946135 | AM44: =+IFERROR(AM42/'RPL1'!AM10%,0) -> 23.812704
C46: Pro forma adjustments:
C47: [open] | AK47: =SUM(E47:P47) -> 0 | AL47: =SUM(Q47:AB47) -> 0 | AM47: =SUM(X47:AI47) -> 0 | AO47: Open
C48: [open] | AK48: =SUM(E48:P48) -> 0 | AL48: =SUM(Q48:AB48) -> 0 | AM48: =SUM(X48:AI48) -> 0 | AO48: Open
C49: [open] | AK49: =SUM(E49:P49) -> 0 | AL49: =SUM(Q49:AB49) -> 0 | AM49: =SUM(X49:AI49) -> 0 | AO49: Open
C50: Total pro forma adjustments | E50: =SUM(E47:E49) -> 0 | F50: =SUM(F47:F49) -> 0 | G50: =SUM(G47:G49) -> 0 | H50: =SUM(H47:H49) -> 0 | I50: =SUM(I47:I49) -> 0 | J50: =SUM(J47:J49) -> 0 | K50: =SUM(K47:K49) -> 0 | L50: =SUM(L47:L49) -> 0 | ... AI50: =SUM(AI47:AI49) -> 0 | AK50: =SUM(AK47:AK49) -> 0 | AL50: =SUM(AL47:AL49) -> 0 | AM50: =SUM(AM47:AM49) -> 0
C51: EBITDA, pro forma | E51: =E42+E50 -> -308.89328 | F51: =F42+F50 -> -106.98811 | G51: =G42+G50 -> 163.93175 | H51: =H42+H50 -> 318.5039 | I51: =I42+I50 -> 108.45597 | J51: =J42+J50 -> -35.9504 | K51: =K42+K50 -> 107.54746 | L51: =L42+L50 -> 674.36889 | ... AI51: =AI42+AI50 -> -102.31718 | AK51: =AK42+AK50 -> 1573.718 | AL51: =AL42+AL50 -> 1284.3113 | AM51: =AM42+AM50 -> 1748.6655
C52: EBITDA margin, pro forma | E52: =+IFERROR(E51/'RPL1'!E10%,0) -> -159.94308 | F52: =+IFERROR(F51/'RPL1'!F10%,0) -> -24.913198 | G52: =+IFERROR(G51/'RPL1'!G10%,0) -> 22.400709 | H52: =+IFERROR(H51/'RPL1'!H10%,0) -> 74.009573 | I52: =+IFERROR(I51/'RPL1'!I10%,0) -> 17.396684 | J52: =+IFERROR(J51/'RPL1'!J10%,0) -> -7.4767226 | K52: =+IFERROR(K51/'RPL1'!K10%,0) -> 15.621272 | L52: =+IFERROR(L51/'RPL1'!L10%,0) -> 53.208865 | ... AI52: =+IFERROR(AI51/'RPL1'!AI10%,0) -> -24.177713 | AK52: =+IFERROR(AK51/'RPL1'!AK10%,0) -> 20.578413 | AL52: =+IFERROR(AL51/'RPL1'!AL10%,0) -> 18.946135 | AM52: =+IFERROR(AM51/'RPL1'!AM10%,0) -> 23.812704
C55: Databook Task List:
C56: Initial databook build
C57: Set up entire databook for appropriate Historical Period, client / project name, Fiscal year, etc
C58: Tie-Out to Internal FS (assuming no assurance work)
C59: PL1, PL2, BS1, BS2
C60: QE1 - identify definitional reported EBITDA / Rec out to Management EBITDA, build in Mgmt EBITDA adjustments (see LOI)
C61: NWC1 - populate DSO, DIOH, DPO from this tab not BS1
C62: NWC2 - Populate DSO, DIOH, DPO from this tab not NWC1
C63: DDL
C64: RPL1
C65: RPL2
C66: ADJ
... C100: Mgmt Meeting (see phase 3 of playbook)
C103: Check to RPL1 | E103: =+'RPL1'!E30-E51 -> 0 | F103: =+'RPL1'!F30-F51 -> 0 | G103: =+'RPL1'!G30-G51 -> 0 | H103: =+'RPL1'!H30-H51 -> 0 | I103: =+'RPL1'!I30-I51 -> 0 | J103: =+'RPL1'!J30-J51 -> 0 | K103: =+'RPL1'!K30-K51 -> 0 | L103: =+'RPL1'!L30-L51 -> 0 | ... AI103: =+'RPL1'!AI30-AI51 -> 0 | AK103: =+'RPL1'!AK30-AK51 -> 0 | AL103: =+'RPL1'!AL30-AL51 -> 0 | AM103: =+'RPL1'!AM30-AM51 -> 0
C105: Check PL1 EBITDA, reported | E105: ='PL1'!E36-E13 -> 0 | F105: ='PL1'!F36-F13 -> 0 | G105: ='PL1'!G36-G13 -> 0 | H105: ='PL1'!H36-H13 -> 0 | I105: ='PL1'!I36-I13 -> 0 | J105: ='PL1'!J36-J13 -> 0 | K105: ='PL1'!K36-K13 -> 0 | L105: ='PL1'!L36-L13 -> 0 | ... AI105: ='PL1'!AI36-AI13 -> 0 | AK105: ='PL1'!AK36-AK13 -> 0 | AL105: ='PL1'!AL36-AL13 -> 0 | AM105: ='PL1'!AM36-AM13 -> 0

Sheet NWC>>
D8: Project X
D9: CLIENT
D10: Net Working Capital Analysis

Sheet NWC1
A1: =IF(ROUND(SUM(E81:AS83),1)<>0,"NO","Yes") -> Yes | C1: Project X
A2: =IF(COUNTIF(E81:AS83,">0.5")+COUNTIF(E81:AS83,"<-0.5")<1,"Yes","No") -> Yes | C2: CLIENT
A3: =2-COUNTIF(A1:A2,"Yes") -> 0 | C3: ($ in 000s)
C4: Net Working Capital Analysis
C7: =C4 -> Net Working Capital Analysis | E7: FY24 | Q7: FY25 | AC7: FY26 | AO7: Averages
C8: =C3 -> ($ in 000s) | D8: Ref | E8: =TB!K1 -> 45046 | F8: =TB!L1 -> 45077 | G8: =TB!M1 -> 45107 | H8: =TB!N1 -> 45138 | I8: =TB!O1 -> 45169 | J8: =TB!P1 -> 45199 | K8: =TB!Q1 -> 45230 | L8: =TB!R1 -> 45260 | ... AI8: =TB!AO1 -> 45961 | AK8: =P8 -> 45382 | AL8: =AB8 -> 45747 | AM8: =AI8 -> 45961 | AO8: 3m | AP8: 6m | AQ8: 9m | AR8: 12m
C9: First Bank Chk 9631 | E9: =SUMIFS(TB!K:K,TB!$J:$J,$C9) -> 1392.9364 | F9: =SUMIFS(TB!L:L,TB!$J:$J,$C9) -> 1274.7818 | G9: =SUMIFS(TB!M:M,TB!$J:$J,$C9) -> 1044.7661 | H9: =SUMIFS(TB!N:N,TB!$J:$J,$C9) -> 1503.9179 | I9: =SUMIFS(TB!O:O,TB!$J:$J,$C9) -> 1652.8162 | J9: =SUMIFS(TB!P:P,TB!$J:$J,$C9) -> 1471.6317 | K9: =SUMIFS(TB!Q:Q,TB!$J:$J,$C9) -> 1561.2997 | L9: =SUMIFS(TB!R:R,TB!$J:$J,$C9) -> 1587.8386 | M9: =SUMIFS(TB!S:S,TB!$J:$J,$C9) -> 2715.6499 | N9: =SUMIFS(TB!T:T,TB!$J:$J,$C9) -> 3088.5361 | O9: =SUMIFS(TB!U:U,TB!$J:$J,$C9) -> 3120.5026 | P9: =SUMIFS(TB!V:V,TB!$J:$J,$C9) -> 2226.7281 | Q9: =SUMIFS(TB!W:W,TB!$J:$J,$C9) -> 2311.9428 | R9: =SUMIFS(TB!X:X,TB!$J:$J,$C9) -> 2217.081 | S9: =SUMIFS(TB!Y:Y,TB!$J:$J,$C9) -> 2312.1652 | T9: =SUMIFS(TB!Z:Z,TB!$J:$J,$C9) -> 2119.5666 | U9: =SUMIFS(TB!AA:AA,TB!$J:$J,$C9) -> 2118.6529 | V9: =SUMIFS(TB!AB:AB,TB!$J:$J,$C9) -> 1856.6124 | W9: =SUMIFS(TB!AC:AC,TB!$J:$J,$C9) -> 1820.1974 | X9: =SUMIFS(TB!AD:AD,TB!$J:$J,$C9) -> 2082.7491 | Y9: =SUMIFS(TB!AE:AE,TB!$J:$J,$C9) -> 2389.3521 | Z9: =SUMIFS(TB!AF:AF,TB!$J:$J,$C9) -> 3006.4508 | AA9: =SUMIFS(TB!AG:AG,TB!$J:$J,$C9) -> 2479.0816 | AB9: =SUMIFS(TB!AH:AH,TB!$J:$J,$C9) -> 2545.0139 | AC9: =SUMIFS(TB!AI:AI,TB!$J:$J,$C9) -> 2228.6964 | AD9: =SUMIFS(TB!AJ:AJ,TB!$J:$J,$C9) -> 2111.778 | AE9: =SUMIFS(TB!AK:AK,TB!$J:$J,$C9) -> 1740.85 | AF9: =SUMIFS(TB!AL:AL,TB!$J:$J,$C9) -> 1788.9023 | AG9: =SUMIFS(TB!AM:AM,TB!$J:$J,$C9) -> 1690.6656 | AH9: =SUMIFS(TB!AN:AN,TB!$J:$J,$C9) -> 1603.7638 | AI9: =SUMIFS(TB!AO:AO,TB!$J:$J,$C9) -> 1360.8279 | AK9: =P9 -> 2226.7281 | AL9: =AB9 -> 2545.0139 | AM9: =AI9 -> 1360.8279 | AO9: =IFERROR(AVERAGE(AG9:AI9),0) -> 1551.7524 | AP9: =IFERROR(AVERAGE(AD9:AI9),0) -> 1716.1313 | AQ9: =IFERROR(AVERAGE(AA9:AI9),0) -> 1949.9533 | AR9: =IFERROR(AVERAGE(X9:AI9),0) -> 2085.6776
C10: Bus Intst Chk 3395 | E10: =SUMIFS(TB!K:K,TB!$J:$J,$C10) -> 241.55249 | F10: =SUMIFS(TB!L:L,TB!$J:$J,$C10) -> 241.05249 | G10: =SUMIFS(TB!M:M,TB!$J:$J,$C10) -> 241.05249 | H10: =SUMIFS(TB!N:N,TB!$J:$J,$C10) -> 240.74938 | I10: =SUMIFS(TB!O:O,TB!$J:$J,$C10) -> 240.74938 | J10: =SUMIFS(TB!P:P,TB!$J:$J,$C10) -> 240.74938 | K10: =SUMIFS(TB!Q:Q,TB!$J:$J,$C10) -> 240.74938 | L10: =SUMIFS(TB!R:R,TB!$J:$J,$C10) -> 240.71334 | M10: =SUMIFS(TB!S:S,TB!$J:$J,$C10) -> 240.40911 | N10: =SUMIFS(TB!T:T,TB!$J:$J,$C10) -> 240.40911 | O10: =SUMIFS(TB!U:U,TB!$J:$J,$C10) -> 240.40911 | P10: =SUMIFS(TB!V:V,TB!$J:$J,$C10) -> 240.40911 | Q10: =SUMIFS(TB!W:W,TB!$J:$J,$C10) -> 240.40911 | R10: =SUMIFS(TB!X:X,TB!$J:$J,$C10) -> 240.38411 | S10: =SUMIFS(TB!Y:Y,TB!$J:$J,$C10) -> 278.73411 | T10: =SUMIFS(TB!Z:Z,TB!$J:$J,$C10) -> 312.08411 | U10: =SUMIFS(TB!AA:AA,TB!$J:$J,$C10) -> 312.08411 | V10: =SUMIFS(TB!AB:AB,TB!$J:$J,$C10) -> 312.08411 | W10: =SUMIFS(TB!AC:AC,TB!$J:$J,$C10) -> 312.08411 | X10: =SUMIFS(TB!AD:AD,TB!$J:$J,$C10) -> 312.08411 | Y10: =SUMIFS(TB!AE:AE,TB!$J:$J,$C10) -> 312.08411 | Z10: =SUMIFS(TB!AF:AF,TB!$J:$J,$C10) -> 312.08411 | AA10: =SUMIFS(TB!AG:AG,TB!$J:$J,$C10) -> 312.08411 | AB10: =SUMIFS(TB!AH:AH,TB!$J:$J,$C10) -> 312.08411 | AC10: =SUMIFS(TB!AI:AI,TB!$J:$J,$C10) -> 312.05552 | AD10: =SUMIFS(TB!AJ:AJ,TB!$J:$J,$C10) -> 312.05552 | AE10: =SUMIFS(TB!AK:AK,TB!$J:$J,$C10) -> 365.15552 | AF10: =SUMIFS(TB!AL:AL,TB!$J:$J,$C10) -> 365.15552 | AG10: =SUMIFS(TB!AM:AM,TB!$J:$J,$C10) -> 403.25552 | AH10: =SUMIFS(TB!AN:AN,TB!$J:$J,$C10) -> 403.25552 | AI10: =SUMIFS(TB!AO:AO,TB!$J:$J,$C10) -> 403.25552 | AK10: =P10 -> 240.40911 | AL10: =AB10 -> 312.08411 | AM10: =AI10 -> 403.25552 | AO10: =IFERROR(AVERAGE(AG10:AI10),0) -> 403.25552 | AP10: =IFERROR(AVERAGE(AD10:AI10),0) -> 375.35552 | AQ10: =IFERROR(AVERAGE(AA10:AI10),0) -> 354.26187 | AR10: =IFERROR(AVERAGE(X10:AI10),0) -> 343.71743
C11: Cash and cash equivalents | E11: =SUM(E9:E10) -> 1634.4889 | F11: =SUM(F9:F10) -> 1515.8343 | G11: =SUM(G9:G10) -> 1285.8186 | H11: =SUM(H9:H10) -> 1744.6673 | I11: =SUM(I9:I10) -> 1893.5656 | J11: =SUM(J9:J10) -> 1712.3811 | K11: =SUM(K9:K10) -> 1802.049 | L11: =SUM(L9:L10) -> 1828.552 | ... AI11: =SUM(AI9:AI10) -> 1764.0835 | AK11: =SUM(AK9:AK10) -> 2467.1372 | AL11: =SUM(AL9:AL10) -> 2857.098 | AM11: =SUM(AM9:AM10) -> 1764.0835 | AO11: =SUM(AO9:AO10) -> 1955.008 | AP11: =SUM(AP9:AP10) -> 2091.4868 | AQ11: =SUM(AQ9:AQ10) -> 2304.2152 | AR11: =SUM(AR9:AR10) -> 2429.3951
C13: Accounts Receivable | E13: =SUMIFS(TB!K:K,TB!$J:$J,$C13) -> 298.091 | F13: =SUMIFS(TB!L:L,TB!$J:$J,$C13) -> 347.8945 | G13: =SUMIFS(TB!M:M,TB!$J:$J,$C13) -> 766.232 | H13: =SUMIFS(TB!N:N,TB!$J:$J,$C13) -> 528.957 | I13: =SUMIFS(TB!O:O,TB!$J:$J,$C13) -> 459.328 | J13: =SUMIFS(TB!P:P,TB!$J:$J,$C13) -> 637.956 | K13: =SUMIFS(TB!Q:Q,TB!$J:$J,$C13) -> 751.575 | L13: =SUMIFS(TB!R:R,TB!$J:$J,$C13) -> 1371.4255 | M13: =SUMIFS(TB!S:S,TB!$J:$J,$C13) -> 911.5285 | N13: =SUMIFS(TB!T:T,TB!$J:$J,$C13) -> 371.5595 | O13: =SUMIFS(TB!U:U,TB!$J:$J,$C13) -> 371.7205 | P13: =SUMIFS(TB!V:V,TB!$J:$J,$C13) -> 636.876 | Q13: =SUMIFS(TB!W:W,TB!$J:$J,$C13) -> 542.1465 | R13: =SUMIFS(TB!X:X,TB!$J:$J,$C13) -> 717.0845 | S13: =SUMIFS(TB!Y:Y,TB!$J:$J,$C13) -> 468.527 | T13: =SUMIFS(TB!Z:Z,TB!$J:$J,$C13) -> 427.884 | U13: =SUMIFS(TB!AA:AA,TB!$J:$J,$C13) -> 521.295 | V13: =SUMIFS(TB!AB:AB,TB!$J:$J,$C13) -> 547.449 | W13: =SUMIFS(TB!AC:AC,TB!$J:$J,$C13) -> 471.657 | X13: =SUMIFS(TB!AD:AD,TB!$J:$J,$C13) -> 917.839 | Y13: =SUMIFS(TB!AE:AE,TB!$J:$J,$C13) -> 1105.536 | Z13: =SUMIFS(TB!AF:AF,TB!$J:$J,$C13) -> 329.661 | AA13: =SUMIFS(TB!AG:AG,TB!$J:$J,$C13) -> 727.5975 | AB13: =SUMIFS(TB!AH:AH,TB!$J:$J,$C13) -> 597.9 | AC13: =SUMIFS(TB!AI:AI,TB!$J:$J,$C13) -> 557.573 | AD13: =SUMIFS(TB!AJ:AJ,TB!$J:$J,$C13) -> 512 | AE13: =SUMIFS(TB!AK:AK,TB!$J:$J,$C13) -> 996.3901 | AF13: =SUMIFS(TB!AL:AL,TB!$J:$J,$C13) -> 636.0036 | AG13: =SUMIFS(TB!AM:AM,TB!$J:$J,$C13) -> 608.917 | AH13: =SUMIFS(TB!AN:AN,TB!$J:$J,$C13) -> 836.82 | AI13: =SUMIFS(TB!AO:AO,TB!$J:$J,$C13) -> 770.763 | AK13: =P13 -> 636.876 | AL13: =AB13 -> 597.9 | AM13: =AI13 -> 770.763 | AO13: =IFERROR(AVERAGE(AG13:AI13),0) -> 738.83333 | AP13: =IFERROR(AVERAGE(AD13:AI13),0) -> 726.81562 | AQ13: =IFERROR(AVERAGE(AA13:AI13),0) -> 693.7738 | AR13: =IFERROR(AVERAGE(X13:AI13),0) -> 716.41668
C14: Accounts receivable, net | E14: =SUM(E13:E13) -> 298.091 | F14: =SUM(F13:F13) -> 347.8945 | G14: =SUM(G13:G13) -> 766.232 | H14: =SUM(H13:H13) -> 528.957 | I14: =SUM(I13:I13) -> 459.328 | J14: =SUM(J13:J13) -> 637.956 | K14: =SUM(K13:K13) -> 751.575 | L14: =SUM(L13:L13) -> 1371.4255 | ... AI14: =SUM(AI13:AI13) -> 770.763 | AK14: =SUM(AK13:AK13) -> 636.876 | AL14: =SUM(AL13:AL13) -> 597.9 | AM14: =SUM(AM13:AM13) -> 770.763 | AO14: =SUM(AO13:AO13) -> 738.83333 | AP14: =SUM(AP13:AP13) -> 726.81562 | AQ14: =SUM(AQ13:AQ13) -> 693.7738 | AR14: =SUM(AR13:AR13) -> 716.41668
C16: Due from Vendor | E16: =SUMIFS(TB!K:K,TB!$J:$J,$C16) -> 0.3 | F16: =SUMIFS(TB!L:L,TB!$J:$J,$C16) -> 0.3 | G16: =SUMIFS(TB!M:M,TB!$J:$J,$C16) -> 0.3 | H16: =SUMIFS(TB!N:N,TB!$J:$J,$C16) -> 0.3 | I16: =SUMIFS(TB!O:O,TB!$J:$J,$C16) -> 0.3 | J16: =SUMIFS(TB!P:P,TB!$J:$J,$C16) -> 0.3 | K16: =SUMIFS(TB!Q:Q,TB!$J:$J,$C16) -> 0.3 | L16: =SUMIFS(TB!R:R,TB!$J:$J,$C16) -> 0.3 | M16: =SUMIFS(TB!S:S,TB!$J:$J,$C16) -> 0.3 | N16: =SUMIFS(TB!T:T,TB!$J:$J,$C16) -> 0.3 | O16: =SUMIFS(TB!U:U,TB!$J:$J,$C16) -> 0.3 | P16: =SUMIFS(TB!V:V,TB!$J:$J,$C16) -> 0.3 | Q16: =SUMIFS(TB!W:W,TB!$J:$J,$C16) -> 0.3 | R16: =SUMIFS(TB!X:X,TB!$J:$J,$C16) -> 0.3 | S16: =SUMIFS(TB!Y:Y,TB!$J:$J,$C16) -> 0.3 | T16: =SUMIFS(TB!Z:Z,TB!$J:$J,$C16) -> 0.3 | U16: =SUMIFS(TB!AA:AA,TB!$J:$J,$C16) -> 0.3 | V16: =SUMIFS(TB!AB:AB,TB!$J:$J,$C16) -> 2.939 | W16: =SUMIFS(TB!AC:AC,TB!$J:$J,$C16) -> 2.939 | X16: =SUMIFS(TB!AD:AD,TB!$J:$J,$C16) -> 2.939 | Y16: =SUMIFS(TB!AE:AE,TB!$J:$J,$C16) -> 2.939 | Z16: =SUMIFS(TB!AF:AF,TB!$J:$J,$C16) -> 2.939 | AA16: =SUMIFS(TB!AG:AG,TB!$J:$J,$C16) -> 2.939 | AB16: =SUMIFS(TB!AH:AH,TB!$J:$J,$C16) -> 2.939 | AC16: =SUMIFS(TB!AI:AI,TB!$J:$J,$C16) -> 2.939 | AD16: =SUMIFS(TB!AJ:AJ,TB!$J:$J,$C16) -> 2.939 | AE16: =SUMIFS(TB!AK:AK,TB!$J:$J,$C16) -> 2.939 | AF16: =SUMIFS(TB!AL:AL,TB!$J:$J,$C16) -> 2.939 | AG16: =SUMIFS(TB!AM:AM,TB!$J:$J,$C16) -> 2.939 | AH16: =SUMIFS(TB!AN:AN,TB!$J:$J,$C16) -> 2.939 | AI16: =SUMIFS(TB!AO:AO,TB!$J:$J,$C16) -> 2.939 | AK16: =P16 -> 0.3 | AL16: =AB16 -> 2.939 | AM16: =AI16 -> 2.939 | AO16: =IFERROR(AVERAGE(AG16:AI16),0) -> 2.939 | AP16: =IFERROR(AVERAGE(AD16:AI16),0) -> 2.939 | AQ16: =IFERROR(AVERAGE(AA16:AI16),0) -> 2.939 | AR16: =IFERROR(AVERAGE(X16:AI16),0) -> 2.939
C17: Due from Accelerant | E17: =SUMIFS(TB!K:K,TB!$J:$J,$C17) -> 0 | F17: =SUMIFS(TB!L:L,TB!$J:$J,$C17) -> 0 | G17: =SUMIFS(TB!M:M,TB!$J:$J,$C17) -> 0 | H17: =SUMIFS(TB!N:N,TB!$J:$J,$C17) -> 0 | I17: =SUMIFS(TB!O:O,TB!$J:$J,$C17) -> 0 | J17: =SUMIFS(TB!P:P,TB!$J:$J,$C17) -> 0 | K17: =SUMIFS(TB!Q:Q,TB!$J:$J,$C17) -> 0 | L17: =SUMIFS(TB!R:R,TB!$J:$J,$C17) -> 0 | M17: =SUMIFS(TB!S:S,TB!$J:$J,$C17) -> 0 | N17: =SUMIFS(TB!T:T,TB!$J:$J,$C17) -> 0 | O17: =SUMIFS(TB!U:U,TB!$J:$J,$C17) -> 0 | P17: =SUMIFS(TB!V:V,TB!$J:$J,$C17) -> 0 | Q17: =SUMIFS(TB!W:W,TB!$J:$J,$C17) -> 0 | R17: =SUMIFS(TB!X:X,TB!$J:$J,$C17) -> 0 | S17: =SUMIFS(TB!Y:Y,TB!$J:$J,$C17) -> 0 | T17: =SUMIFS(TB!Z:Z,TB!$J:$J,$C17) -> 0 | U17: =SUMIFS(TB!AA:AA,TB!$J:$J,$C17) -> 0 | V17: =SUMIFS(TB!AB:AB,TB!$J:$J,$C17) -> 0 | W17: =SUMIFS(TB!AC:AC,TB!$J:$J,$C17) -> 0 | X17: =SUMIFS(TB!AD:AD,TB!$J:$J,$C17) -> 0 | Y17: =SUMIFS(TB!AE:AE,TB!$J:$J,$C17) -> 0 | Z17: =SUMIFS(TB!AF:AF,TB!$J:$J,$C17) -> 0 | AA17: =SUMIFS(TB!AG:AG,TB!$J:$J,$C17) -> 1.3 | AB17: =SUMIFS(TB!AH:AH,TB!$J:$J,$C17) -> 1.3 | AC17: =SUMIFS(TB!AI:AI,TB!$J:$J,$C17) -> 1.3 | AD17: =SUMIFS(TB!AJ:AJ,TB!$J:$J,$C17) -> 1.3 | AE17: =SUMIFS(TB!AK:AK,TB!$J:$J,$C17) -> 1.3 | AF17: =SUMIFS(TB!AL:AL,TB!$J:$J,$C17) -> 1.3 | AG17: =SUMIFS(TB!AM:AM,TB!$J:$J,$C17) -> 1.3 | AH17: =SUMIFS(TB!AN:AN,TB!$J:$J,$C17) -> 1.3 | AI17: =SUMIFS(TB!AO:AO,TB!$J:$J,$C17) -> 1.3 | AK17: =P17 -> 0 | AL17: =AB17 -> 1.3 | AM17: =AI17 -> 1.3 | AO17: =IFERROR(AVERAGE(AG17:AI17),0) -> 1.3 | AP17: =IFERROR(AVERAGE(AD17:AI17),0) -> 1.3 | AQ17: =IFERROR(AVERAGE(AA17:AI17),0) -> 1.3 | AR17: =IFERROR(AVERAGE(X17:AI17),0) -> 0.975
C18: Due from Kathrin | E18: =SUMIFS(TB!K:K,TB!$J:$J,$C18) -> 0 | F18: =SUMIFS(TB!L:L,TB!$J:$J,$C18) -> 0 | G18: =SUMIFS(TB!M:M,TB!$J:$J,$C18) -> 0 | H18: =SUMIFS(TB!N:N,TB!$J:$J,$C18) -> 0.05252 | I18: =SUMIFS(TB!O:O,TB!$J:$J,$C18) -> 0.05252 | J18: =SUMIFS(TB!P:P,TB!$J:$J,$C18) -> 0.05252 | K18: =SUMIFS(TB!Q:Q,TB!$J:$J,$C18) -> 0.05252 | L18: =SUMIFS(TB!R:R,TB!$J:$J,$C18) -> 0.05252 | M18: =SUMIFS(TB!S:S,TB!$J:$J,$C18) -> 0.05252 | N18: =SUMIFS(TB!T:T,TB!$J:$J,$C18) -> 0.05252 | O18: =SUMIFS(TB!U:U,TB!$J:$J,$C18) -> 0.05252 | P18: =SUMIFS(TB!V:V,TB!$J:$J,$C18) -> 0.05252 | Q18: =SUMIFS(TB!W:W,TB!$J:$J,$C18) -> 0.05252 | R18: =SUMIFS(TB!X:X,TB!$J:$J,$C18) -> 0.05252 | S18: =SUMIFS(TB!Y:Y,TB!$J:$J,$C18) -> 0.05252 | T18: =SUMIFS(TB!Z:Z,TB!$J:$J,$C18) -> 0.05252 | U18: =SUMIFS(TB!AA:AA,TB!$J:$J,$C18) -> 0.05252 | V18: =SUMIFS(TB!AB:AB,TB!$J:$J,$C18) -> 0.05252 | W18: =SUMIFS(TB!AC:AC,TB!$J:$J,$C18) -> 0.05252 | X18: =SUMIFS(TB!AD:AD,TB!$J:$J,$C18) -> 0.05252 | Y18: =SUMIFS(TB!AE:AE,TB!$J:$J,$C18) -> 0.05252 | Z18: =SUMIFS(TB!AF:AF,TB!$J:$J,$C18) -> 0.05252 | AA18: =SUMIFS(TB!AG:AG,TB!$J:$J,$C18) -> 0.05252 | AB18: =SUMIFS(TB!AH:AH,TB!$J:$J,$C18) -> 0.05252 | AC18: =SUMIFS(TB!AI:AI,TB!$J:$J,$C18) -> 0.05252 | AD18: =SUMIFS(TB!AJ:AJ,TB!$J:$J,$C18) -> 0.05252 | AE18: =SUMIFS(TB!AK:AK,TB!$J:$J,$C18) -> 0.05252 | AF18: =SUMIFS(TB!AL:AL,TB!$J:$J,$C18) -> 0.05252 | AG18: =SUMIFS(TB!AM:AM,TB!$J:$J,$C18) -> 0.05252 | AH18: =SUMIFS(TB!AN:AN,TB!$J:$J,$C18) -> 0.05252 | AI18: =SUMIFS(TB!AO:AO,TB!$J:$J,$C18) -> 0.05252 | AK18: =P18 -> 0.05252 | AL18: =AB18 -> 0.05252 | AM18: =AI18 -> 0.05252 | AO18: =IFERROR(AVERAGE(AG18:AI18),0) -> 0.05252 | AP18: =IFERROR(AVERAGE(AD18:AI18),0) -> 0.05252 | AQ18: =IFERROR(AVERAGE(AA18:AI18),0) -> 0.05252 | AR18: =IFERROR(AVERAGE(X18:AI18),0) -> 0.05252
C19: Due from Amex | E19: =SUMIFS(TB!K:K,TB!$J:$J,$C19) -> 0.02887 | F19: =SUMIFS(TB!L:L,TB!$J:$J,$C19) -> 0.02887 | G19: =SUMIFS(TB!M:M,TB!$J:$J,$C19) -> 0.02887 | H19: =SUMIFS(TB!N:N,TB!$J:$J,$C19) -> 0.02887 | I19: =SUMIFS(TB!O:O,TB!$J:$J,$C19) -> 0.02887 | J19: =SUMIFS(TB!P:P,TB!$J:$J,$C19) -> 0.02887 | K19: =SUMIFS(TB!Q:Q,TB!$J:$J,$C19) -> 0 | L19: =SUMIFS(TB!R:R,TB!$J:$J,$C19) -> 0 | M19: =SUMIFS(TB!S:S,TB!$J:$J,$C19) -> 0 | N19: =SUMIFS(TB!T:T,TB!$J:$J,$C19) -> 0 | O19: =SUMIFS(TB!U:U,TB!$J:$J,$C19) -> 0 | P19: =SUMIFS(TB!V:V,TB!$J:$J,$C19) -> 0 | Q19: =SUMIFS(TB!W:W,TB!$J:$J,$C19) -> 0 | R19: =SUMIFS(TB!X:X,TB!$J:$J,$C19) -> 0 | S19: =SUMIFS(TB!Y:Y,TB!$J:$J,$C19) -> 0 | T19: =SUMIFS(TB!Z:Z,TB!$J:$J,$C19) -> 0 | U19: =SUMIFS(TB!AA:AA,TB!$J:$J,$C19) -> 0 | V19: =SUMIFS(TB!AB:AB,TB!$J:$J,$C19) -> 0 | W19: =SUMIFS(TB!AC:AC,TB!$J:$J,$C19) -> 0 | X19: =SUMIFS(TB!AD:AD,TB!$J:$J,$C19) -> 0 | Y19: =SUMIFS(TB!AE:AE,TB!$J:$J,$C19) -> 0 | Z19: =SUMIFS(TB!AF:AF,TB!$J:$J,$C19) -> 0 | AA19: =SUMIFS(TB!AG:AG,TB!$J:$J,$C19) -> 0 | AB19: =SUMIFS(TB!AH:AH,TB!$J:$J,$C19) -> 0 | AC19: =SUMIFS(TB!AI:AI,TB!$J:$J,$C19) -> 0 | AD19: =SUMIFS(TB!AJ:AJ,TB!$J:$J,$C19) -> 0 | AE19: =SUMIFS(TB!AK:AK,TB!$J:$J,$C19) -> 0 | AF19: =SUMIFS(TB!AL:AL,TB!$J:$J,$C19) -> 0 | AG19: =SUMIFS(TB!AM:AM,TB!$J:$J,$C19) -> 0 | AH19: =SUMIFS(TB!AN:AN,TB!$J:$J,$C19) -> 0 | AI19: =SUMIFS(TB!AO:AO,TB!$J:$J,$C19) -> 0 | AK19: =P19 -> 0 | AL19: =AB19 -> 0 | AM19: =AI19 -> 0 | AO19: =IFERROR(AVERAGE(AG19:AI19),0) -> 0 | AP19: =IFERROR(AVERAGE(AD19:AI19),0) -> 0 | AQ19: =IFERROR(AVERAGE(AA19:AI19),0) -> 0 | AR19: =IFERROR(AVERAGE(X19:AI19),0) -> 0
C20: Due from Fred | E20: =SUMIFS(TB!K:K,TB!$J:$J,$C20) -> 0.04193 | F20: =SUMIFS(TB!L:L,TB!$J:$J,$C20) -> 0.04193 | G20: =SUMIFS(TB!M:M,TB!$J:$J,$C20) -> 0.04193 | H20: =SUMIFS(TB!N:N,TB!$J:$J,$C20) -> 0.04193 | I20: =SUMIFS(TB!O:O,TB!$J:$J,$C20) -> 0.04193 | J20: =SUMIFS(TB!P:P,TB!$J:$J,$C20) -> 0.04193 | K20: =SUMIFS(TB!Q:Q,TB!$J:$J,$C20) -> 0 | L20: =SUMIFS(TB!R:R,TB!$J:$J,$C20) -> 0 | M20: =SUMIFS(TB!S:S,TB!$J:$J,$C20) -> 0 | N20: =SUMIFS(TB!T:T,TB!$J:$J,$C20) -> 0 | O20: =SUMIFS(TB!U:U,TB!$J:$J,$C20) -> 0 | P20: =SUMIFS(TB!V:V,TB!$J:$J,$C20) -> 0 | Q20: =SUMIFS(TB!W:W,TB!$J:$J,$C20) -> 0 | R20: =SUMIFS(TB!X:X,TB!$J:$J,$C20) -> 0 | S20: =SUMIFS(TB!Y:Y,TB!$J:$J,$C20) -> 0 | T20: =SUMIFS(TB!Z:Z,TB!$J:$J,$C20) -> 0 | U20: =SUMIFS(TB!AA:AA,TB!$J:$J,$C20) -> 0 | V20: =SUMIFS(TB!AB:AB,TB!$J:$J,$C20) -> 0 | W20: =SUMIFS(TB!AC:AC,TB!$J:$J,$C20) -> 0 | X20: =SUMIFS(TB!AD:AD,TB!$J:$J,$C20) -> 0 | Y20: =SUMIFS(TB!AE:AE,TB!$J:$J,$C20) -> 0 | Z20: =SUMIFS(TB!AF:AF,TB!$J:$J,$C20) -> 0 | AA20: =SUMIFS(TB!AG:AG,TB!$J:$J,$C20) -> 0 | AB20: =SUMIFS(TB!AH:AH,TB!$J:$J,$C20) -> 0 | AC20: =SUMIFS(TB!AI:AI,TB!$J:$J,$C20) -> 0 | AD20: =SUMIFS(TB!AJ:AJ,TB!$J:$J,$C20) -> 0 | AE20: =SUMIFS(TB!AK:AK,TB!$J:$J,$C20) -> 0 | AF20: =SUMIFS(TB!AL:AL,TB!$J:$J,$C20) -> 0 | AG20: =SUMIFS(TB!AM:AM,TB!$J:$J,$C20) -> 0 | AH20: =SUMIFS(TB!AN:AN,TB!$J:$J,$C20) -> 0 | AI20: =SUMIFS(TB!AO:AO,TB!$J:$J,$C20) -> 0 | AK20: =P20 -> 0 | AL20: =AB20 -> 0 | AM20: =AI20 -> 0 | AO20: =IFERROR(AVERAGE(AG20:AI20),0) -> 0 | AP20: =IFERROR(AVERAGE(AD20:AI20),0) -> 0 | AQ20: =IFERROR(AVERAGE(AA20:AI20),0) -> 0 | AR20: =IFERROR(AVERAGE(X20:AI20),0) -> 0
C21: Due from Cheri | E21: =SUMIFS(TB!K:K,TB!$J:$J,$C21) -> 0 | F21: =SUMIFS(TB!L:L,TB!$J:$J,$C21) -> 0 | G21: =SUMIFS(TB!M:M,TB!$J:$J,$C21) -> 0 | H21: =SUMIFS(TB!N:N,TB!$J:$J,$C21) -> 0 | I21: =SUMIFS(TB!O:O,TB!$J:$J,$C21) -> 0 | J21: =SUMIFS(TB!P:P,TB!$J:$J,$C21) -> 0 | K21: =SUMIFS(TB!Q:Q,TB!$J:$J,$C21) -> 0 | L21: =SUMIFS(TB!R:R,TB!$J:$J,$C21) -> 0 | M21: =SUMIFS(TB!S:S,TB!$J:$J,$C21) -> 0 | N21: =SUMIFS(TB!T:T,TB!$J:$J,$C21) -> 0 | O21: =SUMIFS(TB!U:U,TB!$J:$J,$C21) -> 0 | P21: =SUMIFS(TB!V:V,TB!$J:$J,$C21) -> 0 | Q21: =SUMIFS(TB!W:W,TB!$J:$J,$C21) -> 0 | R21: =SUMIFS(TB!X:X,TB!$J:$J,$C21) -> 0 | S21: =SUMIFS(TB!Y:Y,TB!$J:$J,$C21) -> 0 | T21: =SUMIFS(TB!Z:Z,TB!$J:$J,$C21) -> 0 | U21: =SUMIFS(TB!AA:AA,TB!$J:$J,$C21) -> 0.02 | V21: =SUMIFS(TB!AB:AB,TB!$J:$J,$C21) -> 0 | W21: =SUMIFS(TB!AC:AC,TB!$J:$J,$C21) -> 0 | X21: =SUMIFS(TB!AD:AD,TB!$J:$J,$C21) -> 0 | Y21: =SUMIFS(TB!AE:AE,TB!$J:$J,$C21) -> 0 | Z21: =SUMIFS(TB!AF:AF,TB!$J:$J,$C21) -> 0 | AA21: =SUMIFS(TB!AG:AG,TB!$J:$J,$C21) -> 0 | AB21: =SUMIFS(TB!AH:AH,TB!$J:$J,$C21) -> 0 | AC21: =SUMIFS(TB!AI:AI,TB!$J:$J,$C21) -> 0 | AD21: =SUMIFS(TB!AJ:AJ,TB!$J:$J,$C21) -> 0 | AE21: =SUMIFS(TB!AK:AK,TB!$J:$J,$C21) -> 0 | AF21: =SUMIFS(TB!AL:AL,TB!$J:$J,$C21) -> 0 | AG21: =SUMIFS(TB!AM:AM,TB!$J:$J,$C21) -> 0 | AH21: =SUMIFS(TB!AN:AN,TB!$J:$J,$C21) -> 0 | AI21: =SUMIFS(TB!AO:AO,TB!$J:$J,$C21) -> 0 | AK21: =P21 -> 0 | AL21: =AB21 -> 0 | AM21: =AI21 -> 0 | AO21: =IFERROR(AVERAGE(AG21:AI21),0) -> 0 | AP21: =IFERROR(AVERAGE(AD21:AI21),0) -> 0 | AQ21: =IFERROR(AVERAGE(AA21:AI21),0) -> 0 | AR21: =IFERROR(AVERAGE(X21:AI21),0) -> 0
C22: Other receivables | E22: =SUM(E16:E21) -> 0.3708 | F22: =SUM(F16:F21) -> 0.3708 | G22: =SUM(G16:G21) -> 0.3708 | H22: =SUM(H16:H21) -> 0.42332 | I22: =SUM(I16:I21) -> 0.42332 | J22: =SUM(J16:J21) -> 0.42332 | K22: =SUM(K16:K21) -> 0.35252 | L22: =SUM(L16:L21) -> 0.35252 | ... AI22: =SUM(AI16:AI21) -> 4.29152 | AK22: =SUM(AK16:AK21) -> 0.35252 | AL22: =SUM(AL16:AL21) -> 4.29152 | AM22: =SUM(AM16:AM21) -> 4.29152 | AO22: =SUM(AO16:AO21) -> 4.29152 | AP22: =SUM(AP16:AP21) -> 4.29152 | AQ22: =SUM(AQ16:AQ21) -> 4.29152 | AR22: =SUM(AR16:AR21) -> 3.96652
C24: Prepaid Expenses | E24: =SUMIFS(TB!K:K,TB!$J:$J,$C24) -> 0 | F24: =SUMIFS(TB!L:L,TB!$J:$J,$C24) -> 0 | G24: =SUMIFS(TB!M:M,TB!$J:$J,$C24) -> 0 | H24: =SUMIFS(TB!N:N,TB!$J:$J,$C24) -> 0 | I24: =SUMIFS(TB!O:O,TB!$J:$J,$C24) -> 0 | J24: =SUMIFS(TB!P:P,TB!$J:$J,$C24) -> 0 | K24: =SUMIFS(TB!Q:Q,TB!$J:$J,$C24) -> 0 | L24: =SUMIFS(TB!R:R,TB!$J:$J,$C24) -> 0 | M24: =SUMIFS(TB!S:S,TB!$J:$J,$C24) -> -5 | N24: =SUMIFS(TB!T:T,TB!$J:$J,$C24) -> -5 | O24: =SUMIFS(TB!U:U,TB!$J:$J,$C24) -> -5 | P24: =SUMIFS(TB!V:V,TB!$J:$J,$C24) -> -5 | Q24: =SUMIFS(TB!W:W,TB!$J:$J,$C24) -> 0 | R24: =SUMIFS(TB!X:X,TB!$J:$J,$C24) -> 0 | S24: =SUMIFS(TB!Y:Y,TB!$J:$J,$C24) -> 0 | T24: =SUMIFS(TB!Z:Z,TB!$J:$J,$C24) -> 0 | U24: =SUMIFS(TB!AA:AA,TB!$J:$J,$C24) -> 0 | V24: =SUMIFS(TB!AB:AB,TB!$J:$J,$C24) -> 0 | W24: =SUMIFS(TB!AC:AC,TB!$J:$J,$C24) -> 0 | X24: =SUMIFS(TB!AD:AD,TB!$J:$J,$C24) -> 0 | Y24: =SUMIFS(TB!AE:AE,TB!$J:$J,$C24) -> 0 | Z24: =SUMIFS(TB!AF:AF,TB!$J:$J,$C24) -> 0 | AA24: =SUMIFS(TB!AG:AG,TB!$J:$J,$C24) -> 0 | AB24: =SUMIFS(TB!AH:AH,TB!$J:$J,$C24) -> 0 | AC24: =SUMIFS(TB!AI:AI,TB!$J:$J,$C24) -> 0 | AD24: =SUMIFS(TB!AJ:AJ,TB!$J:$J,$C24) -> 0 | AE24: =SUMIFS(TB!AK:AK,TB!$J:$J,$C24) -> 0 | AF24: =SUMIFS(TB!AL:AL,TB!$J:$J,$C24) -> 0 | AG24: =SUMIFS(TB!AM:AM,TB!$J:$J,$C24) -> 0 | AH24: =SUMIFS(TB!AN:AN,TB!$J:$J,$C24) -> 0 | AI24: =SUMIFS(TB!AO:AO,TB!$J:$J,$C24) -> 0 | AK24: =P24 -> -5 | AL24: =AB24 -> 0 | AM24: =AI24 -> 0 | AO24: =IFERROR(AVERAGE(AG24:AI24),0) -> 0 | AP24: =IFERROR(AVERAGE(AD24:AI24),0) -> 0 | AQ24: =IFERROR(AVERAGE(AA24:AI24),0) -> 0 | AR24: =IFERROR(AVERAGE(X24:AI24),0) -> 0
C25: Prepaid expenses | E25: =SUM(E24:E24) -> 0 | F25: =SUM(F24:F24) -> 0 | G25: =SUM(G24:G24) -> 0 | H25: =SUM(H24:H24) -> 0 | I25: =SUM(I24:I24) -> 0 | J25: =SUM(J24:J24) -> 0 | K25: =SUM(K24:K24) -> 0 | L25: =SUM(L24:L24) -> 0 | ... AI25: =SUM(AI24:AI24) -> 0 | AK25: =SUM(AK24:AK24) -> -5 | AL25: =SUM(AL24:AL24) -> 0 | AM25: =SUM(AM24:AM24) -> 0 | AO25: =SUM(AO24:AO24) -> 0 | AP25: =SUM(AP24:AP24) -> 0 | AQ25: =SUM(AQ24:AQ24) -> 0 | AR25: =SUM(AR24:AR24) -> 0
C26: Total current assets | E26: =E11+E14+E22+E25 -> 1932.9507 | F26: =F11+F14+F22+F25 -> 1864.0996 | G26: =G11+G14+G22+G25 -> 2052.4214 | H26: =H11+H14+H22+H25 -> 2274.0476 | I26: =I11+I14+I22+I25 -> 2353.3169 | J26: =J11+J14+J22+J25 -> 2350.7604 | K26: =K11+K14+K22+K25 -> 2553.9766 | L26: =L11+L14+L22+L25 -> 3200.33 | ... AI26: =AI11+AI14+AI22+AI25 -> 2539.138 | AK26: =AK11+AK14+AK22+AK25 -> 3099.3657 | AL26: =AL11+AL14+AL22+AL25 -> 3459.2895 | AM26: =AM11+AM14+AM22+AM25 -> 2539.138 | AO26: =AO11+AO14+AO22+AO25 -> 2698.1328 | AP26: =AP11+AP14+AP22+AP25 -> 2822.5939 | AQ26: =AQ11+AQ14+AQ22+AQ25 -> 3002.2805 | AR26: =AR11+AR14+AR22+AR25 -> 3149.7783
C28: Accounts Payable | E28: =-SUMIFS(TB!K:K,TB!$J:$J,$C28) -> 102.97868 | F28: =-SUMIFS(TB!L:L,TB!$J:$J,$C28) -> 125.28342 | G28: =-SUMIFS(TB!M:M,TB!$J:$J,$C28) -> 176.99109 | H28: =-SUMIFS(TB!N:N,TB!$J:$J,$C28) -> 66.26168 | I28: =-SUMIFS(TB!O:O,TB!$J:$J,$C28) -> 116.23258 | J28: =-SUMIFS(TB!P:P,TB!$J:$J,$C28) -> 121.51023 | K28: =-SUMIFS(TB!Q:Q,TB!$J:$J,$C28) -> 187.83073 | L28: =-SUMIFS(TB!R:R,TB!$J:$J,$C28) -> 127.9124 | M28: =-SUMIFS(TB!S:S,TB!$J:$J,$C28) -> -70.61446 | N28: =-SUMIFS(TB!T:T,TB!$J:$J,$C28) -> -35.70238 | O28: =-SUMIFS(TB!U:U,TB!$J:$J,$C28) -> 175.42124 | P28: =-SUMIFS(TB!V:V,TB!$J:$J,$C28) -> 0 | Q28: =-SUMIFS(TB!W:W,TB!$J:$J,$C28) -> 57.58683 | R28: =-SUMIFS(TB!X:X,TB!$J:$J,$C28) -> 5.61409 | S28: =-SUMIFS(TB!Y:Y,TB!$J:$J,$C28) -> 95.67886 | T28: =-SUMIFS(TB!Z:Z,TB!$J:$J,$C28) -> 10.04334 | U28: =-SUMIFS(TB!AA:AA,TB!$J:$J,$C28) -> 131.57437 | V28: =-SUMIFS(TB!AB:AB,TB!$J:$J,$C28) -> 51.04859 | W28: =-SUMIFS(TB!AC:AC,TB!$J:$J,$C28) -> 118.19169 | X28: =-SUMIFS(TB!AD:AD,TB!$J:$J,$C28) -> 169.122 | Y28: =-SUMIFS(TB!AE:AE,TB!$J:$J,$C28) -> 118.87129 | Z28: =-SUMIFS(TB!AF:AF,TB!$J:$J,$C28) -> 222.6332 | AA28: =-SUMIFS(TB!AG:AG,TB!$J:$J,$C28) -> 96.1504 | AB28: =-SUMIFS(TB!AH:AH,TB!$J:$J,$C28) -> 66.37326 | AC28: =-SUMIFS(TB!AI:AI,TB!$J:$J,$C28) -> 111.65542 | AD28: =-SUMIFS(TB!AJ:AJ,TB!$J:$J,$C28) -> 144.52427 | AE28: =-SUMIFS(TB!AK:AK,TB!$J:$J,$C28) -> 237.55036 | AF28: =-SUMIFS(TB!AL:AL,TB!$J:$J,$C28) -> 57.76213 | AG28: =-SUMIFS(TB!AM:AM,TB!$J:$J,$C28) -> 154.90525 | AH28: =-SUMIFS(TB!AN:AN,TB!$J:$J,$C28) -> 105.925 | AI28: =-SUMIFS(TB!AO:AO,TB!$J:$J,$C28) -> 95.75599 | AK28: =P28 -> 0 | AL28: =AB28 -> 66.37326 | AM28: =AI28 -> 95.75599 | AO28: =IFERROR(AVERAGE(AG28:AI28),0) -> 118.86208 | AP28: =IFERROR(AVERAGE(AD28:AI28),0) -> 132.73717 | AQ28: =IFERROR(AVERAGE(AA28:AI28),0) -> 118.95579 | AR28: =IFERROR(AVERAGE(X28:AI28),0) -> 131.76905
C29: Accounts payable | E29: =SUM(E28:E28) -> 102.97868 | F29: =SUM(F28:F28) -> 125.28342 | G29: =SUM(G28:G28) -> 176.99109 | H29: =SUM(H28:H28) -> 66.26168 | I29: =SUM(I28:I28) -> 116.23258 | J29: =SUM(J28:J28) -> 121.51023 | K29: =SUM(K28:K28) -> 187.83073 | L29: =SUM(L28:L28) -> 127.9124 | ... AI29: =SUM(AI28:AI28) -> 95.75599 | AK29: =SUM(AK28:AK28) -> 0 | AL29: =SUM(AL28:AL28) -> 66.37326 | AM29: =SUM(AM28:AM28) -> 95.75599 | AO29: =SUM(AO28:AO28) -> 118.86208 | AP29: =SUM(AP28:AP28) -> 132.73717 | AQ29: =SUM(AQ28:AQ28) -> 118.95579 | AR29: =SUM(AR28:AR28) -> 131.76905
C31: Due to The Hartford | E31: =-SUMIFS(TB!K:K,TB!$J:$J,$C31) -> 0 | F31: =-SUMIFS(TB!L:L,TB!$J:$J,$C31) -> 0 | G31: =-SUMIFS(TB!M:M,TB!$J:$J,$C31) -> 0 | H31: =-SUMIFS(TB!N:N,TB!$J:$J,$C31) -> 0 | I31: =-SUMIFS(TB!O:O,TB!$J:$J,$C31) -> 0 | J31: =-SUMIFS(TB!P:P,TB!$J:$J,$C31) -> 0 | K31: =-SUMIFS(TB!Q:Q,TB!$J:$J,$C31) -> 0 | L31: =-SUMIFS(TB!R:R,TB!$J:$J,$C31) -> 0 | M31: =-SUMIFS(TB!S:S,TB!$J:$J,$C31) -> 0 | N31: =-SUMIFS(TB!T:T,TB!$J:$J,$C31) -> 0 | O31: =-SUMIFS(TB!U:U,TB!$J:$J,$C31) -> 0 | P31: =-SUMIFS(TB!V:V,TB!$J:$J,$C31) -> 0 | Q31: =-SUMIFS(TB!W:W,TB!$J:$J,$C31) -> 0 | R31: =-SUMIFS(TB!X:X,TB!$J:$J,$C31) -> 0 | S31: =-SUMIFS(TB!Y:Y,TB!$J:$J,$C31) -> 0 | T31: =-SUMIFS(TB!Z:Z,TB!$J:$J,$C31) -> 0 | U31: =-SUMIFS(TB!AA:AA,TB!$J:$J,$C31) -> 0 | V31: =-SUMIFS(TB!AB:AB,TB!$J:$J,$C31) -> 0 | W31: =-SUMIFS(TB!AC:AC,TB!$J:$J,$C31) -> 15.655 | X31: =-SUMIFS(TB!AD:AD,TB!$J:$J,$C31) -> 15.655 | Y31: =-SUMIFS(TB!AE:AE,TB!$J:$J,$C31) -> 15.655 | Z31: =-SUMIFS(TB!AF:AF,TB!$J:$J,$C31) -> 15.655 | AA31: =-SUMIFS(TB!AG:AG,TB!$J:$J,$C31) -> 15.655 | AB31: =-SUMIFS(TB!AH:AH,TB!$J:$J,$C31) -> 15.655 | AC31: =-SUMIFS(TB!AI:AI,TB!$J:$J,$C31) -> 15.655 | AD31: =-SUMIFS(TB!AJ:AJ,TB!$J:$J,$C31) -> 15.655 | AE31: =-SUMIFS(TB!AK:AK,TB!$J:$J,$C31) -> 15.655 | AF31: =-SUMIFS(TB!AL:AL,TB!$J:$J,$C31) -> 15.655 | AG31: =-SUMIFS(TB!AM:AM,TB!$J:$J,$C31) -> 15.655 | AH31: =-SUMIFS(TB!AN:AN,TB!$J:$J,$C31) -> 15.655 | AI31: =-SUMIFS(TB!AO:AO,TB!$J:$J,$C31) -> 15.655 | AK31: =P31 -> 0 | AL31: =AB31 -> 15.655 | AM31: =AI31 -> 15.655 | AO31: =IFERROR(AVERAGE(AG31:AI31),0) -> 15.655 | AP31: =IFERROR(AVERAGE(AD31:AI31),0) -> 15.655 | AQ31: =IFERROR(AVERAGE(AA31:AI31),0) -> 15.655 | AR31: =IFERROR(AVERAGE(X31:AI31),0) -> 15.655
C32: Due to BCBSA | E32: =-SUMIFS(TB!K:K,TB!$J:$J,$C32) -> 0 | F32: =-SUMIFS(TB!L:L,TB!$J:$J,$C32) -> 0 | G32: =-SUMIFS(TB!M:M,TB!$J:$J,$C32) -> 0 | H32: =-SUMIFS(TB!N:N,TB!$J:$J,$C32) -> 0 | I32: =-SUMIFS(TB!O:O,TB!$J:$J,$C32) -> 0 | J32: =-SUMIFS(TB!P:P,TB!$J:$J,$C32) -> 0 | K32: =-SUMIFS(TB!Q:Q,TB!$J:$J,$C32) -> 0 | L32: =-SUMIFS(TB!R:R,TB!$J:$J,$C32) -> 0 | M32: =-SUMIFS(TB!S:S,TB!$J:$J,$C32) -> 0 | N32: =-SUMIFS(TB!T:T,TB!$J:$J,$C32) -> 0 | O32: =-SUMIFS(TB!U:U,TB!$J:$J,$C32) -> 0 | P32: =-SUMIFS(TB!V:V,TB!$J:$J,$C32) -> 0 | Q32: =-SUMIFS(TB!W:W,TB!$J:$J,$C32) -> 0 | R32: =-SUMIFS(TB!X:X,TB!$J:$J,$C32) -> 0 | S32: =-SUMIFS(TB!Y:Y,TB!$J:$J,$C32) -> 0 | T32: =-SUMIFS(TB!Z:Z,TB!$J:$J,$C32) -> 0 | U32: =-SUMIFS(TB!AA:AA,TB!$J:$J,$C32) -> 0 | V32: =-SUMIFS(TB!AB:AB,TB!$J:$J,$C32) -> 0 | W32: =-SUMIFS(TB!AC:AC,TB!$J:$J,$C32) -> 0 | X32: =-SUMIFS(TB!AD:AD,TB!$J:$J,$C32) -> 0 | Y32: =-SUMIFS(TB!AE:AE,TB!$J:$J,$C32) -> 0 | Z32: =-SUMIFS(TB!AF:AF,TB!$J:$J,$C32) -> 0 | AA32: =-SUMIFS(TB!AG:AG,TB!$J:$J,$C32) -> 0 | AB32: =-SUMIFS(TB!AH:AH,TB!$J:$J,$C32) -> 0 | AC32: =-SUMIFS(TB!AI:AI,TB!$J:$J,$C32) -> 0 | AD32: =-SUMIFS(TB!AJ:AJ,TB!$J:$J,$C32) -> 0 | AE32: =-SUMIFS(TB!AK:AK,TB!$J:$J,$C32) -> 0 | AF32: =-SUMIFS(TB!AL:AL,TB!$J:$J,$C32) -> 0 | AG32: =-SUMIFS(TB!AM:AM,TB!$J:$J,$C32) -> 0 | AH32: =-SUMIFS(TB!AN:AN,TB!$J:$J,$C32) -> 0.58 | AI32: =-SUMIFS(TB!AO:AO,TB!$J:$J,$C32) -> 0.58 | AK32: =P32 -> 0 | AL32: =AB32 -> 0 | AM32: =AI32 -> 0.58 | AO32: =IFERROR(AVERAGE(AG32:AI32),0) -> 0.38666667 | AP32: =IFERROR(AVERAGE(AD32:AI32),0) -> 0.19333333 | AQ32: =IFERROR(AVERAGE(AA32:AI32),0) -> 0.12888889 | AR32: =IFERROR(AVERAGE(X32:AI32),0) -> 0.096666667
C33: Shareholder Loan-Due to Ken | E33: =-SUMIFS(TB!K:K,TB!$J:$J,$C33) -> 0 | F33: =-SUMIFS(TB!L:L,TB!$J:$J,$C33) -> 0 | G33: =-SUMIFS(TB!M:M,TB!$J:$J,$C33) -> 0 | H33: =-SUMIFS(TB!N:N,TB!$J:$J,$C33) -> 0 | I33: =-SUMIFS(TB!O:O,TB!$J:$J,$C33) -> 0 | J33: =-SUMIFS(TB!P:P,TB!$J:$J,$C33) -> 0 | K33: =-SUMIFS(TB!Q:Q,TB!$J:$J,$C33) -> 0 | L33: =-SUMIFS(TB!R:R,TB!$J:$J,$C33) -> 0 | M33: =-SUMIFS(TB!S:S,TB!$J:$J,$C33) -> 0 | N33: =-SUMIFS(TB!T:T,TB!$J:$J,$C33) -> 0 | O33: =-SUMIFS(TB!U:U,TB!$J:$J,$C33) -> 0 | P33: =-SUMIFS(TB!V:V,TB!$J:$J,$C33) -> 1.21938 | Q33: =-SUMIFS(TB!W:W,TB!$J:$J,$C33) -> 1.21938 | R33: =-SUMIFS(TB!X:X,TB!$J:$J,$C33) -> 1.21938 | S33: =-SUMIFS(TB!Y:Y,TB!$J:$J,$C33) -> 1.21938 | T33: =-SUMIFS(TB!Z:Z,TB!$J:$J,$C33) -> 1.21938 | U33: =-SUMIFS(TB!AA:AA,TB!$J:$J,$C33) -> 1.21938 | V33: =-SUMIFS(TB!AB:AB,TB!$J:$J,$C33) -> 1.21938 | W33: =-SUMIFS(TB!AC:AC,TB!$J:$J,$C33) -> 1.21938 | X33: =-SUMIFS(TB!AD:AD,TB!$J:$J,$C33) -> 1.21938 | Y33: =-SUMIFS(TB!AE:AE,TB!$J:$J,$C33) -> 1.21938 | Z33: =-SUMIFS(TB!AF:AF,TB!$J:$J,$C33) -> 1.21938 | AA33: =-SUMIFS(TB!AG:AG,TB!$J:$J,$C33) -> 0 | AB33: =-SUMIFS(TB!AH:AH,TB!$J:$J,$C33) -> 67.84569 | AC33: =-SUMIFS(TB!AI:AI,TB!$J:$J,$C33) -> 67.84569 | AD33: =-SUMIFS(TB!AJ:AJ,TB!$J:$J,$C33) -> 67.84569 | AE33: =-SUMIFS(TB!AK:AK,TB!$J:$J,$C33) -> 67.84569 | AF33: =-SUMIFS(TB!AL:AL,TB!$J:$J,$C33) -> 0 | AG33: =-SUMIFS(TB!AM:AM,TB!$J:$J,$C33) -> 0 | AH33: =-SUMIFS(TB!AN:AN,TB!$J:$J,$C33) -> 0 | AI33: =-SUMIFS(TB!AO:AO,TB!$J:$J,$C33) -> 0 | AK33: =P33 -> 1.21938 | AL33: =AB33 -> 67.84569 | AM33: =AI33 -> 0 | AO33: =IFERROR(AVERAGE(AG33:AI33),0) -> 0 | AP33: =IFERROR(AVERAGE(AD33:AI33),0) -> 22.61523 | AQ33: =IFERROR(AVERAGE(AA33:AI33),0) -> 30.15364 | AR33: =IFERROR(AVERAGE(X33:AI33),0) -> 22.920075
C34: Due to Exodus | E34: =-SUMIFS(TB!K:K,TB!$J:$J,$C34) -> 15 | F34: =-SUMIFS(TB!L:L,TB!$J:$J,$C34) -> 15 | G34: =-SUMIFS(TB!M:M,TB!$J:$J,$C34) -> 15 | H34: =-SUMIFS(TB!N:N,TB!$J:$J,$C34) -> 15 | I34: =-SUMIFS(TB!O:O,TB!$J:$J,$C34) -> 15 | J34: =-SUMIFS(TB!P:P,TB!$J:$J,$C34) -> 15 | K34: =-SUMIFS(TB!Q:Q,TB!$J:$J,$C34) -> 15 | L34: =-SUMIFS(TB!R:R,TB!$J:$J,$C34) -> 0 | M34: =-SUMIFS(TB!S:S,TB!$J:$J,$C34) -> 0 | N34: =-SUMIFS(TB!T:T,TB!$J:$J,$C34) -> 0 | O34: =-SUMIFS(TB!U:U,TB!$J:$J,$C34) -> 0 | P34: =-SUMIFS(TB!V:V,TB!$J:$J,$C34) -> 0 | Q34: =-SUMIFS(TB!W:W,TB!$J:$J,$C34) -> 0 | R34: =-SUMIFS(TB!X:X,TB!$J:$J,$C34) -> 0 | S34: =-SUMIFS(TB!Y:Y,TB!$J:$J,$C34) -> 0 | T34: =-SUMIFS(TB!Z:Z,TB!$J:$J,$C34) -> 0 | U34: =-SUMIFS(TB!AA:AA,TB!$J:$J,$C34) -> 0 | V34: =-SUMIFS(TB!AB:AB,TB!$J:$J,$C34) -> 0 | W34: =-SUMIFS(TB!AC:AC,TB!$J:$J,$C34) -> 0 | X34: =-SUMIFS(TB!AD:AD,TB!$J:$J,$C34) -> 0 | Y34: =-SUMIFS(TB!AE:AE,TB!$J:$J,$C34) -> 0 | Z34: =-SUMIFS(TB!AF:AF,TB!$J:$J,$C34) -> 0 | AA34: =-SUMIFS(TB!AG:AG,TB!$J:$J,$C34) -> 0 | AB34: =-SUMIFS(TB!AH:AH,TB!$J:$J,$C34) -> 0 | AC34: =-SUMIFS(TB!AI:AI,TB!$J:$J,$C34) -> 0 | AD34: =-SUMIFS(TB!AJ:AJ,TB!$J:$J,$C34) -> 0 | AE34: =-SUMIFS(TB!AK:AK,TB!$J:$J,$C34) -> 0 | AF34: =-SUMIFS(TB!AL:AL,TB!$J:$J,$C34) -> 0 | AG34: =-SUMIFS(TB!AM:AM,TB!$J:$J,$C34) -> 0 | AH34: =-SUMIFS(TB!AN:AN,TB!$J:$J,$C34) -> 0 | AI34: =-SUMIFS(TB!AO:AO,TB!$J:$J,$C34) -> 0 | AK34: =P34 -> 0 | AL34: =AB34 -> 0 | AM34: =AI34 -> 0 | AO34: =IFERROR(AVERAGE(AG34:AI34),0) -> 0 | AP34: =IFERROR(AVERAGE(AD34:AI34),0) -> 0 | AQ34: =IFERROR(AVERAGE(AA34:AI34),0) -> 0 | AR34: =IFERROR(AVERAGE(X34:AI34),0) -> 0
C35: Other payables | E35: =SUM(E31:E34) -> 15 | F35: =SUM(F31:F34) -> 15 | G35: =SUM(G31:G34) -> 15 | H35: =SUM(H31:H34) -> 15 | I35: =SUM(I31:I34) -> 15 | J35: =SUM(J31:J34) -> 15 | K35: =SUM(K31:K34) -> 15 | L35: =SUM(L31:L34) -> 0 | ... AI35: =SUM(AI31:AI34) -> 16.235 | AK35: =SUM(AK31:AK34) -> 1.21938 | AL35: =SUM(AL31:AL34) -> 83.50069 | AM35: =SUM(AM31:AM34) -> 16.235 | AO35: =SUM(AO31:AO34) -> 16.041667 | AP35: =SUM(AP31:AP34) -> 38.463563 | AQ35: =SUM(AQ31:AQ34) -> 45.937529 | AR35: =SUM(AR31:AR34) -> 38.671742
C37: Unearned Revenue | E37: =-SUMIFS(TB!K:K,TB!$J:$J,$C37) -> 1166.1135 | F37: =-SUMIFS(TB!L:L,TB!$J:$J,$C37) -> 1166.1135 | G37: =-SUMIFS(TB!M:M,TB!$J:$J,$C37) -> 1166.1135 | H37: =-SUMIFS(TB!N:N,TB!$J:$J,$C37) -> 1166.1135 | I37: =-SUMIFS(TB!O:O,TB!$J:$J,$C37) -> 1166.1135 | J37: =-SUMIFS(TB!P:P,TB!$J:$J,$C37) -> 1166.1135 | K37: =-SUMIFS(TB!Q:Q,TB!$J:$J,$C37) -> 1166.1135 | L37: =-SUMIFS(TB!R:R,TB!$J:$J,$C37) -> 1166.1135 | M37: =-SUMIFS(TB!S:S,TB!$J:$J,$C37) -> 1166.1135 | N37: =-SUMIFS(TB!T:T,TB!$J:$J,$C37) -> 1166.1135 | O37: =-SUMIFS(TB!U:U,TB!$J:$J,$C37) -> 1166.1135 | P37: =-SUMIFS(TB!V:V,TB!$J:$J,$C37) -> 1112.584 | Q37: =-SUMIFS(TB!W:W,TB!$J:$J,$C37) -> 1112.584 | R37: =-SUMIFS(TB!X:X,TB!$J:$J,$C37) -> 1112.584 | S37: =-SUMIFS(TB!Y:Y,TB!$J:$J,$C37) -> 1000.846 | T37: =-SUMIFS(TB!Z:Z,TB!$J:$J,$C37) -> 1000.846 | U37: =-SUMIFS(TB!AA:AA,TB!$J:$J,$C37) -> 1000.846 | V37: =-SUMIFS(TB!AB:AB,TB!$J:$J,$C37) -> 1000.846 | W37: =-SUMIFS(TB!AC:AC,TB!$J:$J,$C37) -> 933.346 | X37: =-SUMIFS(TB!AD:AD,TB!$J:$J,$C37) -> 933.346 | Y37: =-SUMIFS(TB!AE:AE,TB!$J:$J,$C37) -> 933.346 | Z37: =-SUMIFS(TB!AF:AF,TB!$J:$J,$C37) -> 933.346 | AA37: =-SUMIFS(TB!AG:AG,TB!$J:$J,$C37) -> 933.346 | AB37: =-SUMIFS(TB!AH:AH,TB!$J:$J,$C37) -> 925.17 | AC37: =-SUMIFS(TB!AI:AI,TB!$J:$J,$C37) -> 925.17 | AD37: =-SUMIFS(TB!AJ:AJ,TB!$J:$J,$C37) -> 925.17 | AE37: =-SUMIFS(TB!AK:AK,TB!$J:$J,$C37) -> 851.17 | AF37: =-SUMIFS(TB!AL:AL,TB!$J:$J,$C37) -> 851.17 | AG37: =-SUMIFS(TB!AM:AM,TB!$J:$J,$C37) -> 851.17 | AH37: =-SUMIFS(TB!AN:AN,TB!$J:$J,$C37) -> 851.17 | AI37: =-SUMIFS(TB!AO:AO,TB!$J:$J,$C37) -> 810.145 | AK37: =P37 -> 1112.584 | AL37: =AB37 -> 925.17 | AM37: =AI37 -> 810.145 | AO37: =IFERROR(AVERAGE(AG37:AI37),0) -> 837.495 | AP37: =IFERROR(AVERAGE(AD37:AI37),0) -> 856.66583 | AQ37: =IFERROR(AVERAGE(AA37:AI37),0) -> 880.409 | AR37: =IFERROR(AVERAGE(X37:AI37),0) -> 893.64325
C38: Unearned revenue | E38: =SUM(E37:E37) -> 1166.1135 | F38: =SUM(F37:F37) -> 1166.1135 | G38: =SUM(G37:G37) -> 1166.1135 | H38: =SUM(H37:H37) -> 1166.1135 | I38: =SUM(I37:I37) -> 1166.1135 | J38: =SUM(J37:J37) -> 1166.1135 | K38: =SUM(K37:K37) -> 1166.1135 | L38: =SUM(L37:L37) -> 1166.1135 | ... AI38: =SUM(AI37:AI37) -> 810.145 | AK38: =SUM(AK37:AK37) -> 1112.584 | AL38: =SUM(AL37:AL37) -> 925.17 | AM38: =SUM(AM37:AM37) -> 810.145 | AO38: =SUM(AO37:AO37) -> 837.495 | AP38: =SUM(AP37:AP37) -> 856.66583 | AQ38: =SUM(AQ37:AQ37) -> 880.409 | AR38: =SUM(AR37:AR37) -> 893.64325
C40: Accrued Bonuses | E40: =-SUMIFS(TB!K:K,TB!$J:$J,$C40) -> 48.5 | F40: =-SUMIFS(TB!L:L,TB!$J:$J,$C40) -> 97 | G40: =-SUMIFS(TB!M:M,TB!$J:$J,$C40) -> 145.5 | H40: =-SUMIFS(TB!N:N,TB!$J:$J,$C40) -> 194 | I40: =-SUMIFS(TB!O:O,TB!$J:$J,$C40) -> 242.5 | J40: =-SUMIFS(TB!P:P,TB!$J:$J,$C40) -> 291 | K40: =-SUMIFS(TB!Q:Q,TB!$J:$J,$C40) -> 339.5 | L40: =-SUMIFS(TB!R:R,TB!$J:$J,$C40) -> 388 | M40: =-SUMIFS(TB!S:S,TB!$J:$J,$C40) -> 436.5 | N40: =-SUMIFS(TB!T:T,TB!$J:$J,$C40) -> 485 | O40: =-SUMIFS(TB!U:U,TB!$J:$J,$C40) -> 533.5 | P40: =-SUMIFS(TB!V:V,TB!$J:$J,$C40) -> 0 | Q40: =-SUMIFS(TB!W:W,TB!$J:$J,$C40) -> 51.25 | R40: =-SUMIFS(TB!X:X,TB!$J:$J,$C40) -> 102.5 | S40: =-SUMIFS(TB!Y:Y,TB!$J:$J,$C40) -> 153.75 | T40: =-SUMIFS(TB!Z:Z,TB!$J:$J,$C40) -> 205 | U40: =-SUMIFS(TB!AA:AA,TB!$J:$J,$C40) -> 256.25 | V40: =-SUMIFS(TB!AB:AB,TB!$J:$J,$C40) -> 307.5 | W40: =-SUMIFS(TB!AC:AC,TB!$J:$J,$C40) -> 358.75 | X40: =-SUMIFS(TB!AD:AD,TB!$J:$J,$C40) -> 410 | Y40: =-SUMIFS(TB!AE:AE,TB!$J:$J,$C40) -> 461.25 | Z40: =-SUMIFS(TB!AF:AF,TB!$J:$J,$C40) -> 0 | AA40: =-SUMIFS(TB!AG:AG,TB!$J:$J,$C40) -> 0 | AB40: =-SUMIFS(TB!AH:AH,TB!$J:$J,$C40) -> 0 | AC40: =-SUMIFS(TB!AI:AI,TB!$J:$J,$C40) -> 0 | AD40: =-SUMIFS(TB!AJ:AJ,TB!$J:$J,$C40) -> 102.5 | AE40: =-SUMIFS(TB!AK:AK,TB!$J:$J,$C40) -> 153.75 | AF40: =-SUMIFS(TB!AL:AL,TB!$J:$J,$C40) -> 205 | AG40: =-SUMIFS(TB!AM:AM,TB!$J:$J,$C40) -> 256.25 | AH40: =-SUMIFS(TB!AN:AN,TB!$J:$J,$C40) -> 307.5 | AI40: =-SUMIFS(TB!AO:AO,TB!$J:$J,$C40) -> 358.75 | AK40: =P40 -> 0 | AL40: =AB40 -> 0 | AM40: =AI40 -> 358.75 | AO40: =IFERROR(AVERAGE(AG40:AI40),0) -> 307.5 | AP40: =IFERROR(AVERAGE(AD40:AI40),0) -> 230.625 | AQ40: =IFERROR(AVERAGE(AA40:AI40),0) -> 153.75 | AR40: =IFERROR(AVERAGE(X40:AI40),0) -> 187.91667
C41: Pension Payable | E41: =-SUMIFS(TB!K:K,TB!$J:$J,$C41) -> 103.44607 | F41: =-SUMIFS(TB!L:L,TB!$J:$J,$C41) -> 103.44607 | G41: =-SUMIFS(TB!M:M,TB!$J:$J,$C41) -> 103.44607 | H41: =-SUMIFS(TB!N:N,TB!$J:$J,$C41) -> 103.44607 | I41: =-SUMIFS(TB!O:O,TB!$J:$J,$C41) -> 0 | J41: =-SUMIFS(TB!P:P,TB!$J:$J,$C41) -> 0 | K41: =-SUMIFS(TB!Q:Q,TB!$J:$J,$C41) -> 0 | L41: =-SUMIFS(TB!R:R,TB!$J:$J,$C41) -> 0 | M41: =-SUMIFS(TB!S:S,TB!$J:$J,$C41) -> 0 | N41: =-SUMIFS(TB!T:T,TB!$J:$J,$C41) -> 0 | O41: =-SUMIFS(TB!U:U,TB!$J:$J,$C41) -> 0 | P41: =-SUMIFS(TB!V:V,TB!$J:$J,$C41) -> 91.93914 | Q41: =-SUMIFS(TB!W:W,TB!$J:$J,$C41) -> 91.93914 | R41: =-SUMIFS(TB!X:X,TB!$J:$J,$C41) -> 91.93914 | S41: =-SUMIFS(TB!Y:Y,TB!$J:$J,$C41) -> 91.93914 | T41: =-SUMIFS(TB!Z:Z,TB!$J:$J,$C41) -> 91.93914 | U41: =-SUMIFS(TB!AA:AA,TB!$J:$J,$C41) -> 0 | V41: =-SUMIFS(TB!AB:AB,TB!$J:$J,$C41) -> 0 | W41: =-SUMIFS(TB!AC:AC,TB!$J:$J,$C41) -> 0 | X41: =-SUMIFS(TB!AD:AD,TB!$J:$J,$C41) -> 0 | Y41: =-SUMIFS(TB!AE:AE,TB!$J:$J,$C41) -> 0 | Z41: =-SUMIFS(TB!AF:AF,TB!$J:$J,$C41) -> 0 | AA41: =-SUMIFS(TB!AG:AG,TB!$J:$J,$C41) -> 0 | AB41: =-SUMIFS(TB!AH:AH,TB!$J:$J,$C41) -> 87.32589 | AC41: =-SUMIFS(TB!AI:AI,TB!$J:$J,$C41) -> 87.32589 | AD41: =-SUMIFS(TB!AJ:AJ,TB!$J:$J,$C41) -> 87.32589 | AE41: =-SUMIFS(TB!AK:AK,TB!$J:$J,$C41) -> 87.32589 | AF41: =-SUMIFS(TB!AL:AL,TB!$J:$J,$C41) -> 0 | AG41: =-SUMIFS(TB!AM:AM,TB!$J:$J,$C41) -> 0 | AH41: =-SUMIFS(TB!AN:AN,TB!$J:$J,$C41) -> 0 | AI41: =-SUMIFS(TB!AO:AO,TB!$J:$J,$C41) -> 0 | AK41: =P41 -> 91.93914 | AL41: =AB41 -> 87.32589 | AM41: =AI41 -> 0 | AO41: =IFERROR(AVERAGE(AG41:AI41),0) -> 0 | AP41: =IFERROR(AVERAGE(AD41:AI41),0) -> 29.10863 | AQ41: =IFERROR(AVERAGE(AA41:AI41),0) -> 38.811507 | AR41: =IFERROR(AVERAGE(X41:AI41),0) -> 29.10863
C42: 401k contributions due | E42: =-SUMIFS(TB!K:K,TB!$J:$J,$C42) -> 8.05888 | F42: =-SUMIFS(TB!L:L,TB!$J:$J,$C42) -> 8.84102 | G42: =-SUMIFS(TB!M:M,TB!$J:$J,$C42) -> 8.84102 | H42: =-SUMIFS(TB!N:N,TB!$J:$J,$C42) -> 8.88102 | I42: =-SUMIFS(TB!O:O,TB!$J:$J,$C42) -> 8.75602 | J42: =-SUMIFS(TB!P:P,TB!$J:$J,$C42) -> 8.75602 | K42: =-SUMIFS(TB!Q:Q,TB!$J:$J,$C42) -> 8.28408 | L42: =-SUMIFS(TB!R:R,TB!$J:$J,$C42) -> 8.28408 | M42: =-SUMIFS(TB!S:S,TB!$J:$J,$C42) -> 6.29658 | N42: =-SUMIFS(TB!T:T,TB!$J:$J,$C42) -> 9.04258 | O42: =-SUMIFS(TB!U:U,TB!$J:$J,$C42) -> 9.04258 | P42: =-SUMIFS(TB!V:V,TB!$J:$J,$C42) -> 34.04452 | Q42: =-SUMIFS(TB!W:W,TB!$J:$J,$C42) -> 9.04258 | R42: =-SUMIFS(TB!X:X,TB!$J:$J,$C42) -> 9.26258 | S42: =-SUMIFS(TB!Y:Y,TB!$J:$J,$C42) -> 9.26258 | T42: =-SUMIFS(TB!Z:Z,TB!$J:$J,$C42) -> 9.27011 | U42: =-SUMIFS(TB!AA:AA,TB!$J:$J,$C42) -> 9.27011 | V42: =-SUMIFS(TB!AB:AB,TB!$J:$J,$C42) -> 9.26258 | W42: =-SUMIFS(TB!AC:AC,TB!$J:$J,$C42) -> 9.27011 | X42: =-SUMIFS(TB!AD:AD,TB!$J:$J,$C42) -> 9.27011 | Y42: =-SUMIFS(TB!AE:AE,TB!$J:$J,$C42) -> 9.27011 | Z42: =-SUMIFS(TB!AF:AF,TB!$J:$J,$C42) -> 9.39784 | AA42: =-SUMIFS(TB!AG:AG,TB!$J:$J,$C42) -> 7.64716 | AB42: =-SUMIFS(TB!AH:AH,TB!$J:$J,$C42) -> 7.98016 | AC42: =-SUMIFS(TB!AI:AI,TB!$J:$J,$C42) -> 8.00942 | AD42: =-SUMIFS(TB!AJ:AJ,TB!$J:$J,$C42) -> 8.00942 | AE42: =-SUMIFS(TB!AK:AK,TB!$J:$J,$C42) -> 17.01345 | AF42: =-SUMIFS(TB!AL:AL,TB!$J:$J,$C42) -> 8.50942 | AG42: =-SUMIFS(TB!AM:AM,TB!$J:$J,$C42) -> 8.38672 | AH42: =-SUMIFS(TB!AN:AN,TB!$J:$J,$C42) -> 8.38672 | AI42: =-SUMIFS(TB!AO:AO,TB!$J:$J,$C42) -> 0 | AK42: =P42 -> 34.04452 | AL42: =AB42 -> 7.98016 | AM42: =AI42 -> 0 | AO42: =IFERROR(AVERAGE(AG42:AI42),0) -> 5.5911467 | AP42: =IFERROR(AVERAGE(AD42:AI42),0) -> 8.3842883 | AQ42: =IFERROR(AVERAGE(AA42:AI42),0) -> 8.21583 | AR42: =IFERROR(AVERAGE(X42:AI42),0) -> 8.4900442
C43: Payroll liabilities | E43: =SUM(E40:E42) -> 160.00495 | F43: =SUM(F40:F42) -> 209.28709 | G43: =SUM(G40:G42) -> 257.78709 | H43: =SUM(H40:H42) -> 306.32709 | I43: =SUM(I40:I42) -> 251.25602 | J43: =SUM(J40:J42) -> 299.75602 | K43: =SUM(K40:K42) -> 347.78408 | L43: =SUM(L40:L42) -> 396.28408 | ... AI43: =SUM(AI40:AI42) -> 358.75 | AK43: =SUM(AK40:AK42) -> 125.98366 | AL43: =SUM(AL40:AL42) -> 95.30605 | AM43: =SUM(AM40:AM42) -> 358.75 | AO43: =SUM(AO40:AO42) -> 313.09115 | AP43: =SUM(AP40:AP42) -> 268.11792 | AQ43: =SUM(AQ40:AQ42) -> 200.77734 | AR43: =SUM(AR40:AR42) -> 225.51534
C45: Zeldis American Express | E45: =-SUMIFS(TB!K:K,TB!$J:$J,$C45) -> 4.99889 | F45: =-SUMIFS(TB!L:L,TB!$J:$J,$C45) -> 11.54903 | G45: =-SUMIFS(TB!M:M,TB!$J:$J,$C45) -> 0.10635 | H45: =-SUMIFS(TB!N:N,TB!$J:$J,$C45) -> 5.72126 | I45: =-SUMIFS(TB!O:O,TB!$J:$J,$C45) -> 1.63473 | J45: =-SUMIFS(TB!P:P,TB!$J:$J,$C45) -> 1.62597 | K45: =-SUMIFS(TB!Q:Q,TB!$J:$J,$C45) -> 2.94612 | L45: =-SUMIFS(TB!R:R,TB!$J:$J,$C45) -> 1.34899 | M45: =-SUMIFS(TB!S:S,TB!$J:$J,$C45) -> 0.2138 | N45: =-SUMIFS(TB!T:T,TB!$J:$J,$C45) -> 0.66918 | O45: =-SUMIFS(TB!U:U,TB!$J:$J,$C45) -> 5.42513 | P45: =-SUMIFS(TB!V:V,TB!$J:$J,$C45) -> 5.60014 | Q45: =-SUMIFS(TB!W:W,TB!$J:$J,$C45) -> 4.88868 | R45: =-SUMIFS(TB!X:X,TB!$J:$J,$C45) -> 1.1119 | S45: =-SUMIFS(TB!Y:Y,TB!$J:$J,$C45) -> 5.43933 | T45: =-SUMIFS(TB!Z:Z,TB!$J:$J,$C45) -> 3.84379 | U45: =-SUMIFS(TB!AA:AA,TB!$J:$J,$C45) -> 0.43464 | V45: =-SUMIFS(TB!AB:AB,TB!$J:$J,$C45) -> 5.49789 | W45: =-SUMIFS(TB!AC:AC,TB!$J:$J,$C45) -> 4.19833 | X45: =-SUMIFS(TB!AD:AD,TB!$J:$J,$C45) -> 4.02806 | Y45: =-SUMIFS(TB!AE:AE,TB!$J:$J,$C45) -> 0 | Z45: =-SUMIFS(TB!AF:AF,TB!$J:$J,$C45) -> 3.46022 | AA45: =-SUMIFS(TB!AG:AG,TB!$J:$J,$C45) -> 4.39943 | AB45: =-SUMIFS(TB!AH:AH,TB!$J:$J,$C45) -> 3.90425 | AC45: =-SUMIFS(TB!AI:AI,TB!$J:$J,$C45) -> 3.98306 | AD45: =-SUMIFS(TB!AJ:AJ,TB!$J:$J,$C45) -> 2.30298 | AE45: =-SUMIFS(TB!AK:AK,TB!$J:$J,$C45) -> 3.40988 | AF45: =-SUMIFS(TB!AL:AL,TB!$J:$J,$C45) -> 5.76356 | AG45: =-SUMIFS(TB!AM:AM,TB!$J:$J,$C45) -> 3.06282 | AH45: =-SUMIFS(TB!AN:AN,TB!$J:$J,$C45) -> 3.19919 | AI45: =-SUMIFS(TB!AO:AO,TB!$J:$J,$C45) -> 4.85422 | AK45: =P45 -> 5.60014 | AL45: =AB45 -> 3.90425 | AM45: =AI45 -> 4.85422 | AO45: =IFERROR(AVERAGE(AG45:AI45),0) -> 3.70541 | AP45: =IFERROR(AVERAGE(AD45:AI45),0) -> 3.7654417 | AQ45: =IFERROR(AVERAGE(AA45:AI45),0) -> 3.8754878 | AR45: =IFERROR(AVERAGE(X45:AI45),0) -> 3.5306392
C46: Credit cards payable | E46: =SUM(E45:E45) -> 4.99889 | F46: =SUM(F45:F45) -> 11.54903 | G46: =SUM(G45:G45) -> 0.10635 | H46: =SUM(H45:H45) -> 5.72126 | I46: =SUM(I45:I45) -> 1.63473 | J46: =SUM(J45:J45) -> 1.62597 | K46: =SUM(K45:K45) -> 2.94612 | L46: =SUM(L45:L45) -> 1.34899 | ... AI46: =SUM(AI45:AI45) -> 4.85422 | AK46: =SUM(AK45:AK45) -> 5.60014 | AL46: =SUM(AL45:AL45) -> 3.90425 | AM46: =SUM(AM45:AM45) -> 4.85422 | AO46: =SUM(AO45:AO45) -> 3.70541 | AP46: =SUM(AP45:AP45) -> 3.7654417 | AQ46: =SUM(AQ45:AQ45) -> 3.8754878 | AR46: =SUM(AR45:AR45) -> 3.5306392
C47: Total current liabilities | E47: =E29+E35+E38+E46+E43 -> 1449.096 | F47: =F29+F35+F38+F46+F43 -> 1527.233 | G47: =G29+G35+G38+G46+G43 -> 1615.998 | H47: =H29+H35+H38+H46+H43 -> 1559.4235 | I47: =I29+I35+I38+I46+I43 -> 1550.2368 | J47: =J29+J35+J38+J46+J43 -> 1604.0057 | K47: =K29+K35+K38+K46+K43 -> 1719.6744 | L47: =L29+L35+L38+L46+L43 -> 1691.659 | ... AI47: =AI29+AI35+AI38+AI46+AI43 -> 1285.7402 | AK47: =AK29+AK35+AK38+AK46+AK43 -> 1245.3872 | AL47: =AL29+AL35+AL38+AL46+AL43 -> 1174.2542 | AM47: =AM29+AM35+AM38+AM46+AM43 -> 1285.7402 | AO47: =AO29+AO35+AO38+AO46+AO43 -> 1289.1953 | AP47: =AP29+AP35+AP38+AP46+AP43 -> 1299.7499 | AQ47: =AQ29+AQ35+AQ38+AQ46+AQ43 -> 1249.9551 | AR47: =AR29+AR35+AR38+AR46+AR43 -> 1293.13
C48: Net working capital, reported | E48: =E26-E47 -> 483.85468 | F48: =F26-F47 -> 336.86657 | G48: =G26-G47 -> 436.42332 | H48: =H26-H47 -> 714.62411 | I48: =I26-I47 -> 803.08008 | J48: =J26-J47 -> 746.75468 | K48: =K26-K47 -> 834.30214 | L48: =L26-L47 -> 1508.671 | ... AI48: =AI26-AI47 -> 1253.3978 | AK48: =AK26-AK47 -> 1853.9785 | AL48: =AL26-AL47 -> 2285.0353 | AM48: =AM26-AM47 -> 1253.3978 | AO48: =AO26-AO47 -> 1408.9375 | AP48: =AP26-AP47 -> 1522.844 | AQ48: =AQ26-AQ47 -> 1752.3253 | AR48: =AR26-AR47 -> 1856.6482
C50: Cash-free, debt-free adjustments:
C51: Cash and cash equivalents | E51: =-E11 -> -1634.4889 | F51: =-F11 -> -1515.8343 | G51: =-G11 -> -1285.8186 | H51: =-H11 -> -1744.6673 | I51: =-I11 -> -1893.5656 | J51: =-J11 -> -1712.3811 | K51: =-K11 -> -1802.049 | L51: =-L11 -> -1828.552 | ... AI51: =-AI11 -> -1764.0835 | AK51: =P51 -> -2467.1372 | AL51: =AB51 -> -2857.098 | AM51: =AI51 -> -1764.0835 | AO51: =IFERROR(AVERAGE(AG51:AI51),0) -> -1955.008 | AP51: =IFERROR(AVERAGE(AD51:AI51),0) -> -2091.4868 | AQ51: =IFERROR(AVERAGE(AA51:AI51),0) -> -2304.2152 | AR51: =IFERROR(AVERAGE(X51:AI51),0) -> -2429.3951
C52: Current debt | E52: 0 | F52: 0 | G52: 0 | H52: 0 | I52: 0 | J52: 0 | K52: 0 | L52: 0 | M52: 0 | N52: 0 | O52: 0 | P52: 0 | Q52: 0 | R52: 0 | S52: 0 | T52: 0 | U52: 0 | V52: 0 | W52: 0 | X52: 0 | Y52: 0 | Z52: 0 | AA52: 0 | AB52: 0 | AC52: 0 | AD52: 0 | AE52: 0 | AF52: 0 | AG52: 0 | AH52: 0 | AI52: 0 | AK52: =P52 -> 0 | AL52: =AB52 -> 0 | AM52: =AI52 -> 0 | AO52: =IFERROR(AVERAGE(AG52:AI52),0) -> 0 | AP52: =IFERROR(AVERAGE(AD52:AI52),0) -> 0 | AQ52: =IFERROR(AVERAGE(AA52:AI52),0) -> 0 | AR52: =IFERROR(AVERAGE(X52:AI52),0) -> 0
C53: Accrued interest | E53: 0 | F53: 0 | G53: 0 | H53: 0 | I53: 0 | J53: 0 | K53: 0 | L53: 0 | M53: 0 | N53: 0 | O53: 0 | P53: 0 | Q53: 0 | R53: 0 | S53: 0 | T53: 0 | U53: 0 | V53: 0 | W53: 0 | X53: 0 | Y53: 0 | Z53: 0 | AA53: 0 | AB53: 0 | AC53: 0 | AD53: 0 | AE53: 0 | AF53: 0 | AG53: 0 | AH53: 0 | AI53: 0 | AK53: =P53 -> 0 | AL53: =AB53 -> 0 | AM53: =AI53 -> 0 | AO53: =IFERROR(AVERAGE(AG53:AI53),0) -> 0 | AP53: =IFERROR(AVERAGE(AD53:AI53),0) -> 0 | AQ53: =IFERROR(AVERAGE(AA53:AI53),0) -> 0 | AR53: =IFERROR(AVERAGE(X53:AI53),0) -> 0
C54: Accrued income taxes | E54: 0 | F54: 0 | G54: 0 | H54: 0 | I54: 0 | J54: 0 | K54: 0 | L54: 0 | M54: 0 | N54: 0 | O54: 0 | P54: 0 | Q54: 0 | R54: 0 | S54: 0 | T54: 0 | U54: 0 | V54: 0 | W54: 0 | X54: 0 | Y54: 0 | Z54: 0 | AA54: 0 | AB54: 0 | AC54: 0 | AD54: 0 | AE54: 0 | AF54: 0 | AG54: 0 | AH54: 0 | AI54: 0 | AK54: =P54 -> 0 | AL54: =AB54 -> 0 | AM54: =AI54 -> 0 | AO54: =IFERROR(AVERAGE(AG54:AI54),0) -> 0 | AP54: =IFERROR(AVERAGE(AD54:AI54),0) -> 0 | AQ54: =IFERROR(AVERAGE(AA54:AI54),0) -> 0 | AR54: =IFERROR(AVERAGE(X54:AI54),0) -> 0
C55: Cash-free, debt-free adjustments | D55: [A] | E55: =SUM(E51:E54) -> -1634.4889 | F55: =SUM(F51:F54) -> -1515.8343 | G55: =SUM(G51:G54) -> -1285.8186 | H55: =SUM(H51:H54) -> -1744.6673 | I55: =SUM(I51:I54) -> -1893.5656 | J55: =SUM(J51:J54) -> -1712.3811 | K55: =SUM(K51:K54) -> -1802.049 | L55: =SUM(L51:L54) -> -1828.552 | ... AI55: =SUM(AI51:AI54) -> -1764.0835 | AK55: =SUM(AK51:AK54) -> -2467.1372 | AL55: =SUM(AL51:AL54) -> -2857.098 | AM55: =SUM(AM51:AM54) -> -1764.0835 | AO55: =SUM(AO51:AO54) -> -1955.008 | AP55: =SUM(AP51:AP54) -> -2091.4868 | AQ55: =SUM(AQ51:AQ54) -> -2304.2152 | AR55: =SUM(AR51:AR54) -> -2429.3951
C56: Net working capital, definitional | E56: =E48+E55 -> -1150.6342 | F56: =F48+F55 -> -1178.9677 | G56: =G48+G55 -> -849.39523 | H56: =H48+H55 -> -1030.0432 | I56: =I48+I55 -> -1090.4855 | J56: =J48+J55 -> -965.6264 | K56: =K48+K55 -> -967.74691 | L56: =L48+L55 -> -319.88095 | ... AI56: =AI48+AI55 -> -510.68569 | AK56: =AK48+AK55 -> -613.15866 | AL56: =AL48+AL55 -> -572.06273 | AM56: =AM48+AM55 -> -510.68569 | AO56: =AO48+AO55 -> -546.07045 | AP56: =AP48+AP55 -> -568.64279 | AQ56: =AQ48+AQ55 -> -551.88982 | AR56: =AR48+AR55 -> -572.74682
C58: Impact of Quality of Earnings adjustments
C59: [open] | D59: [B] | E59: 0 | F59: 0 | G59: 0 | H59: 0 | I59: 0 | J59: 0 | K59: 0 | L59: 0 | M59: 0 | N59: 0 | O59: 0 | P59: 0 | Q59: 0 | R59: 0 | S59: 0 | T59: 0 | U59: 0 | V59: 0 | W59: 0 | X59: 0 | Y59: 0 | Z59: 0 | AA59: 0 | AB59: 0 | AC59: 0 | AD59: 0 | AE59: 0 | AF59: 0 | AG59: 0 | AH59: 0 | AI59: 0 | AK59: =P59 -> 0 | AL59: =AB59 -> 0 | AM59: =AI59 -> 0 | AO59: =IFERROR(AVERAGE(AG59:AI59),0) -> 0 | AP59: =IFERROR(AVERAGE(AD59:AI59),0) -> 0 | AQ59: =IFERROR(AVERAGE(AA59:AI59),0) -> 0 | AR59: =IFERROR(AVERAGE(X59:AI59),0) -> 0
C60: [open] | D60: [C] | E60: 0 | F60: 0 | G60: 0 | H60: 0 | I60: 0 | J60: 0 | K60: 0 | L60: 0 | M60: 0 | N60: 0 | O60: 0 | P60: 0 | Q60: 0 | R60: 0 | S60: 0 | T60: 0 | U60: 0 | V60: 0 | W60: 0 | X60: 0 | Y60: 0 | Z60: 0 | AA60: 0 | AB60: 0 | AC60: 0 | AD60: 0 | AE60: 0 | AF60: 0 | AG60: 0 | AH60: 0 | AI60: 0 | AK60: =P60 -> 0 | AL60: =AB60 -> 0 | AM60: =AI60 -> 0 | AO60: =IFERROR(AVERAGE(AG60:AI60),0) -> 0 | AP60: =IFERROR(AVERAGE(AD60:AI60),0) -> 0 | AQ60: =IFERROR(AVERAGE(AA60:AI60),0) -> 0 | AR60: =IFERROR(AVERAGE(X60:AI60),0) -> 0
C61: [open] | D61: [D] | E61: 0 | F61: 0 | G61: 0 | H61: 0 | I61: 0 | J61: 0 | K61: 0 | L61: 0 | M61: 0 | N61: 0 | O61: 0 | P61: 0 | Q61: 0 | R61: 0 | S61: 0 | T61: 0 | U61: 0 | V61: 0 | W61: 0 | X61: 0 | Y61: 0 | Z61: 0 | AA61: 0 | AB61: 0 | AC61: 0 | AD61: 0 | AE61: 0 | AF61: 0 | AG61: 0 | AH61: 0 | AI61: 0 | AK61: =P61 -> 0 | AL61: =AB61 -> 0 | AM61: =AI61 -> 0 | AO61: =IFERROR(AVERAGE(AG61:AI61),0) -> 0 | AP61: =IFERROR(AVERAGE(AD61:AI61),0) -> 0 | AQ61: =IFERROR(AVERAGE(AA61:AI61),0) -> 0 | AR61: =IFERROR(AVERAGE(X61:AI61),0) -> 0
C62: [open] | D62: [E] | E62: 0 | F62: 0 | G62: 0 | H62: 0 | I62: 0 | J62: 0 | K62: 0 | L62: 0 | M62: 0 | N62: 0 | O62: 0 | P62: 0 | Q62: 0 | R62: 0 | S62: 0 | T62: 0 | U62: 0 | V62: 0 | W62: 0 | X62: 0 | Y62: 0 | Z62: 0 | AA62: 0 | AB62: 0 | AC62: 0 | AD62: 0 | AE62: 0 | AF62: 0 | AG62: 0 | AH62: 0 | AI62: 0 | AK62: =P62 -> 0 | AL62: =AB62 -> 0 | AM62: =AI62 -> 0 | AO62: =IFERROR(AVERAGE(AG62:AI62),0) -> 0 | AP62: =IFERROR(AVERAGE(AD62:AI62),0) -> 0 | AQ62: =IFERROR(AVERAGE(AA62:AI62),0) -> 0 | AR62: =IFERROR(AVERAGE(X62:AI62),0) -> 0
C63: [open] | E63: 0 | F63: 0 | G63: 0 | H63: 0 | I63: 0 | J63: 0 | K63: 0 | L63: 0 | M63: 0 | N63: 0 | O63: 0 | P63: 0 | Q63: 0 | R63: 0 | S63: 0 | T63: 0 | U63: 0 | V63: 0 | W63: 0 | X63: 0 | Y63: 0 | Z63: 0 | AA63: 0 | AB63: 0 | AC63: 0 | AD63: 0 | AE63: 0 | AF63: 0 | AG63: 0 | AH63: 0 | AI63: 0 | AK63: =P63 -> 0 | AL63: =AB63 -> 0 | AM63: =AI63 -> 0 | AO63: =IFERROR(AVERAGE(AG63:AI63),0) -> 0 | AP63: =IFERROR(AVERAGE(AD63:AI63),0) -> 0 | AQ63: =IFERROR(AVERAGE(AA63:AI63),0) -> 0 | AR63: =IFERROR(AVERAGE(X63:AI63),0) -> 0
C64: [open] | E64: 0 | F64: 0 | G64: 0 | H64: 0 | I64: 0 | J64: 0 | K64: 0 | L64: 0 | M64: 0 | N64: 0 | O64: 0 | P64: 0 | Q64: 0 | R64: 0 | S64: 0 | T64: 0 | U64: 0 | V64: 0 | W64: 0 | X64: 0 | Y64: 0 | Z64: 0 | AA64: 0 | AB64: 0 | AC64: 0 | AD64: 0 | AE64: 0 | AF64: 0 | AG64: 0 | AH64: 0 | AI64: 0 | AK64: =P64 -> 0 | AL64: =AB64 -> 0 | AM64: =AI64 -> 0 | AO64: =IFERROR(AVERAGE(AG64:AI64),0) -> 0 | AP64: =IFERROR(AVERAGE(AD64:AI64),0) -> 0 | AQ64: =IFERROR(AVERAGE(AA64:AI64),0) -> 0 | AR64: =IFERROR(AVERAGE(X64:AI64),0) -> 0
C66: Other diligence adjustments
C67: [open] | E67: 0 | F67: 0 | G67: 0 | H67: 0 | I67: 0 | J67: 0 | K67: 0 | L67: 0 | M67: 0 | N67: 0 | O67: 0 | P67: 0 | Q67: 0 | R67: 0 | S67: 0 | T67: 0 | U67: 0 | V67: 0 | W67: 0 | X67: 0 | Y67: 0 | Z67: 0 | AA67: 0 | AB67: 0 | AC67: 0 | AD67: 0 | AE67: 0 | AF67: 0 | AG67: 0 | AH67: 0 | AI67: 0 | AK67: =P67 -> 0 | AL67: =AB67 -> 0 | AM67: =AI67 -> 0 | AO67: =IFERROR(AVERAGE(AG67:AI67),0) -> 0 | AP67: =IFERROR(AVERAGE(AD67:AI67),0) -> 0 | AQ67: =IFERROR(AVERAGE(AA67:AI67),0) -> 0 | AR67: =IFERROR(AVERAGE(X67:AI67),0) -> 0
C68: [open] | E68: 0 | F68: 0 | G68: 0 | H68: 0 | I68: 0 | J68: 0 | K68: 0 | L68: 0 | M68: 0 | N68: 0 | O68: 0 | P68: 0 | Q68: 0 | R68: 0 | S68: 0 | T68: 0 | U68: 0 | V68: 0 | W68: 0 | X68: 0 | Y68: 0 | Z68: 0 | AA68: 0 | AB68: 0 | AC68: 0 | AD68: 0 | AE68: 0 | AF68: 0 | AG68: 0 | AH68: 0 | AI68: 0 | AK68: =P68 -> 0 | AL68: =AB68 -> 0 | AM68: =AI68 -> 0 | AO68: =IFERROR(AVERAGE(AG68:AI68),0) -> 0 | AP68: =IFERROR(AVERAGE(AD68:AI68),0) -> 0 | AQ68: =IFERROR(AVERAGE(AA68:AI68),0) -> 0 | AR68: =IFERROR(AVERAGE(X68:AI68),0) -> 0
C69: [open] | E69: 0 | F69: 0 | G69: 0 | H69: 0 | I69: 0 | J69: 0 | K69: 0 | L69: 0 | M69: 0 | N69: 0 | O69: 0 | P69: 0 | Q69: 0 | R69: 0 | S69: 0 | T69: 0 | U69: 0 | V69: 0 | W69: 0 | X69: 0 | Y69: 0 | Z69: 0 | AA69: 0 | AB69: 0 | AC69: 0 | AD69: 0 | AE69: 0 | AF69: 0 | AG69: 0 | AH69: 0 | AI69: 0 | AK69: =P69 -> 0 | AL69: =AB69 -> 0 | AM69: =AI69 -> 0 | AO69: =IFERROR(AVERAGE(AG69:AI69),0) -> 0 | AP69: =IFERROR(AVERAGE(AD69:AI69),0) -> 0 | AQ69: =IFERROR(AVERAGE(AA69:AI69),0) -> 0 | AR69: =IFERROR(AVERAGE(X69:AI69),0) -> 0
C70: [open] | E70: 0 | F70: 0 | G70: 0 | H70: 0 | I70: 0 | J70: 0 | K70: 0 | L70: 0 | M70: 0 | N70: 0 | O70: 0 | P70: 0 | Q70: 0 | R70: 0 | S70: 0 | T70: 0 | U70: 0 | V70: 0 | W70: 0 | X70: 0 | Y70: 0 | Z70: 0 | AA70: 0 | AB70: 0 | AC70: 0 | AD70: 0 | AE70: 0 | AF70: 0 | AG70: 0 | AH70: 0 | AI70: 0 | AK70: =P70 -> 0 | AL70: =AB70 -> 0 | AM70: =AI70 -> 0 | AO70: =IFERROR(AVERAGE(AG70:AI70),0) -> 0 | AP70: =IFERROR(AVERAGE(AD70:AI70),0) -> 0 | AQ70: =IFERROR(AVERAGE(AA70:AI70),0) -> 0 | AR70: =IFERROR(AVERAGE(X70:AI70),0) -> 0
C71: [open] | E71: 0 | F71: 0 | G71: 0 | H71: 0 | I71: 0 | J71: 0 | K71: 0 | L71: 0 | M71: 0 | N71: 0 | O71: 0 | P71: 0 | Q71: 0 | R71: 0 | S71: 0 | T71: 0 | U71: 0 | V71: 0 | W71: 0 | X71: 0 | Y71: 0 | Z71: 0 | AA71: 0 | AB71: 0 | AC71: 0 | AD71: 0 | AE71: 0 | AF71: 0 | AG71: 0 | AH71: 0 | AI71: 0 | AK71: =P71 -> 0 | AL71: =AB71 -> 0 | AM71: =AI71 -> 0 | AO71: =IFERROR(AVERAGE(AG71:AI71),0) -> 0 | AP71: =IFERROR(AVERAGE(AD71:AI71),0) -> 0 | AQ71: =IFERROR(AVERAGE(AA71:AI71),0) -> 0 | AR71: =IFERROR(AVERAGE(X71:AI71),0) -> 0
C72: Total diligence adjustments | E72: =SUM(E58:E71) -> 0 | F72: =SUM(F58:F71) -> 0 | G72: =SUM(G58:G71) -> 0 | H72: =SUM(H58:H71) -> 0 | I72: =SUM(I58:I71) -> 0 | J72: =SUM(J58:J71) -> 0 | K72: =SUM(K58:K71) -> 0 | L72: =SUM(L58:L71) -> 0 | ... AI72: =SUM(AI58:AI71) -> 0 | AK72: =SUM(AK58:AK71) -> 0 | AL72: =SUM(AL58:AL71) -> 0 | AM72: =SUM(AM58:AM71) -> 0 | AO72: =SUM(AO58:AO71) -> 0 | AP72: =SUM(AP58:AP71) -> 0 | AQ72: =SUM(AQ58:AQ71) -> 0 | AR72: =SUM(AR58:AR71) -> 0
C73: Net working capital, adjusted | E73: =E56+E72 -> -1150.6342 | F73: =F56+F72 -> -1178.9677 | G73: =G56+G72 -> -849.39523 | H73: =H56+H72 -> -1030.0432 | I73: =I56+I72 -> -1090.4855 | J73: =J56+J72 -> -965.6264 | K73: =K56+K72 -> -967.74691 | L73: =L56+L72 -> -319.88095 | ... AI73: =AI56+AI72 -> -510.68569 | AK73: =AK56+AK72 -> -613.15866 | AL73: =AL56+AL72 -> -572.06273 | AM73: =AM56+AM72 -> -510.68569 | AO73: =AO56+AO72 -> -546.07045 | AP73: =AP56+AP72 -> -568.64279 | AQ73: =AQ56+AQ72 -> -551.88982 | AR73: =AR56+AR72 -> -572.74682
C74: Adjusted NWC as % of TTM Net Revenue | E74: n/a | F74: n/a | G74: n/a | H74: n/a | I74: n/a | J74: n/a | K74: n/a | L74: n/a | M74: n/a | N74: n/a | O74: n/a | P74: =IFERROR(P73/P86%,0) -> -8.0178483 | Q74: =IFERROR(Q73/Q86%,0) -> -9.9794032 | R74: =IFERROR(R73/R86%,0) -> -7.6110459 | S74: =IFERROR(S73/S86%,0) -> -11.682168 | T74: =IFERROR(T73/T86%,0) -> -11.81916 | U74: =IFERROR(U73/U86%,0) -> -11.741533 | V74: =IFERROR(V73/V86%,0) -> -11.218737 | W74: =IFERROR(W73/W86%,0) -> -13.740216 | ... AI74: =IFERROR(AI73/AI86%,0) -> -6.9543358 | AK74: =P74 -> -8.0178483 | AL74: =AB74 -> -8.4390578 | AM74: =AI74 -> -6.9543358 | AO74: =IFERROR(AVERAGE(AG74:AI74),0) -> -7.6580013 | AP74: =IFERROR(AVERAGE(AD74:AI74),0) -> -8.0970831 | AQ74: =IFERROR(AVERAGE(AA74:AI74),0) -> -7.9341693 | AR74: =IFERROR(AVERAGE(X74:AI74),0) -> -8.2724778
C76: DSO, reported | E76: =+'BS1'!E37 -> 47.848416 | F76: =+'BS1'!F37 -> 25.113268 | G76: =+'BS1'!G37 -> 31.410889 | H76: =+'BS1'!H37 -> 38.102652 | I76: =+'BS1'!I37 -> 22.84008 | J76: =+'BS1'!J37 -> 39.80334 | K76: =+'BS1'!K37 -> 33.841551 | L76: =+'BS1'!L37 -> 32.462349 | ... AI76: =+'BS1'!AI37 -> 56.461083 | AK76: =+'BS1'!AK37 -> 30.397139 | AL76: =+'BS1'!AL37 -> 32.193762 | AM76: =+'BS1'!AM37 -> 38.310312 | AO76: =IFERROR(AVERAGE(AG76:AI76),0) -> 51.966469 | AP76: =IFERROR(AVERAGE(AD76:AI76),0) -> 45.333312 | AQ76: =IFERROR(AVERAGE(AA76:AI76),0) -> 43.295743 | AR76: =IFERROR(AVERAGE(X76:AI76),0) -> 39.597423
C77: DIO, reported | E77: 0 | F77: 0 | G77: 0 | H77: 0 | I77: 0 | J77: 0 | K77: 0 | L77: 0 | M77: 0 | N77: 0 | O77: 0 | P77: 0 | Q77: 0 | R77: 0 | S77: 0 | T77: 0 | U77: 0 | V77: 0 | W77: 0 | X77: 0 | Y77: 0 | Z77: 0 | AA77: 0 | AB77: 0 | AC77: 0 | AD77: 0 | AE77: 0 | AF77: 0 | AG77: 0 | AH77: 0 | AI77: 0 | AK77: =+'BS1'!AK38 -> n/a | AL77: =+'BS1'!AL38 -> n/a | AM77: =+'BS1'!AM38 -> n/a | AO77: =IFERROR(AVERAGE(AG77:AI77),0) -> 0 | AP77: =IFERROR(AVERAGE(AD77:AI77),0) -> 0 | AQ77: =IFERROR(AVERAGE(AA77:AI77),0) -> 0 | AR77: =IFERROR(AVERAGE(X77:AI77),0) -> 0
C78: DPO, reported | E78: =+'BS1'!E39 -> 15.731247 | F78: =+'BS1'!F39 -> 16.349467 | G78: =+'BS1'!G39 -> 18.751137 | H78: =+'BS1'!H39 -> 10.793711 | I78: =+'BS1'!I39 -> 14.671003 | J78: =+'BS1'!J39 -> 14.458426 | K78: =+'BS1'!K39 -> 18.625684 | L78: =+'BS1'!L39 -> 11.764053 | ... AI78: =+'BS1'!AI39 -> 12.460613 | AK78: =+'BS1'!AK39 -> 0 | AL78: =+'BS1'!AL39 -> 8.7413086 | AM78: =+'BS1'!AM39 -> 11.996859 | AO78: =IFERROR(AVERAGE(AG78:AI78),0) -> 15.270617 | AP78: =IFERROR(AVERAGE(AD78:AI78),0) -> 17.148904 | AQ78: =IFERROR(AVERAGE(AA78:AI78),0) -> 15.554841 | AR78: =IFERROR(AVERAGE(X78:AI78),0) -> 16.675024
C81: Check to Recast NWC2 | E81: ='NWC2'!E44-E73 -> 0 | F81: ='NWC2'!F44-F73 -> 0 | G81: ='NWC2'!G44-G73 -> 0 | H81: ='NWC2'!H44-H73 -> 0 | I81: ='NWC2'!I44-I73 -> 0 | J81: ='NWC2'!J44-J73 -> 0 | K81: ='NWC2'!K44-K73 -> 0 | L81: ='NWC2'!L44-L73 -> 0 | ... AI81: ='NWC2'!AI44-AI73 -> 0 | AK81: ='NWC2'!AK44-AK73 -> 0 | AL81: ='NWC2'!AL44-AL73 -> 0 | AM81: ='NWC2'!AM44-AM73 -> 0 | AO81: ='NWC2'!AO44-AO73 -> 0 | AP81: ='NWC2'!AP44-AP73 -> 0 | AQ81: ='NWC2'!AQ44-AQ73 -> 0 | AR81: ='NWC2'!AR44-AR73 -> 0
C82: Current assets check: | E82: ='BS1'!E13-E26 -> 0 | F82: ='BS1'!F13-F26 -> 0 | G82: ='BS1'!G13-G26 -> 0 | H82: ='BS1'!H13-H26 -> 0 | I82: ='BS1'!I13-I26 -> 0 | J82: ='BS1'!J13-J26 -> 0 | K82: ='BS1'!K13-K26 -> 0 | L82: ='BS1'!L13-L26 -> 0 | ... AI82: ='BS1'!AI13-AI26 -> 0 | AK82: ='BS1'!AK13-AK26 -> 0 | AL82: ='BS1'!AL13-AL26 -> 0 | AM82: ='BS1'!AM13-AM26 -> 0
C83: Current liabilities check: | E83: ='BS1'!E25-E47 -> 0 | F83: ='BS1'!F25-F47 -> 0 | G83: ='BS1'!G25-G47 -> 0 | H83: ='BS1'!H25-H47 -> 0 | I83: ='BS1'!I25-I47 -> 0 | J83: ='BS1'!J25-J47 -> 0 | K83: ='BS1'!K25-K47 -> 0 | L83: ='BS1'!L25-L47 -> 0 | ... AI83: ='BS1'!AI25-AI47 -> 0 | AK83: ='BS1'!AK25-AK47 -> 0 | AL83: ='BS1'!AL25-AL47 -> 0 | AM83: ='BS1'!AM25-AM47 -> 0
C86: Adjusted TTM Net Revenue | E86: =SUM(E87:E87) -> 193.127 | F86: =SUM(E87:F87) -> 622.5705 | G86: =SUM(E87:G87) -> 1354.3855 | H86: =SUM(E87:H87) -> 1784.7405 | I86: =SUM(E87:I87) -> 2408.1695 | J86: =SUM(E87:J87) -> 2889.0005 | K86: =SUM(E87:K87) -> 3577.4685 | L86: =SUM(E87:L87) -> 4844.868 | M86: =SUM(E87:M87) -> 6121.044 | N86: =SUM(E87:N87) -> 6359.7455 | O86: =SUM(E87:O87) -> 6910.6386 | P86: =SUM(E87:P87) -> 7647.4216 | Q86: =SUM(F87:Q87) -> 7876.3386 | R86: =SUM(G87:R87) -> 7972.5451 | S86: =SUM(H87:S87) -> 7612.0781 | T86: =SUM(I87:T87) -> 7563.3571 | U86: =SUM(J87:U87) -> 7477.1071 | V86: =SUM(K87:V87) -> 7353.1801 | W86: =SUM(L87:W87) -> 7030.3261 | ... AI86: =SUM(X87:AI87) -> 7343.4143
C87: Adjusted Net Revenue | E87: ='RPL1'!E10 -> 193.127 | F87: ='RPL1'!F10 -> 429.4435 | G87: ='RPL1'!G10 -> 731.815 | H87: ='RPL1'!H10 -> 430.355 | I87: ='RPL1'!I10 -> 623.429 | J87: ='RPL1'!J10 -> 480.831 | K87: ='RPL1'!K10 -> 688.468 | L87: ='RPL1'!L10 -> 1267.3995 | ... AI87: ='RPL1'!AI10 -> 423.188

Sheet NWC2
A1: =IF(ROUND(SUM(E52:AS52),1)<>0,"NO","Yes") -> Yes | C1: Project X
A2: =IF(COUNTIF(E52:AS52,">0.5")+COUNTIF(E52:AS52,"<-0.5")<1,"Yes","No") -> Yes | C2: CLIENT
A3: =2-COUNTIF(A1:A2,"Yes") -> 0 | C3: ($ in 000s)
C4: Adjusted Net Working Capital
C7: =C4 -> Adjusted Net Working Capital | E7: FY24 | Q7: FY25 | AC7: FY26 | AO7: Averages
C8: =C3 -> ($ in 000s) | D8: Ref | E8: =TB!K1 -> 45046 | F8: =TB!L1 -> 45077 | G8: =TB!M1 -> 45107 | H8: =TB!N1 -> 45138 | I8: =TB!O1 -> 45169 | J8: =TB!P1 -> 45199 | K8: =TB!Q1 -> 45230 | L8: =TB!R1 -> 45260 | ... AI8: =TB!AO1 -> 45961 | AK8: =P8 -> 45382 | AL8: =AB8 -> 45747 | AM8: =AI8 -> 45961 | AO8: 3m | AP8: 6m | AQ8: 9m | AR8: 12m
C9: Accounts Receivable | E9: =SUMIFS('NWC1'!E:E,'NWC1'!$C:$C,$C9)+SUMIFS(ADJ!G:G,ADJ!$E:$E,$C9) -> 298.091 | F9: =SUMIFS('NWC1'!F:F,'NWC1'!$C:$C,$C9)+SUMIFS(ADJ!H:H,ADJ!$E:$E,$C9) -> 347.8945 | G9: =SUMIFS('NWC1'!G:G,'NWC1'!$C:$C,$C9)+SUMIFS(ADJ!I:I,ADJ!$E:$E,$C9) -> 766.232 | H9: =SUMIFS('NWC1'!H:H,'NWC1'!$C:$C,$C9)+SUMIFS(ADJ!J:J,ADJ!$E:$E,$C9) -> 528.957 | I9: =SUMIFS('NWC1'!I:I,'NWC1'!$C:$C,$C9)+SUMIFS(ADJ!K:K,ADJ!$E:$E,$C9) -> 459.328 | J9: =SUMIFS('NWC1'!J:J,'NWC1'!$C:$C,$C9)+SUMIFS(ADJ!L:L,ADJ!$E:$E,$C9) -> 637.956 | K9: =SUMIFS('NWC1'!K:K,'NWC1'!$C:$C,$C9)+SUMIFS(ADJ!M:M,ADJ!$E:$E,$C9) -> 751.575 | L9: =SUMIFS('NWC1'!L:L,'NWC1'!$C:$C,$C9)+SUMIFS(ADJ!N:N,ADJ!$E:$E,$C9) -> 1371.4255 | M9: =SUMIFS('NWC1'!M:M,'NWC1'!$C:$C,$C9)+SUMIFS(ADJ!O:O,ADJ!$E:$E,$C9) -> 911.5285 | N9: =SUMIFS('NWC1'!N:N,'NWC1'!$C:$C,$C9)+SUMIFS(ADJ!P:P,ADJ!$E:$E,$C9) -> 371.5595 | O9: =SUMIFS('NWC1'!O:O,'NWC1'!$C:$C,$C9)+SUMIFS(ADJ!Q:Q,ADJ!$E:$E,$C9) -> 371.7205 | P9: =SUMIFS('NWC1'!P:P,'NWC1'!$C:$C,$C9)+SUMIFS(ADJ!R:R,ADJ!$E:$E,$C9) -> 636.876 | Q9: =SUMIFS('NWC1'!Q:Q,'NWC1'!$C:$C,$C9)+SUMIFS(ADJ!S:S,ADJ!$E:$E,$C9) -> 542.1465 | R9: =SUMIFS('NWC1'!R:R,'NWC1'!$C:$C,$C9)+SUMIFS(ADJ!T:T,ADJ!$E:$E,$C9) -> 717.0845 | S9: =SUMIFS('NWC1'!S:S,'NWC1'!$C:$C,$C9)+SUMIFS(ADJ!U:U,ADJ!$E:$E,$C9) -> 468.527 | T9: =SUMIFS('NWC1'!T:T,'NWC1'!$C:$C,$C9)+SUMIFS(ADJ!V:V,ADJ!$E:$E,$C9) -> 427.884 | U9: =SUMIFS('NWC1'!U:U,'NWC1'!$C:$C,$C9)+SUMIFS(ADJ!W:W,ADJ!$E:$E,$C9) -> 521.295 | V9: =SUMIFS('NWC1'!V:V,'NWC1'!$C:$C,$C9)+SUMIFS(ADJ!X:X,ADJ!$E:$E,$C9) -> 547.449 | W9: =SUMIFS('NWC1'!W:W,'NWC1'!$C:$C,$C9)+SUMIFS(ADJ!Y:Y,ADJ!$E:$E,$C9) -> 471.657 | X9: =SUMIFS('NWC1'!X:X,'NWC1'!$C:$C,$C9)+SUMIFS(ADJ!Z:Z,ADJ!$E:$E,$C9) -> 917.839 | Y9: =SUMIFS('NWC1'!Y:Y,'NWC1'!$C:$C,$C9)+SUMIFS(ADJ!AA:AA,ADJ!$E:$E,$C9) -> 1105.536 | Z9: =SUMIFS('NWC1'!Z:Z,'NWC1'!$C:$C,$C9)+SUMIFS(ADJ!AB:AB,ADJ!$E:$E,$C9) -> 329.661 | AA9: =SUMIFS('NWC1'!AA:AA,'NWC1'!$C:$C,$C9)+SUMIFS(ADJ!AC:AC,ADJ!$E:$E,$C9) -> 727.5975 | AB9: =SUMIFS('NWC1'!AB:AB,'NWC1'!$C:$C,$C9)+SUMIFS(ADJ!AD:AD,ADJ!$E:$E,$C9) -> 597.9 | AC9: =SUMIFS('NWC1'!AC:AC,'NWC1'!$C:$C,$C9)+SUMIFS(ADJ!AE:AE,ADJ!$E:$E,$C9) -> 557.573 | AD9: =SUMIFS('NWC1'!AD:AD,'NWC1'!$C:$C,$C9)+SUMIFS(ADJ!AF:AF,ADJ!$E:$E,$C9) -> 512 | AE9: =SUMIFS('NWC1'!AE:AE,'NWC1'!$C:$C,$C9)+SUMIFS(ADJ!AG:AG,ADJ!$E:$E,$C9) -> 996.3901 | AF9: =SUMIFS('NWC1'!AF:AF,'NWC1'!$C:$C,$C9)+SUMIFS(ADJ!AH:AH,ADJ!$E:$E,$C9) -> 636.0036 | AG9: =SUMIFS('NWC1'!AG:AG,'NWC1'!$C:$C,$C9)+SUMIFS(ADJ!AI:AI,ADJ!$E:$E,$C9) -> 608.917 | AH9: =SUMIFS('NWC1'!AH:AH,'NWC1'!$C:$C,$C9)+SUMIFS(ADJ!AJ:AJ,ADJ!$E:$E,$C9) -> 836.82 | AI9: =SUMIFS('NWC1'!AI:AI,'NWC1'!$C:$C,$C9)+SUMIFS(ADJ!AK:AK,ADJ!$E:$E,$C9) -> 770.763 | AK9: =P9 -> 636.876 | AL9: =AB9 -> 597.9 | AM9: =AI9 -> 770.763 | AO9: =IFERROR(AVERAGE(AG9:AI9),0) -> 738.83333 | AP9: =IFERROR(AVERAGE(AD9:AI9),0) -> 726.81562 | AQ9: =IFERROR(AVERAGE(AA9:AI9),0) -> 693.7738 | AR9: =IFERROR(AVERAGE(X9:AI9),0) -> 716.41668
C10: Accounts receivable, net | E10: =SUM(E9:E9) -> 298.091 | F10: =SUM(F9:F9) -> 347.8945 | G10: =SUM(G9:G9) -> 766.232 | H10: =SUM(H9:H9) -> 528.957 | I10: =SUM(I9:I9) -> 459.328 | J10: =SUM(J9:J9) -> 637.956 | K10: =SUM(K9:K9) -> 751.575 | L10: =SUM(L9:L9) -> 1371.4255 | ... AI10: =SUM(AI9:AI9) -> 770.763 | AK10: =SUM(AK9:AK9) -> 636.876 | AL10: =SUM(AL9:AL9) -> 597.9 | AM10: =SUM(AM9:AM9) -> 770.763 | AO10: =SUM(AO9:AO9) -> 738.83333 | AP10: =SUM(AP9:AP9) -> 726.81562 | AQ10: =SUM(AQ9:AQ9) -> 693.7738 | AR10: =SUM(AR9:AR9) -> 716.41668
C12: Due from Vendor | E12: =SUMIFS('NWC1'!E:E,'NWC1'!$C:$C,$C12)+SUMIFS(ADJ!G:G,ADJ!$E:$E,$C12) -> 0.3 | F12: =SUMIFS('NWC1'!F:F,'NWC1'!$C:$C,$C12)+SUMIFS(ADJ!H:H,ADJ!$E:$E,$C12) -> 0.3 | G12: =SUMIFS('NWC1'!G:G,'NWC1'!$C:$C,$C12)+SUMIFS(ADJ!I:I,ADJ!$E:$E,$C12) -> 0.3 | H12: =SUMIFS('NWC1'!H:H,'NWC1'!$C:$C,$C12)+SUMIFS(ADJ!J:J,ADJ!$E:$E,$C12) -> 0.3 | I12: =SUMIFS('NWC1'!I:I,'NWC1'!$C:$C,$C12)+SUMIFS(ADJ!K:K,ADJ!$E:$E,$C12) -> 0.3 | J12: =SUMIFS('NWC1'!J:J,'NWC1'!$C:$C,$C12)+SUMIFS(ADJ!L:L,ADJ!$E:$E,$C12) -> 0.3 | K12: =SUMIFS('NWC1'!K:K,'NWC1'!$C:$C,$C12)+SUMIFS(ADJ!M:M,ADJ!$E:$E,$C12) -> 0.3 | L12: =SUMIFS('NWC1'!L:L,'NWC1'!$C:$C,$C12)+SUMIFS(ADJ!N:N,ADJ!$E:$E,$C12) -> 0.3 | M12: =SUMIFS('NWC1'!M:M,'NWC1'!$C:$C,$C12)+SUMIFS(ADJ!O:O,ADJ!$E:$E,$C12) -> 0.3 | N12: =SUMIFS('NWC1'!N:N,'NWC1'!$C:$C,$C12)+SUMIFS(ADJ!P:P,ADJ!$E:$E,$C12) -> 0.3 | O12: =SUMIFS('NWC1'!O:O,'NWC1'!$C:$C,$C12)+SUMIFS(ADJ!Q:Q,ADJ!$E:$E,$C12) -> 0.3 | P12: =SUMIFS('NWC1'!P:P,'NWC1'!$C:$C,$C12)+SUMIFS(ADJ!R:R,ADJ!$E:$E,$C12) -> 0.3 | Q12: =SUMIFS('NWC1'!Q:Q,'NWC1'!$C:$C,$C12)+SUMIFS(ADJ!S:S,ADJ!$E:$E,$C12) -> 0.3 | R12: =SUMIFS('NWC1'!R:R,'NWC1'!$C:$C,$C12)+SUMIFS(ADJ!T:T,ADJ!$E:$E,$C12) -> 0.3 | S12: =SUMIFS('NWC1'!S:S,'NWC1'!$C:$C,$C12)+SUMIFS(ADJ!U:U,ADJ!$E:$E,$C12) -> 0.3 | T12: =SUMIFS('NWC1'!T:T,'NWC1'!$C:$C,$C12)+SUMIFS(ADJ!V:V,ADJ!$E:$E,$C12) -> 0.3 | U12: =SUMIFS('NWC1'!U:U,'NWC1'!$C:$C,$C12)+SUMIFS(ADJ!W:W,ADJ!$E:$E,$C12) -> 0.3 | V12: =SUMIFS('NWC1'!V:V,'NWC1'!$C:$C,$C12)+SUMIFS(ADJ!X:X,ADJ!$E:$E,$C12) -> 2.939 | W12: =SUMIFS('NWC1'!W:W,'NWC1'!$C:$C,$C12)+SUMIFS(ADJ!Y:Y,ADJ!$E:$E,$C12) -> 2.939 | X12: =SUMIFS('NWC1'!X:X,'NWC1'!$C:$C,$C12)+SUMIFS(ADJ!Z:Z,ADJ!$E:$E,$C12) -> 2.939 | Y12: =SUMIFS('NWC1'!Y:Y,'NWC1'!$C:$C,$C12)+SUMIFS(ADJ!AA:AA,ADJ!$E:$E,$C12) -> 2.939 | Z12: =SUMIFS('NWC1'!Z:Z,'NWC1'!$C:$C,$C12)+SUMIFS(ADJ!AB:AB,ADJ!$E:$E,$C12) -> 2.939 | AA12: =SUMIFS('NWC1'!AA:AA,'NWC1'!$C:$C,$C12)+SUMIFS(ADJ!AC:AC,ADJ!$E:$E,$C12) -> 2.939 | AB12: =SUMIFS('NWC1'!AB:AB,'NWC1'!$C:$C,$C12)+SUMIFS(ADJ!AD:AD,ADJ!$E:$E,$C12) -> 2.939 | AC12: =SUMIFS('NWC1'!AC:AC,'NWC1'!$C:$C,$C12)+SUMIFS(ADJ!AE:AE,ADJ!$E:$E,$C12) -> 2.939 | AD12: =SUMIFS('NWC1'!AD:AD,'NWC1'!$C:$C,$C12)+SUMIFS(ADJ!AF:AF,ADJ!$E:$E,$C12) -> 2.939 | AE12: =SUMIFS('NWC1'!AE:AE,'NWC1'!$C:$C,$C12)+SUMIFS(ADJ!AG:AG,ADJ!$E:$E,$C12) -> 2.939 | AF12: =SUMIFS('NWC1'!AF:AF,'NWC1'!$C:$C,$C12)+SUMIFS(ADJ!AH:AH,ADJ!$E:$E,$C12) -> 2.939 | AG12: =SUMIFS('NWC1'!AG:AG,'NWC1'!$C:$C,$C12)+SUMIFS(ADJ!AI:AI,ADJ!$E:$E,$C12) -> 2.939 | AH12: =SUMIFS('NWC1'!AH:AH,'NWC1'!$C:$C,$C12)+SUMIFS(ADJ!AJ:AJ,ADJ!$E:$E,$C12) -> 2.939 | AI12: =SUMIFS('NWC1'!AI:AI,'NWC1'!$C:$C,$C12)+SUMIFS(ADJ!AK:AK,ADJ!$E:$E,$C12) -> 2.939 | AK12: =P12 -> 0.3 | AL12: =AB12 -> 2.939 | AM12: =AI12 -> 2.939 | AO12: =IFERROR(AVERAGE(AG12:AI12),0) -> 2.939 | AP12: =IFERROR(AVERAGE(AD12:AI12),0) -> 2.939 | AQ12: =IFERROR(AVERAGE(AA12:AI12),0) -> 2.939 | AR12: =IFERROR(AVERAGE(X12:AI12),0) -> 2.939
C13: Due from Accelerant | E13: =SUMIFS('NWC1'!E:E,'NWC1'!$C:$C,$C13)+SUMIFS(ADJ!G:G,ADJ!$E:$E,$C13) -> 0 | F13: =SUMIFS('NWC1'!F:F,'NWC1'!$C:$C,$C13)+SUMIFS(ADJ!H:H,ADJ!$E:$E,$C13) -> 0 | G13: =SUMIFS('NWC1'!G:G,'NWC1'!$C:$C,$C13)+SUMIFS(ADJ!I:I,ADJ!$E:$E,$C13) -> 0 | H13: =SUMIFS('NWC1'!H:H,'NWC1'!$C:$C,$C13)+SUMIFS(ADJ!J:J,ADJ!$E:$E,$C13) -> 0 | I13: =SUMIFS('NWC1'!I:I,'NWC1'!$C:$C,$C13)+SUMIFS(ADJ!K:K,ADJ!$E:$E,$C13) -> 0 | J13: =SUMIFS('NWC1'!J:J,'NWC1'!$C:$C,$C13)+SUMIFS(ADJ!L:L,ADJ!$E:$E,$C13) -> 0 | K13: =SUMIFS('NWC1'!K:K,'NWC1'!$C:$C,$C13)+SUMIFS(ADJ!M:M,ADJ!$E:$E,$C13) -> 0 | L13: =SUMIFS('NWC1'!L:L,'NWC1'!$C:$C,$C13)+SUMIFS(ADJ!N:N,ADJ!$E:$E,$C13) -> 0 | M13: =SUMIFS('NWC1'!M:M,'NWC1'!$C:$C,$C13)+SUMIFS(ADJ!O:O,ADJ!$E:$E,$C13) -> 0 | N13: =SUMIFS('NWC1'!N:N,'NWC1'!$C:$C,$C13)+SUMIFS(ADJ!P:P,ADJ!$E:$E,$C13) -> 0 | O13: =SUMIFS('NWC1'!O:O,'NWC1'!$C:$C,$C13)+SUMIFS(ADJ!Q:Q,ADJ!$E:$E,$C13) -> 0 | P13: =SUMIFS('NWC1'!P:P,'NWC1'!$C:$C,$C13)+SUMIFS(ADJ!R:R,ADJ!$E:$E,$C13) -> 0 | Q13: =SUMIFS('NWC1'!Q:Q,'NWC1'!$C:$C,$C13)+SUMIFS(ADJ!S:S,ADJ!$E:$E,$C13) -> 0 | R13: =SUMIFS('NWC1'!R:R,'NWC1'!$C:$C,$C13)+SUMIFS(ADJ!T:T,ADJ!$E:$E,$C13) -> 0 | S13: =SUMIFS('NWC1'!S:S,'NWC1'!$C:$C,$C13)+SUMIFS(ADJ!U:U,ADJ!$E:$E,$C13) -> 0 | T13: =SUMIFS('NWC1'!T:T,'NWC1'!$C:$C,$C13)+SUMIFS(ADJ!V:V,ADJ!$E:$E,$C13) -> 0 | U13: =SUMIFS('NWC1'!U:U,'NWC1'!$C:$C,$C13)+SUMIFS(ADJ!W:W,ADJ!$E:$E,$C13) -> 0 | V13: =SUMIFS('NWC1'!V:V,'NWC1'!$C:$C,$C13)+SUMIFS(ADJ!X:X,ADJ!$E:$E,$C13) -> 0 | W13: =SUMIFS('NWC1'!W:W,'NWC1'!$C:$C,$C13)+SUMIFS(ADJ!Y:Y,ADJ!$E:$E,$C13) -> 0 | X13: =SUMIFS('NWC1'!X:X,'NWC1'!$C:$C,$C13)+SUMIFS(ADJ!Z:Z,ADJ!$E:$E,$C13) -> 0 | Y13: =SUMIFS('NWC1'!Y:Y,'NWC1'!$C:$C,$C13)+SUMIFS(ADJ!AA:AA,ADJ!$E:$E,$C13) -> 0 | Z13: =SUMIFS('NWC1'!Z:Z,'NWC1'!$C:$C,$C13)+SUMIFS(ADJ!AB:AB,ADJ!$E:$E,$C13) -> 0 | AA13: =SUMIFS('NWC1'!AA:AA,'NWC1'!$C:$C,$C13)+SUMIFS(ADJ!AC:AC,ADJ!$E:$E,$C13) -> 1.3 | AB13: =SUMIFS('NWC1'!AB:AB,'NWC1'!$C:$C,$C13)+SUMIFS(ADJ!AD:AD,ADJ!$E:$E,$C13) -> 1.3 | AC13: =SUMIFS('NWC1'!AC:AC,'NWC1'!$C:$C,$C13)+SUMIFS(ADJ!AE:AE,ADJ!$E:$E,$C13) -> 1.3 | AD13: =SUMIFS('NWC1'!AD:AD,'NWC1'!$C:$C,$C13)+SUMIFS(ADJ!AF:AF,ADJ!$E:$E,$C13) -> 1.3 | AE13: =SUMIFS('NWC1'!AE:AE,'NWC1'!$C:$C,$C13)+SUMIFS(ADJ!AG:AG,ADJ!$E:$E,$C13) -> 1.3 | AF13: =SUMIFS('NWC1'!AF:AF,'NWC1'!$C:$C,$C13)+SUMIFS(ADJ!AH:AH,ADJ!$E:$E,$C13) -> 1.3 | AG13: =SUMIFS('NWC1'!AG:AG,'NWC1'!$C:$C,$C13)+SUMIFS(ADJ!AI:AI,ADJ!$E:$E,$C13) -> 1.3 | AH13: =SUMIFS('NWC1'!AH:AH,'NWC1'!$C:$C,$C13)+SUMIFS(ADJ!AJ:AJ,ADJ!$E:$E,$C13) -> 1.3 | AI13: =SUMIFS('NWC1'!AI:AI,'NWC1'!$C:$C,$C13)+SUMIFS(ADJ!AK:AK,ADJ!$E:$E,$C13) -> 1.3 | AK13: =P13 -> 0 | AL13: =AB13 -> 1.3 | AM13: =AI13 -> 1.3 | AO13: =IFERROR(AVERAGE(AG13:AI13),0) -> 1.3 | AP13: =IFERROR(AVERAGE(AD13:AI13),0) -> 1.3 | AQ13: =IFERROR(AVERAGE(AA13:AI13),0) -> 1.3 | AR13: =IFERROR(AVERAGE(X13:AI13),0) -> 0.975
C14: Due from Kathrin | E14: =SUMIFS('NWC1'!E:E,'NWC1'!$C:$C,$C14)+SUMIFS(ADJ!G:G,ADJ!$E:$E,$C14) -> 0 | F14: =SUMIFS('NWC1'!F:F,'NWC1'!$C:$C,$C14)+SUMIFS(ADJ!H:H,ADJ!$E:$E,$C14) -> 0 | G14: =SUMIFS('NWC1'!G:G,'NWC1'!$C:$C,$C14)+SUMIFS(ADJ!I:I,ADJ!$E:$E,$C14) -> 0 | H14: =SUMIFS('NWC1'!H:H,'NWC1'!$C:$C,$C14)+SUMIFS(ADJ!J:J,ADJ!$E:$E,$C14) -> 0.05252 | I14: =SUMIFS('NWC1'!I:I,'NWC1'!$C:$C,$C14)+SUMIFS(ADJ!K:K,ADJ!$E:$E,$C14) -> 0.05252 | J14: =SUMIFS('NWC1'!J:J,'NWC1'!$C:$C,$C14)+SUMIFS(ADJ!L:L,ADJ!$E:$E,$C14) -> 0.05252 | K14: =SUMIFS('NWC1'!K:K,'NWC1'!$C:$C,$C14)+SUMIFS(ADJ!M:M,ADJ!$E:$E,$C14) -> 0.05252 | L14: =SUMIFS('NWC1'!L:L,'NWC1'!$C:$C,$C14)+SUMIFS(ADJ!N:N,ADJ!$E:$E,$C14) -> 0.05252 | M14: =SUMIFS('NWC1'!M:M,'NWC1'!$C:$C,$C14)+SUMIFS(ADJ!O:O,ADJ!$E:$E,$C14) -> 0.05252 | N14: =SUMIFS('NWC1'!N:N,'NWC1'!$C:$C,$C14)+SUMIFS(ADJ!P:P,ADJ!$E:$E,$C14) -> 0.05252 | O14: =SUMIFS('NWC1'!O:O,'NWC1'!$C:$C,$C14)+SUMIFS(ADJ!Q:Q,ADJ!$E:$E,$C14) -> 0.05252 | P14: =SUMIFS('NWC1'!P:P,'NWC1'!$C:$C,$C14)+SUMIFS(ADJ!R:R,ADJ!$E:$E,$C14) -> 0.05252 | Q14: =SUMIFS('NWC1'!Q:Q,'NWC1'!$C:$C,$C14)+SUMIFS(ADJ!S:S,ADJ!$E:$E,$C14) -> 0.05252 | R14: =SUMIFS('NWC1'!R:R,'NWC1'!$C:$C,$C14)+SUMIFS(ADJ!T:T,ADJ!$E:$E,$C14) -> 0.05252 | S14: =SUMIFS('NWC1'!S:S,'NWC1'!$C:$C,$C14)+SUMIFS(ADJ!U:U,ADJ!$E:$E,$C14) -> 0.05252 | T14: =SUMIFS('NWC1'!T:T,'NWC1'!$C:$C,$C14)+SUMIFS(ADJ!V:V,ADJ!$E:$E,$C14) -> 0.05252 | U14: =SUMIFS('NWC1'!U:U,'NWC1'!$C:$C,$C14)+SUMIFS(ADJ!W:W,ADJ!$E:$E,$C14) -> 0.05252 | V14: =SUMIFS('NWC1'!V:V,'NWC1'!$C:$C,$C14)+SUMIFS(ADJ!X:X,ADJ!$E:$E,$C14) -> 0.05252 | W14: =SUMIFS('NWC1'!W:W,'NWC1'!$C:$C,$C14)+SUMIFS(ADJ!Y:Y,ADJ!$E:$E,$C14) -> 0.05252 | X14: =SUMIFS('NWC1'!X:X,'NWC1'!$C:$C,$C14)+SUMIFS(ADJ!Z:Z,ADJ!$E:$E,$C14) -> 0.05252 | Y14: =SUMIFS('NWC1'!Y:Y,'NWC1'!$C:$C,$C14)+SUMIFS(ADJ!AA:AA,ADJ!$E:$E,$C14) -> 0.05252 | Z14: =SUMIFS('NWC1'!Z:Z,'NWC1'!$C:$C,$C14)+SUMIFS(ADJ!AB:AB,ADJ!$E:$E,$C14) -> 0.05252 | AA14: =SUMIFS('NWC1'!AA:AA,'NWC1'!$C:$C,$C14)+SUMIFS(ADJ!AC:AC,ADJ!$E:$E,$C14) -> 0.05252 | AB14: =SUMIFS('NWC1'!AB:AB,'NWC1'!$C:$C,$C14)+SUMIFS(ADJ!AD:AD,ADJ!$E:$E,$C14) -> 0.05252 | AC14: =SUMIFS('NWC1'!AC:AC,'NWC1'!$C:$C,$C14)+SUMIFS(ADJ!AE:AE,ADJ!$E:$E,$C14) -> 0.05252 | AD14: =SUMIFS('NWC1'!AD:AD,'NWC1'!$C:$C,$C14)+SUMIFS(ADJ!AF:AF,ADJ!$E:$E,$C14) -> 0.05252 | AE14: =SUMIFS('NWC1'!AE:AE,'NWC1'!$C:$C,$C14)+SUMIFS(ADJ!AG:AG,ADJ!$E:$E,$C14) -> 0.05252 | AF14: =SUMIFS('NWC1'!AF:AF,'NWC1'!$C:$C,$C14)+SUMIFS(ADJ!AH:AH,ADJ!$E:$E,$C14) -> 0.05252 | AG14: =SUMIFS('NWC1'!AG:AG,'NWC1'!$C:$C,$C14)+SUMIFS(ADJ!AI:AI,ADJ!$E:$E,$C14) -> 0.05252 | AH14: =SUMIFS('NWC1'!AH:AH,'NWC1'!$C:$C,$C14)+SUMIFS(ADJ!AJ:AJ,ADJ!$E:$E,$C14) -> 0.05252 | AI14: =SUMIFS('NWC1'!AI:AI,'NWC1'!$C:$C,$C14)+SUMIFS(ADJ!AK:AK,ADJ!$E:$E,$C14) -> 0.05252 | AK14: =P14 -> 0.05252 | AL14: =AB14 -> 0.05252 | AM14: =AI14 -> 0.05252 | AO14: =IFERROR(AVERAGE(AG14:AI14),0) -> 0.05252 | AP14: =IFERROR(AVERAGE(AD14:AI14),0) -> 0.05252 | AQ14: =IFERROR(AVERAGE(AA14:AI14),0) -> 0.05252 | AR14: =IFERROR(AVERAGE(X14:AI14),0) -> 0.05252
C15: Due from Amex | E15: =SUMIFS('NWC1'!E:E,'NWC1'!$C:$C,$C15)+SUMIFS(ADJ!G:G,ADJ!$E:$E,$C15) -> 0.02887 | F15: =SUMIFS('NWC1'!F:F,'NWC1'!$C:$C,$C15)+SUMIFS(ADJ!H:H,ADJ!$E:$E,$C15) -> 0.02887 | G15: =SUMIFS('NWC1'!G:G,'NWC1'!$C:$C,$C15)+SUMIFS(ADJ!I:I,ADJ!$E:$E,$C15) -> 0.02887 | H15: =SUMIFS('NWC1'!H:H,'NWC1'!$C:$C,$C15)+SUMIFS(ADJ!J:J,ADJ!$E:$E,$C15) -> 0.02887 | I15: =SUMIFS('NWC1'!I:I,'NWC1'!$C:$C,$C15)+SUMIFS(ADJ!K:K,ADJ!$E:$E,$C15) -> 0.02887 | J15: =SUMIFS('NWC1'!J:J,'NWC1'!$C:$C,$C15)+SUMIFS(ADJ!L:L,ADJ!$E:$E,$C15) -> 0.02887 | K15: =SUMIFS('NWC1'!K:K,'NWC1'!$C:$C,$C15)+SUMIFS(ADJ!M:M,ADJ!$E:$E,$C15) -> 0 | L15: =SUMIFS('NWC1'!L:L,'NWC1'!$C:$C,$C15)+SUMIFS(ADJ!N:N,ADJ!$E:$E,$C15) -> 0 | M15: =SUMIFS('NWC1'!M:M,'NWC1'!$C:$C,$C15)+SUMIFS(ADJ!O:O,ADJ!$E:$E,$C15) -> 0 | N15: =SUMIFS('NWC1'!N:N,'NWC1'!$C:$C,$C15)+SUMIFS(ADJ!P:P,ADJ!$E:$E,$C15) -> 0 | O15: =SUMIFS('NWC1'!O:O,'NWC1'!$C:$C,$C15)+SUMIFS(ADJ!Q:Q,ADJ!$E:$E,$C15) -> 0 | P15: =SUMIFS('NWC1'!P:P,'NWC1'!$C:$C,$C15)+SUMIFS(ADJ!R:R,ADJ!$E:$E,$C15) -> 0 | Q15: =SUMIFS('NWC1'!Q:Q,'NWC1'!$C:$C,$C15)+SUMIFS(ADJ!S:S,ADJ!$E:$E,$C15) -> 0 | R15: =SUMIFS('NWC1'!R:R,'NWC1'!$C:$C,$C15)+SUMIFS(ADJ!T:T,ADJ!$E:$E,$C15) -> 0 | S15: =SUMIFS('NWC1'!S:S,'NWC1'!$C:$C,$C15)+SUMIFS(ADJ!U:U,ADJ!$E:$E,$C15) -> 0 | T15: =SUMIFS('NWC1'!T:T,'NWC1'!$C:$C,$C15)+SUMIFS(ADJ!V:V,ADJ!$E:$E,$C15) -> 0 | U15: =SUMIFS('NWC1'!U:U,'NWC1'!$C:$C,$C15)+SUMIFS(ADJ!W:W,ADJ!$E:$E,$C15) -> 0 | V15: =SUMIFS('NWC1'!V:V,'NWC1'!$C:$C,$C15)+SUMIFS(ADJ!X:X,ADJ!$E:$E,$C15) -> 0 | W15: =SUMIFS('NWC1'!W:W,'NWC1'!$C:$C,$C15)+SUMIFS(ADJ!Y:Y,ADJ!$E:$E,$C15) -> 0 | X15: =SUMIFS('NWC1'!X:X,'NWC1'!$C:$C,$C15)+SUMIFS(ADJ!Z:Z,ADJ!$E:$E,$C15) -> 0 | Y15: =SUMIFS('NWC1'!Y:Y,'NWC1'!$C:$C,$C15)+SUMIFS(ADJ!AA:AA,ADJ!$E:$E,$C15) -> 0 | Z15: =SUMIFS('NWC1'!Z:Z,'NWC1'!$C:$C,$C15)+SUMIFS(ADJ!AB:AB,ADJ!$E:$E,$C15) -> 0 | AA15: =SUMIFS('NWC1'!AA:AA,'NWC1'!$C:$C,$C15)+SUMIFS(ADJ!AC:AC,ADJ!$E:$E,$C15) -> 0 | AB15: =SUMIFS('NWC1'!AB:AB,'NWC1'!$C:$C,$C15)+SUMIFS(ADJ!AD:AD,ADJ!$E:$E,$C15) -> 0 | AC15: =SUMIFS('NWC1'!AC:AC,'NWC1'!$C:$C,$C15)+SUMIFS(ADJ!AE:AE,ADJ!$E:$E,$C15) -> 0 | AD15: =SUMIFS('NWC1'!AD:AD,'NWC1'!$C:$C,$C15)+SUMIFS(ADJ!AF:AF,ADJ!$E:$E,$C15) -> 0 | AE15: =SUMIFS('NWC1'!AE:AE,'NWC1'!$C:$C,$C15)+SUMIFS(ADJ!AG:AG,ADJ!$E:$E,$C15) -> 0 | AF15: =SUMIFS('NWC1'!AF:AF,'NWC1'!$C:$C,$C15)+SUMIFS(ADJ!AH:AH,ADJ!$E:$E,$C15) -> 0 | AG15: =SUMIFS('NWC1'!AG:AG,'NWC1'!$C:$C,$C15)+SUMIFS(ADJ!AI:AI,ADJ!$E:$E,$C15) -> 0 | AH15: =SUMIFS('NWC1'!AH:AH,'NWC1'!$C:$C,$C15)+SUMIFS(ADJ!AJ:AJ,ADJ!$E:$E,$C15) -> 0 | AI15: =SUMIFS('NWC1'!AI:AI,'NWC1'!$C:$C,$C15)+SUMIFS(ADJ!AK:AK,ADJ!$E:$E,$C15) -> 0 | AK15: =P15 -> 0 | AL15: =AB15 -> 0 | AM15: =AI15 -> 0 | AO15: =IFERROR(AVERAGE(AG15:AI15),0) -> 0 | AP15: =IFERROR(AVERAGE(AD15:AI15),0) -> 0 | AQ15: =IFERROR(AVERAGE(AA15:AI15),0) -> 0 | AR15: =IFERROR(AVERAGE(X15:AI15),0) -> 0
C16: Due from Fred | E16: =SUMIFS('NWC1'!E:E,'NWC1'!$C:$C,$C16)+SUMIFS(ADJ!G:G,ADJ!$E:$E,$C16) -> 0.04193 | F16: =SUMIFS('NWC1'!F:F,'NWC1'!$C:$C,$C16)+SUMIFS(ADJ!H:H,ADJ!$E:$E,$C16) -> 0.04193 | G16: =SUMIFS('NWC1'!G:G,'NWC1'!$C:$C,$C16)+SUMIFS(ADJ!I:I,ADJ!$E:$E,$C16) -> 0.04193 | H16: =SUMIFS('NWC1'!H:H,'NWC1'!$C:$C,$C16)+SUMIFS(ADJ!J:J,ADJ!$E:$E,$C16) -> 0.04193 | I16: =SUMIFS('NWC1'!I:I,'NWC1'!$C:$C,$C16)+SUMIFS(ADJ!K:K,ADJ!$E:$E,$C16) -> 0.04193 | J16: =SUMIFS('NWC1'!J:J,'NWC1'!$C:$C,$C16)+SUMIFS(ADJ!L:L,ADJ!$E:$E,$C16) -> 0.04193 | K16: =SUMIFS('NWC1'!K:K,'NWC1'!$C:$C,$C16)+SUMIFS(ADJ!M:M,ADJ!$E:$E,$C16) -> 0 | L16: =SUMIFS('NWC1'!L:L,'NWC1'!$C:$C,$C16)+SUMIFS(ADJ!N:N,ADJ!$E:$E,$C16) -> 0 | M16: =SUMIFS('NWC1'!M:M,'NWC1'!$C:$C,$C16)+SUMIFS(ADJ!O:O,ADJ!$E:$E,$C16) -> 0 | N16: =SUMIFS('NWC1'!N:N,'NWC1'!$C:$C,$C16)+SUMIFS(ADJ!P:P,ADJ!$E:$E,$C16) -> 0 | O16: =SUMIFS('NWC1'!O:O,'NWC1'!$C:$C,$C16)+SUMIFS(ADJ!Q:Q,ADJ!$E:$E,$C16) -> 0 | P16: =SUMIFS('NWC1'!P:P,'NWC1'!$C:$C,$C16)+SUMIFS(ADJ!R:R,ADJ!$E:$E,$C16) -> 0 | Q16: =SUMIFS('NWC1'!Q:Q,'NWC1'!$C:$C,$C16)+SUMIFS(ADJ!S:S,ADJ!$E:$E,$C16) -> 0 | R16: =SUMIFS('NWC1'!R:R,'NWC1'!$C:$C,$C16)+SUMIFS(ADJ!T:T,ADJ!$E:$E,$C16) -> 0 | S16: =SUMIFS('NWC1'!S:S,'NWC1'!$C:$C,$C16)+SUMIFS(ADJ!U:U,ADJ!$E:$E,$C16) -> 0 | T16: =SUMIFS('NWC1'!T:T,'NWC1'!$C:$C,$C16)+SUMIFS(ADJ!V:V,ADJ!$E:$E,$C16) -> 0 | U16: =SUMIFS('NWC1'!U:U,'NWC1'!$C:$C,$C16)+SUMIFS(ADJ!W:W,ADJ!$E:$E,$C16) -> 0 | V16: =SUMIFS('NWC1'!V:V,'NWC1'!$C:$C,$C16)+SUMIFS(ADJ!X:X,ADJ!$E:$E,$C16) -> 0 | W16: =SUMIFS('NWC1'!W:W,'NWC1'!$C:$C,$C16)+SUMIFS(ADJ!Y:Y,ADJ!$E:$E,$C16) -> 0 | X16: =SUMIFS('NWC1'!X:X,'NWC1'!$C:$C,$C16)+SUMIFS(ADJ!Z:Z,ADJ!$E:$E,$C16) -> 0 | Y16: =SUMIFS('NWC1'!Y:Y,'NWC1'!$C:$C,$C16)+SUMIFS(ADJ!AA:AA,ADJ!$E:$E,$C16) -> 0 | Z16: =SUMIFS('NWC1'!Z:Z,'NWC1'!$C:$C,$C16)+SUMIFS(ADJ!AB:AB,ADJ!$E:$E,$C16) -> 0 | AA16: =SUMIFS('NWC1'!AA:AA,'NWC1'!$C:$C,$C16)+SUMIFS(ADJ!AC:AC,ADJ!$E:$E,$C16) -> 0 | AB16: =SUMIFS('NWC1'!AB:AB,'NWC1'!$C:$C,$C16)+SUMIFS(ADJ!AD:AD,ADJ!$E:$E,$C16) -> 0 | AC16: =SUMIFS('NWC1'!AC:AC,'NWC1'!$C:$C,$C16)+SUMIFS(ADJ!AE:AE,ADJ!$E:$E,$C16) -> 0 | AD16: =SUMIFS('NWC1'!AD:AD,'NWC1'!$C:$C,$C16)+SUMIFS(ADJ!AF:AF,ADJ!$E:$E,$C16) -> 0 | AE16: =SUMIFS('NWC1'!AE:AE,'NWC1'!$C:$C,$C16)+SUMIFS(ADJ!AG:AG,ADJ!$E:$E,$C16) -> 0 | AF16: =SUMIFS('NWC1'!AF:AF,'NWC1'!$C:$C,$C16)+SUMIFS(ADJ!AH:AH,ADJ!$E:$E,$C16) -> 0 | AG16: =SUMIFS('NWC1'!AG:AG,'NWC1'!$C:$C,$C16)+SUMIFS(ADJ!AI:AI,ADJ!$E:$E,$C16) -> 0 | AH16: =SUMIFS('NWC1'!AH:AH,'NWC1'!$C:$C,$C16)+SUMIFS(ADJ!AJ:AJ,ADJ!$E:$E,$C16) -> 0 | AI16: =SUMIFS('NWC1'!AI:AI,'NWC1'!$C:$C,$C16)+SUMIFS(ADJ!AK:AK,ADJ!$E:$E,$C16) -> 0 | AK16: =P16 -> 0 | AL16: =AB16 -> 0 | AM16: =AI16 -> 0 | AO16: =IFERROR(AVERAGE(AG16:AI16),0) -> 0 | AP16: =IFERROR(AVERAGE(AD16:AI16),0) -> 0 | AQ16: =IFERROR(AVERAGE(AA16:AI16),0) -> 0 | AR16: =IFERROR(AVERAGE(X16:AI16),0) -> 0
C17: Due from Cheri | E17: =SUMIFS('NWC1'!E:E,'NWC1'!$C:$C,$C17)+SUMIFS(ADJ!G:G,ADJ!$E:$E,$C17) -> 0 | F17: =SUMIFS('NWC1'!F:F,'NWC1'!$C:$C,$C17)+SUMIFS(ADJ!H:H,ADJ!$E:$E,$C17) -> 0 | G17: =SUMIFS('NWC1'!G:G,'NWC1'!$C:$C,$C17)+SUMIFS(ADJ!I:I,ADJ!$E:$E,$C17) -> 0 | H17: =SUMIFS('NWC1'!H:H,'NWC1'!$C:$C,$C17)+SUMIFS(ADJ!J:J,ADJ!$E:$E,$C17) -> 0 | I17: =SUMIFS('NWC1'!I:I,'NWC1'!$C:$C,$C17)+SUMIFS(ADJ!K:K,ADJ!$E:$E,$C17) -> 0 | J17: =SUMIFS('NWC1'!J:J,'NWC1'!$C:$C,$C17)+SUMIFS(ADJ!L:L,ADJ!$E:$E,$C17) -> 0 | K17: =SUMIFS('NWC1'!K:K,'NWC1'!$C:$C,$C17)+SUMIFS(ADJ!M:M,ADJ!$E:$E,$C17) -> 0 | L17: =SUMIFS('NWC1'!L:L,'NWC1'!$C:$C,$C17)+SUMIFS(ADJ!N:N,ADJ!$E:$E,$C17) -> 0 | M17: =SUMIFS('NWC1'!M:M,'NWC1'!$C:$C,$C17)+SUMIFS(ADJ!O:O,ADJ!$E:$E,$C17) -> 0 | N17: =SUMIFS('NWC1'!N:N,'NWC1'!$C:$C,$C17)+SUMIFS(ADJ!P:P,ADJ!$E:$E,$C17) -> 0 | O17: =SUMIFS('NWC1'!O:O,'NWC1'!$C:$C,$C17)+SUMIFS(ADJ!Q:Q,ADJ!$E:$E,$C17) -> 0 | P17: =SUMIFS('NWC1'!P:P,'NWC1'!$C:$C,$C17)+SUMIFS(ADJ!R:R,ADJ!$E:$E,$C17) -> 0 | Q17: =SUMIFS('NWC1'!Q:Q,'NWC1'!$C:$C,$C17)+SUMIFS(ADJ!S:S,ADJ!$E:$E,$C17) -> 0 | R17: =SUMIFS('NWC1'!R:R,'NWC1'!$C:$C,$C17)+SUMIFS(ADJ!T:T,ADJ!$E:$E,$C17) -> 0 | S17: =SUMIFS('NWC1'!S:S,'NWC1'!$C:$C,$C17)+SUMIFS(ADJ!U:U,ADJ!$E:$E,$C17) -> 0 | T17: =SUMIFS('NWC1'!T:T,'NWC1'!$C:$C,$C17)+SUMIFS(ADJ!V:V,ADJ!$E:$E,$C17) -> 0 | U17: =SUMIFS('NWC1'!U:U,'NWC1'!$C:$C,$C17)+SUMIFS(ADJ!W:W,ADJ!$E:$E,$C17) -> 0.02 | V17: =SUMIFS('NWC1'!V:V,'NWC1'!$C:$C,$C17)+SUMIFS(ADJ!X:X,ADJ!$E:$E,$C17) -> 0 | W17: =SUMIFS('NWC1'!W:W,'NWC1'!$C:$C,$C17)+SUMIFS(ADJ!Y:Y,ADJ!$E:$E,$C17) -> 0 | X17: =SUMIFS('NWC1'!X:X,'NWC1'!$C:$C,$C17)+SUMIFS(ADJ!Z:Z,ADJ!$E:$E,$C17) -> 0 | Y17: =SUMIFS('NWC1'!Y:Y,'NWC1'!$C:$C,$C17)+SUMIFS(ADJ!AA:AA,ADJ!$E:$E,$C17) -> 0 | Z17: =SUMIFS('NWC1'!Z:Z,'NWC1'!$C:$C,$C17)+SUMIFS(ADJ!AB:AB,ADJ!$E:$E,$C17) -> 0 | AA17: =SUMIFS('NWC1'!AA:AA,'NWC1'!$C:$C,$C17)+SUMIFS(ADJ!AC:AC,ADJ!$E:$E,$C17) -> 0 | AB17: =SUMIFS('NWC1'!AB:AB,'NWC1'!$C:$C,$C17)+SUMIFS(ADJ!AD:AD,ADJ!$E:$E,$C17) -> 0 | AC17: =SUMIFS('NWC1'!AC:AC,'NWC1'!$C:$C,$C17)+SUMIFS(ADJ!AE:AE,ADJ!$E:$E,$C17) -> 0 | AD17: =SUMIFS('NWC1'!AD:AD,'NWC1'!$C:$C,$C17)+SUMIFS(ADJ!AF:AF,ADJ!$E:$E,$C17) -> 0 | AE17: =SUMIFS('NWC1'!AE:AE,'NWC1'!$C:$C,$C17)+SUMIFS(ADJ!AG:AG,ADJ!$E:$E,$C17) -> 0 | AF17: =SUMIFS('NWC1'!AF:AF,'NWC1'!$C:$C,$C17)+SUMIFS(ADJ!AH:AH,ADJ!$E:$E,$C17) -> 0 | AG17: =SUMIFS('NWC1'!AG:AG,'NWC1'!$C:$C,$C17)+SUMIFS(ADJ!AI:AI,ADJ!$E:$E,$C17) -> 0 | AH17: =SUMIFS('NWC1'!AH:AH,'NWC1'!$C:$C,$C17)+SUMIFS(ADJ!AJ:AJ,ADJ!$E:$E,$C17) -> 0 | AI17: =SUMIFS('NWC1'!AI:AI,'NWC1'!$C:$C,$C17)+SUMIFS(ADJ!AK:AK,ADJ!$E:$E,$C17) -> 0 | AK17: =P17 -> 0 | AL17: =AB17 -> 0 | AM17: =AI17 -> 0 | AO17: =IFERROR(AVERAGE(AG17:AI17),0) -> 0 | AP17: =IFERROR(AVERAGE(AD17:AI17),0) -> 0 | AQ17: =IFERROR(AVERAGE(AA17:AI17),0) -> 0 | AR17: =IFERROR(AVERAGE(X17:AI17),0) -> 0
C18: Other receivables | E18: =SUM(E12:E17) -> 0.3708 | F18: =SUM(F12:F17) -> 0.3708 | G18: =SUM(G12:G17) -> 0.3708 | H18: =SUM(H12:H17) -> 0.42332 | I18: =SUM(I12:I17) -> 0.42332 | J18: =SUM(J12:J17) -> 0.42332 | K18: =SUM(K12:K17) -> 0.35252 | L18: =SUM(L12:L17) -> 0.35252 | ... AI18: =SUM(AI12:AI17) -> 4.29152 | AK18: =SUM(AK12:AK17) -> 0.35252 | AL18: =SUM(AL12:AL17) -> 4.29152 | AM18: =SUM(AM12:AM17) -> 4.29152 | AO18: =SUM(AO12:AO17) -> 4.29152 | AP18: =SUM(AP12:AP17) -> 4.29152 | AQ18: =SUM(AQ12:AQ17) -> 4.29152 | AR18: =SUM(AR12:AR17) -> 3.96652
C20: Prepaid Expenses | E20: =SUMIFS('NWC1'!E:E,'NWC1'!$C:$C,$C20)+SUMIFS(ADJ!G:G,ADJ!$E:$E,$C20) -> 0 | F20: =SUMIFS('NWC1'!F:F,'NWC1'!$C:$C,$C20)+SUMIFS(ADJ!H:H,ADJ!$E:$E,$C20) -> 0 | G20: =SUMIFS('NWC1'!G:G,'NWC1'!$C:$C,$C20)+SUMIFS(ADJ!I:I,ADJ!$E:$E,$C20) -> 0 | H20: =SUMIFS('NWC1'!H:H,'NWC1'!$C:$C,$C20)+SUMIFS(ADJ!J:J,ADJ!$E:$E,$C20) -> 0 | I20: =SUMIFS('NWC1'!I:I,'NWC1'!$C:$C,$C20)+SUMIFS(ADJ!K:K,ADJ!$E:$E,$C20) -> 0 | J20: =SUMIFS('NWC1'!J:J,'NWC1'!$C:$C,$C20)+SUMIFS(ADJ!L:L,ADJ!$E:$E,$C20) -> 0 | K20: =SUMIFS('NWC1'!K:K,'NWC1'!$C:$C,$C20)+SUMIFS(ADJ!M:M,ADJ!$E:$E,$C20) -> 0 | L20: =SUMIFS('NWC1'!L:L,'NWC1'!$C:$C,$C20)+SUMIFS(ADJ!N:N,ADJ!$E:$E,$C20) -> 0 | M20: =SUMIFS('NWC1'!M:M,'NWC1'!$C:$C,$C20)+SUMIFS(ADJ!O:O,ADJ!$E:$E,$C20) -> -5 | N20: =SUMIFS('NWC1'!N:N,'NWC1'!$C:$C,$C20)+SUMIFS(ADJ!P:P,ADJ!$E:$E,$C20) -> -5 | O20: =SUMIFS('NWC1'!O:O,'NWC1'!$C:$C,$C20)+SUMIFS(ADJ!Q:Q,ADJ!$E:$E,$C20) -> -5 | P20: =SUMIFS('NWC1'!P:P,'NWC1'!$C:$C,$C20)+SUMIFS(ADJ!R:R,ADJ!$E:$E,$C20) -> -5 | Q20: =SUMIFS('NWC1'!Q:Q,'NWC1'!$C:$C,$C20)+SUMIFS(ADJ!S:S,ADJ!$E:$E,$C20) -> 0 | R20: =SUMIFS('NWC1'!R:R,'NWC1'!$C:$C,$C20)+SUMIFS(ADJ!T:T,ADJ!$E:$E,$C20) -> 0 | S20: =SUMIFS('NWC1'!S:S,'NWC1'!$C:$C,$C20)+SUMIFS(ADJ!U:U,ADJ!$E:$E,$C20) -> 0 | T20: =SUMIFS('NWC1'!T:T,'NWC1'!$C:$C,$C20)+SUMIFS(ADJ!V:V,ADJ!$E:$E,$C20) -> 0 | U20: =SUMIFS('NWC1'!U:U,'NWC1'!$C:$C,$C20)+SUMIFS(ADJ!W:W,ADJ!$E:$E,$C20) -> 0 | V20: =SUMIFS('NWC1'!V:V,'NWC1'!$C:$C,$C20)+SUMIFS(ADJ!X:X,ADJ!$E:$E,$C20) -> 0 | W20: =SUMIFS('NWC1'!W:W,'NWC1'!$C:$C,$C20)+SUMIFS(ADJ!Y:Y,ADJ!$E:$E,$C20) -> 0 | X20: =SUMIFS('NWC1'!X:X,'NWC1'!$C:$C,$C20)+SUMIFS(ADJ!Z:Z,ADJ!$E:$E,$C20) -> 0 | Y20: =SUMIFS('NWC1'!Y:Y,'NWC1'!$C:$C,$C20)+SUMIFS(ADJ!AA:AA,ADJ!$E:$E,$C20) -> 0 | Z20: =SUMIFS('NWC1'!Z:Z,'NWC1'!$C:$C,$C20)+SUMIFS(ADJ!AB:AB,ADJ!$E:$E,$C20) -> 0 | AA20: =SUMIFS('NWC1'!AA:AA,'NWC1'!$C:$C,$C20)+SUMIFS(ADJ!AC:AC,ADJ!$E:$E,$C20) -> 0 | AB20: =SUMIFS('NWC1'!AB:AB,'NWC1'!$C:$C,$C20)+SUMIFS(ADJ!AD:AD,ADJ!$E:$E,$C20) -> 0 | AC20: =SUMIFS('NWC1'!AC:AC,'NWC1'!$C:$C,$C20)+SUMIFS(ADJ!AE:AE,ADJ!$E:$E,$C20) -> 0 | AD20: =SUMIFS('NWC1'!AD:AD,'NWC1'!$C:$C,$C20)+SUMIFS(ADJ!AF:AF,ADJ!$E:$E,$C20) -> 0 | AE20: =SUMIFS('NWC1'!AE:AE,'NWC1'!$C:$C,$C20)+SUMIFS(ADJ!AG:AG,ADJ!$E:$E,$C20) -> 0 | AF20: =SUMIFS('NWC1'!AF:AF,'NWC1'!$C:$C,$C20)+SUMIFS(ADJ!AH:AH,ADJ!$E:$E,$C20) -> 0 | AG20: =SUMIFS('NWC1'!AG:AG,'NWC1'!$C:$C,$C20)+SUMIFS(ADJ!AI:AI,ADJ!$E:$E,$C20) -> 0 | AH20: =SUMIFS('NWC1'!AH:AH,'NWC1'!$C:$C,$C20)+SUMIFS(ADJ!AJ:AJ,ADJ!$E:$E,$C20) -> 0 | AI20: =SUMIFS('NWC1'!AI:AI,'NWC1'!$C:$C,$C20)+SUMIFS(ADJ!AK:AK,ADJ!$E:$E,$C20) -> 0 | AK20: =P20 -> -5 | AL20: =AB20 -> 0 | AM20: =AI20 -> 0 | AO20: =IFERROR(AVERAGE(AG20:AI20),0) -> 0 | AP20: =IFERROR(AVERAGE(AD20:AI20),0) -> 0 | AQ20: =IFERROR(AVERAGE(AA20:AI20),0) -> 0 | AR20: =IFERROR(AVERAGE(X20:AI20),0) -> 0
C21: Prepaid expenses | E21: =SUM(E20:E20) -> 0 | F21: =SUM(F20:F20) -> 0 | G21: =SUM(G20:G20) -> 0 | H21: =SUM(H20:H20) -> 0 | I21: =SUM(I20:I20) -> 0 | J21: =SUM(J20:J20) -> 0 | K21: =SUM(K20:K20) -> 0 | L21: =SUM(L20:L20) -> 0 | ... AI21: =SUM(AI20:AI20) -> 0 | AK21: =SUM(AK20:AK20) -> -5 | AL21: =SUM(AL20:AL20) -> 0 | AM21: =SUM(AM20:AM20) -> 0 | AO21: =SUM(AO20:AO20) -> 0 | AP21: =SUM(AP20:AP20) -> 0 | AQ21: =SUM(AQ20:AQ20) -> 0 | AR21: =SUM(AR20:AR20) -> 0
C22: Total current assets | E22: =E10+E18+E21 -> 298.4618 | F22: =F10+F18+F21 -> 348.2653 | G22: =G10+G18+G21 -> 766.6028 | H22: =H10+H18+H21 -> 529.38032 | I22: =I10+I18+I21 -> 459.75132 | J22: =J10+J18+J21 -> 638.37932 | K22: =K10+K18+K21 -> 751.92752 | L22: =L10+L18+L21 -> 1371.778 | ... AI22: =AI10+AI18+AI21 -> 775.05452 | AK22: =AK10+AK18+AK21 -> 632.22852 | AL22: =AL10+AL18+AL21 -> 602.19152 | AM22: =AM10+AM18+AM21 -> 775.05452 | AO22: =AO10+AO18+AO21 -> 743.12485 | AP22: =AP10+AP18+AP21 -> 731.10714 | AQ22: =AQ10+AQ18+AQ21 -> 698.06532 | AR22: =AR10+AR18+AR21 -> 720.3832
C24: Accounts Payable | E24: =SUMIFS('NWC1'!E:E,'NWC1'!$C:$C,$C24)-SUMIFS(ADJ!G:G,ADJ!$E:$E,$C24) -> 102.97868 | F24: =SUMIFS('NWC1'!F:F,'NWC1'!$C:$C,$C24)-SUMIFS(ADJ!H:H,ADJ!$E:$E,$C24) -> 125.28342 | G24: =SUMIFS('NWC1'!G:G,'NWC1'!$C:$C,$C24)-SUMIFS(ADJ!I:I,ADJ!$E:$E,$C24) -> 176.99109 | H24: =SUMIFS('NWC1'!H:H,'NWC1'!$C:$C,$C24)-SUMIFS(ADJ!J:J,ADJ!$E:$E,$C24) -> 66.26168 | I24: =SUMIFS('NWC1'!I:I,'NWC1'!$C:$C,$C24)-SUMIFS(ADJ!K:K,ADJ!$E:$E,$C24) -> 116.23258 | J24: =SUMIFS('NWC1'!J:J,'NWC1'!$C:$C,$C24)-SUMIFS(ADJ!L:L,ADJ!$E:$E,$C24) -> 121.51023 | K24: =SUMIFS('NWC1'!K:K,'NWC1'!$C:$C,$C24)-SUMIFS(ADJ!M:M,ADJ!$E:$E,$C24) -> 187.83073 | L24: =SUMIFS('NWC1'!L:L,'NWC1'!$C:$C,$C24)-SUMIFS(ADJ!N:N,ADJ!$E:$E,$C24) -> 127.9124 | M24: =SUMIFS('NWC1'!M:M,'NWC1'!$C:$C,$C24)-SUMIFS(ADJ!O:O,ADJ!$E:$E,$C24) -> -70.61446 | N24: =SUMIFS('NWC1'!N:N,'NWC1'!$C:$C,$C24)-SUMIFS(ADJ!P:P,ADJ!$E:$E,$C24) -> -35.70238 | O24: =SUMIFS('NWC1'!O:O,'NWC1'!$C:$C,$C24)-SUMIFS(ADJ!Q:Q,ADJ!$E:$E,$C24) -> 175.42124 | P24: =SUMIFS('NWC1'!P:P,'NWC1'!$C:$C,$C24)-SUMIFS(ADJ!R:R,ADJ!$E:$E,$C24) -> 0 | Q24: =SUMIFS('NWC1'!Q:Q,'NWC1'!$C:$C,$C24)-SUMIFS(ADJ!S:S,ADJ!$E:$E,$C24) -> 57.58683 | R24: =SUMIFS('NWC1'!R:R,'NWC1'!$C:$C,$C24)-SUMIFS(ADJ!T:T,ADJ!$E:$E,$C24) -> 5.61409 | S24: =SUMIFS('NWC1'!S:S,'NWC1'!$C:$C,$C24)-SUMIFS(ADJ!U:U,ADJ!$E:$E,$C24) -> 95.67886 | T24: =SUMIFS('NWC1'!T:T,'NWC1'!$C:$C,$C24)-SUMIFS(ADJ!V:V,ADJ!$E:$E,$C24) -> 10.04334 | U24: =SUMIFS('NWC1'!U:U,'NWC1'!$C:$C,$C24)-SUMIFS(ADJ!W:W,ADJ!$E:$E,$C24) -> 131.57437 | V24: =SUMIFS('NWC1'!V:V,'NWC1'!$C:$C,$C24)-SUMIFS(ADJ!X:X,ADJ!$E:$E,$C24) -> 51.04859 | W24: =SUMIFS('NWC1'!W:W,'NWC1'!$C:$C,$C24)-SUMIFS(ADJ!Y:Y,ADJ!$E:$E,$C24) -> 118.19169 | X24: =SUMIFS('NWC1'!X:X,'NWC1'!$C:$C,$C24)-SUMIFS(ADJ!Z:Z,ADJ!$E:$E,$C24) -> 169.122 | Y24: =SUMIFS('NWC1'!Y:Y,'NWC1'!$C:$C,$C24)-SUMIFS(ADJ!AA:AA,ADJ!$E:$E,$C24) -> 118.87129 | Z24: =SUMIFS('NWC1'!Z:Z,'NWC1'!$C:$C,$C24)-SUMIFS(ADJ!AB:AB,ADJ!$E:$E,$C24) -> 222.6332 | AA24: =SUMIFS('NWC1'!AA:AA,'NWC1'!$C:$C,$C24)-SUMIFS(ADJ!AC:AC,ADJ!$E:$E,$C24) -> 96.1504 | AB24: =SUMIFS('NWC1'!AB:AB,'NWC1'!$C:$C,$C24)-SUMIFS(ADJ!AD:AD,ADJ!$E:$E,$C24) -> 66.37326 | AC24: =SUMIFS('NWC1'!AC:AC,'NWC1'!$C:$C,$C24)-SUMIFS(ADJ!AE:AE,ADJ!$E:$E,$C24) -> 111.65542 | AD24: =SUMIFS('NWC1'!AD:AD,'NWC1'!$C:$C,$C24)-SUMIFS(ADJ!AF:AF,ADJ!$E:$E,$C24) -> 144.52427 | AE24: =SUMIFS('NWC1'!AE:AE,'NWC1'!$C:$C,$C24)-SUMIFS(ADJ!AG:AG,ADJ!$E:$E,$C24) -> 237.55036 | AF24: =SUMIFS('NWC1'!AF:AF,'NWC1'!$C:$C,$C24)-SUMIFS(ADJ!AH:AH,ADJ!$E:$E,$C24) -> 57.76213 | AG24: =SUMIFS('NWC1'!AG:AG,'NWC1'!$C:$C,$C24)-SUMIFS(ADJ!AI:AI,ADJ!$E:$E,$C24) -> 154.90525 | AH24: =SUMIFS('NWC1'!AH:AH,'NWC1'!$C:$C,$C24)-SUMIFS(ADJ!AJ:AJ,ADJ!$E:$E,$C24) -> 105.925 | AI24: =SUMIFS('NWC1'!AI:AI,'NWC1'!$C:$C,$C24)-SUMIFS(ADJ!AK:AK,ADJ!$E:$E,$C24) -> 95.75599 | AK24: =P24 -> 0 | AL24: =AB24 -> 66.37326 | AM24: =AI24 -> 95.75599 | AO24: =IFERROR(AVERAGE(AG24:AI24),0) -> 118.86208 | AP24: =IFERROR(AVERAGE(AD24:AI24),0) -> 132.73717 | AQ24: =IFERROR(AVERAGE(AA24:AI24),0) -> 118.95579 | AR24: =IFERROR(AVERAGE(X24:AI24),0) -> 131.76905
C25: Accounts payable | E25: =SUM(E24:E24) -> 102.97868 | F25: =SUM(F24:F24) -> 125.28342 | G25: =SUM(G24:G24) -> 176.99109 | H25: =SUM(H24:H24) -> 66.26168 | I25: =SUM(I24:I24) -> 116.23258 | J25: =SUM(J24:J24) -> 121.51023 | K25: =SUM(K24:K24) -> 187.83073 | L25: =SUM(L24:L24) -> 127.9124 | ... AI25: =SUM(AI24:AI24) -> 95.75599 | AK25: =SUM(AK24:AK24) -> 0 | AL25: =SUM(AL24:AL24) -> 66.37326 | AM25: =SUM(AM24:AM24) -> 95.75599 | AO25: =SUM(AO24:AO24) -> 118.86208 | AP25: =SUM(AP24:AP24) -> 132.73717 | AQ25: =SUM(AQ24:AQ24) -> 118.95579 | AR25: =SUM(AR24:AR24) -> 131.76905
C27: Due to The Hartford | E27: =SUMIFS('NWC1'!E:E,'NWC1'!$C:$C,$C27)-SUMIFS(ADJ!G:G,ADJ!$E:$E,$C27) -> 0 | F27: =SUMIFS('NWC1'!F:F,'NWC1'!$C:$C,$C27)-SUMIFS(ADJ!H:H,ADJ!$E:$E,$C27) -> 0 | G27: =SUMIFS('NWC1'!G:G,'NWC1'!$C:$C,$C27)-SUMIFS(ADJ!I:I,ADJ!$E:$E,$C27) -> 0 | H27: =SUMIFS('NWC1'!H:H,'NWC1'!$C:$C,$C27)-SUMIFS(ADJ!J:J,ADJ!$E:$E,$C27) -> 0 | I27: =SUMIFS('NWC1'!I:I,'NWC1'!$C:$C,$C27)-SUMIFS(ADJ!K:K,ADJ!$E:$E,$C27) -> 0 | J27: =SUMIFS('NWC1'!J:J,'NWC1'!$C:$C,$C27)-SUMIFS(ADJ!L:L,ADJ!$E:$E,$C27) -> 0 | K27: =SUMIFS('NWC1'!K:K,'NWC1'!$C:$C,$C27)-SUMIFS(ADJ!M:M,ADJ!$E:$E,$C27) -> 0 | L27: =SUMIFS('NWC1'!L:L,'NWC1'!$C:$C,$C27)-SUMIFS(ADJ!N:N,ADJ!$E:$E,$C27) -> 0 | M27: =SUMIFS('NWC1'!M:M,'NWC1'!$C:$C,$C27)-SUMIFS(ADJ!O:O,ADJ!$E:$E,$C27) -> 0 | N27: =SUMIFS('NWC1'!N:N,'NWC1'!$C:$C,$C27)-SUMIFS(ADJ!P:P,ADJ!$E:$E,$C27) -> 0 | O27: =SUMIFS('NWC1'!O:O,'NWC1'!$C:$C,$C27)-SUMIFS(ADJ!Q:Q,ADJ!$E:$E,$C27) -> 0 | P27: =SUMIFS('NWC1'!P:P,'NWC1'!$C:$C,$C27)-SUMIFS(ADJ!R:R,ADJ!$E:$E,$C27) -> 0 | Q27: =SUMIFS('NWC1'!Q:Q,'NWC1'!$C:$C,$C27)-SUMIFS(ADJ!S:S,ADJ!$E:$E,$C27) -> 0 | R27: =SUMIFS('NWC1'!R:R,'NWC1'!$C:$C,$C27)-SUMIFS(ADJ!T:T,ADJ!$E:$E,$C27) -> 0 | S27: =SUMIFS('NWC1'!S:S,'NWC1'!$C:$C,$C27)-SUMIFS(ADJ!U:U,ADJ!$E:$E,$C27) -> 0 | T27: =SUMIFS('NWC1'!T:T,'NWC1'!$C:$C,$C27)-SUMIFS(ADJ!V:V,ADJ!$E:$E,$C27) -> 0 | U27: =SUMIFS('NWC1'!U:U,'NWC1'!$C:$C,$C27)-SUMIFS(ADJ!W:W,ADJ!$E:$E,$C27) -> 0 | V27: =SUMIFS('NWC1'!V:V,'NWC1'!$C:$C,$C27)-SUMIFS(ADJ!X:X,ADJ!$E:$E,$C27) -> 0 | W27: =SUMIFS('NWC1'!W:W,'NWC1'!$C:$C,$C27)-SUMIFS(ADJ!Y:Y,ADJ!$E:$E,$C27) -> 15.655 | X27: =SUMIFS('NWC1'!X:X,'NWC1'!$C:$C,$C27)-SUMIFS(ADJ!Z:Z,ADJ!$E:$E,$C27) -> 15.655 | Y27: =SUMIFS('NWC1'!Y:Y,'NWC1'!$C:$C,$C27)-SUMIFS(ADJ!AA:AA,ADJ!$E:$E,$C27) -> 15.655 | Z27: =SUMIFS('NWC1'!Z:Z,'NWC1'!$C:$C,$C27)-SUMIFS(ADJ!AB:AB,ADJ!$E:$E,$C27) -> 15.655 | AA27: =SUMIFS('NWC1'!AA:AA,'NWC1'!$C:$C,$C27)-SUMIFS(ADJ!AC:AC,ADJ!$E:$E,$C27) -> 15.655 | AB27: =SUMIFS('NWC1'!AB:AB,'NWC1'!$C:$C,$C27)-SUMIFS(ADJ!AD:AD,ADJ!$E:$E,$C27) -> 15.655 | AC27: =SUMIFS('NWC1'!AC:AC,'NWC1'!$C:$C,$C27)-SUMIFS(ADJ!AE:AE,ADJ!$E:$E,$C27) -> 15.655 | AD27: =SUMIFS('NWC1'!AD:AD,'NWC1'!$C:$C,$C27)-SUMIFS(ADJ!AF:AF,ADJ!$E:$E,$C27) -> 15.655 | AE27: =SUMIFS('NWC1'!AE:AE,'NWC1'!$C:$C,$C27)-SUMIFS(ADJ!AG:AG,ADJ!$E:$E,$C27) -> 15.655 | AF27: =SUMIFS('NWC1'!AF:AF,'NWC1'!$C:$C,$C27)-SUMIFS(ADJ!AH:AH,ADJ!$E:$E,$C27) -> 15.655 | AG27: =SUMIFS('NWC1'!AG:AG,'NWC1'!$C:$C,$C27)-SUMIFS(ADJ!AI:AI,ADJ!$E:$E,$C27) -> 15.655 | AH27: =SUMIFS('NWC1'!AH:AH,'NWC1'!$C:$C,$C27)-SUMIFS(ADJ!AJ:AJ,ADJ!$E:$E,$C27) -> 15.655 | AI27: =SUMIFS('NWC1'!AI:AI,'NWC1'!$C:$C,$C27)-SUMIFS(ADJ!AK:AK,ADJ!$E:$E,$C27) -> 15.655 | AK27: =P27 -> 0 | AL27: =AB27 -> 15.655 | AM27: =AI27 -> 15.655 | AO27: =IFERROR(AVERAGE(AG27:AI27),0) -> 15.655 | AP27: =IFERROR(AVERAGE(AD27:AI27),0) -> 15.655 | AQ27: =IFERROR(AVERAGE(AA27:AI27),0) -> 15.655 | AR27: =IFERROR(AVERAGE(X27:AI27),0) -> 15.655
C28: Due to BCBSA | E28: =SUMIFS('NWC1'!E:E,'NWC1'!$C:$C,$C28)-SUMIFS(ADJ!G:G,ADJ!$E:$E,$C28) -> 0 | F28: =SUMIFS('NWC1'!F:F,'NWC1'!$C:$C,$C28)-SUMIFS(ADJ!H:H,ADJ!$E:$E,$C28) -> 0 | G28: =SUMIFS('NWC1'!G:G,'NWC1'!$C:$C,$C28)-SUMIFS(ADJ!I:I,ADJ!$E:$E,$C28) -> 0 | H28: =SUMIFS('NWC1'!H:H,'NWC1'!$C:$C,$C28)-SUMIFS(ADJ!J:J,ADJ!$E:$E,$C28) -> 0 | I28: =SUMIFS('NWC1'!I:I,'NWC1'!$C:$C,$C28)-SUMIFS(ADJ!K:K,ADJ!$E:$E,$C28) -> 0 | J28: =SUMIFS('NWC1'!J:J,'NWC1'!$C:$C,$C28)-SUMIFS(ADJ!L:L,ADJ!$E:$E,$C28) -> 0 | K28: =SUMIFS('NWC1'!K:K,'NWC1'!$C:$C,$C28)-SUMIFS(ADJ!M:M,ADJ!$E:$E,$C28) -> 0 | L28: =SUMIFS('NWC1'!L:L,'NWC1'!$C:$C,$C28)-SUMIFS(ADJ!N:N,ADJ!$E:$E,$C28) -> 0 | M28: =SUMIFS('NWC1'!M:M,'NWC1'!$C:$C,$C28)-SUMIFS(ADJ!O:O,ADJ!$E:$E,$C28) -> 0 | N28: =SUMIFS('NWC1'!N:N,'NWC1'!$C:$C,$C28)-SUMIFS(ADJ!P:P,ADJ!$E:$E,$C28) -> 0 | O28: =SUMIFS('NWC1'!O:O,'NWC1'!$C:$C,$C28)-SUMIFS(ADJ!Q:Q,ADJ!$E:$E,$C28) -> 0 | P28: =SUMIFS('NWC1'!P:P,'NWC1'!$C:$C,$C28)-SUMIFS(ADJ!R:R,ADJ!$E:$E,$C28) -> 0 | Q28: =SUMIFS('NWC1'!Q:Q,'NWC1'!$C:$C,$C28)-SUMIFS(ADJ!S:S,ADJ!$E:$E,$C28) -> 0 | R28: =SUMIFS('NWC1'!R:R,'NWC1'!$C:$C,$C28)-SUMIFS(ADJ!T:T,ADJ!$E:$E,$C28) -> 0 | S28: =SUMIFS('NWC1'!S:S,'NWC1'!$C:$C,$C28)-SUMIFS(ADJ!U:U,ADJ!$E:$E,$C28) -> 0 | T28: =SUMIFS('NWC1'!T:T,'NWC1'!$C:$C,$C28)-SUMIFS(ADJ!V:V,ADJ!$E:$E,$C28) -> 0 | U28: =SUMIFS('NWC1'!U:U,'NWC1'!$C:$C,$C28)-SUMIFS(ADJ!W:W,ADJ!$E:$E,$C28) -> 0 | V28: =SUMIFS('NWC1'!V:V,'NWC1'!$C:$C,$C28)-SUMIFS(ADJ!X:X,ADJ!$E:$E,$C28) -> 0 | W28: =SUMIFS('NWC1'!W:W,'NWC1'!$C:$C,$C28)-SUMIFS(ADJ!Y:Y,ADJ!$E:$E,$C28) -> 0 | X28: =SUMIFS('NWC1'!X:X,'NWC1'!$C:$C,$C28)-SUMIFS(ADJ!Z:Z,ADJ!$E:$E,$C28) -> 0 | Y28: =SUMIFS('NWC1'!Y:Y,'NWC1'!$C:$C,$C28)-SUMIFS(ADJ!AA:AA,ADJ!$E:$E,$C28) -> 0 | Z28: =SUMIFS('NWC1'!Z:Z,'NWC1'!$C:$C,$C28)-SUMIFS(ADJ!AB:AB,ADJ!$E:$E,$C28) -> 0 | AA28: =SUMIFS('NWC1'!AA:AA,'NWC1'!$C:$C,$C28)-SUMIFS(ADJ!AC:AC,ADJ!$E:$E,$C28) -> 0 | AB28: =SUMIFS('NWC1'!AB:AB,'NWC1'!$C:$C,$C28)-SUMIFS(ADJ!AD:AD,ADJ!$E:$E,$C28) -> 0 | AC28: =SUMIFS('NWC1'!AC:AC,'NWC1'!$C:$C,$C28)-SUMIFS(ADJ!AE:AE,ADJ!$E:$E,$C28) -> 0 | AD28: =SUMIFS('NWC1'!AD:AD,'NWC1'!$C:$C,$C28)-SUMIFS(ADJ!AF:AF,ADJ!$E:$E,$C28) -> 0 | AE28: =SUMIFS('NWC1'!AE:AE,'NWC1'!$C:$C,$C28)-SUMIFS(ADJ!AG:AG,ADJ!$E:$E,$C28) -> 0 | AF28: =SUMIFS('NWC1'!AF:AF,'NWC1'!$C:$C,$C28)-SUMIFS(ADJ!AH:AH,ADJ!$E:$E,$C28) -> 0 | AG28: =SUMIFS('NWC1'!AG:AG,'NWC1'!$C:$C,$C28)-SUMIFS(ADJ!AI:AI,ADJ!$E:$E,$C28) -> 0 | AH28: =SUMIFS('NWC1'!AH:AH,'NWC1'!$C:$C,$C28)-SUMIFS(ADJ!AJ:AJ,ADJ!$E:$E,$C28) -> 0.58 | AI28: =SUMIFS('NWC1'!AI:AI,'NWC1'!$C:$C,$C28)-SUMIFS(ADJ!AK:AK,ADJ!$E:$E,$C28) -> 0.58 | AK28: =P28 -> 0 | AL28: =AB28 -> 0 | AM28: =AI28 -> 0.58 | AO28: =IFERROR(AVERAGE(AG28:AI28),0) -> 0.38666667 | AP28: =IFERROR(AVERAGE(AD28:AI28),0) -> 0.19333333 | AQ28: =IFERROR(AVERAGE(AA28:AI28),0) -> 0.12888889 | AR28: =IFERROR(AVERAGE(X28:AI28),0) -> 0.096666667
C29: Shareholder Loan-Due to Ken | E29: =SUMIFS('NWC1'!E:E,'NWC1'!$C:$C,$C29)-SUMIFS(ADJ!G:G,ADJ!$E:$E,$C29) -> 0 | F29: =SUMIFS('NWC1'!F:F,'NWC1'!$C:$C,$C29)-SUMIFS(ADJ!H:H,ADJ!$E:$E,$C29) -> 0 | G29: =SUMIFS('NWC1'!G:G,'NWC1'!$C:$C,$C29)-SUMIFS(ADJ!I:I,ADJ!$E:$E,$C29) -> 0 | H29: =SUMIFS('NWC1'!H:H,'NWC1'!$C:$C,$C29)-SUMIFS(ADJ!J:J,ADJ!$E:$E,$C29) -> 0 | I29: =SUMIFS('NWC1'!I:I,'NWC1'!$C:$C,$C29)-SUMIFS(ADJ!K:K,ADJ!$E:$E,$C29) -> 0 | J29: =SUMIFS('NWC1'!J:J,'NWC1'!$C:$C,$C29)-SUMIFS(ADJ!L:L,ADJ!$E:$E,$C29) -> 0 | K29: =SUMIFS('NWC1'!K:K,'NWC1'!$C:$C,$C29)-SUMIFS(ADJ!M:M,ADJ!$E:$E,$C29) -> 0 | L29: =SUMIFS('NWC1'!L:L,'NWC1'!$C:$C,$C29)-SUMIFS(ADJ!N:N,ADJ!$E:$E,$C29) -> 0 | M29: =SUMIFS('NWC1'!M:M,'NWC1'!$C:$C,$C29)-SUMIFS(ADJ!O:O,ADJ!$E:$E,$C29) -> 0 | N29: =SUMIFS('NWC1'!N:N,'NWC1'!$C:$C,$C29)-SUMIFS(ADJ!P:P,ADJ!$E:$E,$C29) -> 0 | O29: =SUMIFS('NWC1'!O:O,'NWC1'!$C:$C,$C29)-SUMIFS(ADJ!Q:Q,ADJ!$E:$E,$C29) -> 0 | P29: =SUMIFS('NWC1'!P:P,'NWC1'!$C:$C,$C29)-SUMIFS(ADJ!R:R,ADJ!$E:$E,$C29) -> 1.21938 | Q29: =SUMIFS('NWC1'!Q:Q,'NWC1'!$C:$C,$C29)-SUMIFS(ADJ!S:S,ADJ!$E:$E,$C29) -> 1.21938 | R29: =SUMIFS('NWC1'!R:R,'NWC1'!$C:$C,$C29)-SUMIFS(ADJ!T:T,ADJ!$E:$E,$C29) -> 1.21938 | S29: =SUMIFS('NWC1'!S:S,'NWC1'!$C:$C,$C29)-SUMIFS(ADJ!U:U,ADJ!$E:$E,$C29) -> 1.21938 | T29: =SUMIFS('NWC1'!T:T,'NWC1'!$C:$C,$C29)-SUMIFS(ADJ!V:V,ADJ!$E:$E,$C29) -> 1.21938 | U29: =SUMIFS('NWC1'!U:U,'NWC1'!$C:$C,$C29)-SUMIFS(ADJ!W:W,ADJ!$E:$E,$C29) -> 1.21938 | V29: =SUMIFS('NWC1'!V:V,'NWC1'!$C:$C,$C29)-SUMIFS(ADJ!X:X,ADJ!$E:$E,$C29) -> 1.21938 | W29: =SUMIFS('NWC1'!W:W,'NWC1'!$C:$C,$C29)-SUMIFS(ADJ!Y:Y,ADJ!$E:$E,$C29) -> 1.21938 | X29: =SUMIFS('NWC1'!X:X,'NWC1'!$C:$C,$C29)-SUMIFS(ADJ!Z:Z,ADJ!$E:$E,$C29) -> 1.21938 | Y29: =SUMIFS('NWC1'!Y:Y,'NWC1'!$C:$C,$C29)-SUMIFS(ADJ!AA:AA,ADJ!$E:$E,$C29) -> 1.21938 | Z29: =SUMIFS('NWC1'!Z:Z,'NWC1'!$C:$C,$C29)-SUMIFS(ADJ!AB:AB,ADJ!$E:$E,$C29) -> 1.21938 | AA29: =SUMIFS('NWC1'!AA:AA,'NWC1'!$C:$C,$C29)-SUMIFS(ADJ!AC:AC,ADJ!$E:$E,$C29) -> 0 | AB29: =SUMIFS('NWC1'!AB:AB,'NWC1'!$C:$C,$C29)-SUMIFS(ADJ!AD:AD,ADJ!$E:$E,$C29) -> 67.84569 | AC29: =SUMIFS('NWC1'!AC:AC,'NWC1'!$C:$C,$C29)-SUMIFS(ADJ!AE:AE,ADJ!$E:$E,$C29) -> 67.84569 | AD29: =SUMIFS('NWC1'!AD:AD,'NWC1'!$C:$C,$C29)-SUMIFS(ADJ!AF:AF,ADJ!$E:$E,$C29) -> 67.84569 | AE29: =SUMIFS('NWC1'!AE:AE,'NWC1'!$C:$C,$C29)-SUMIFS(ADJ!AG:AG,ADJ!$E:$E,$C29) -> 67.84569 | AF29: =SUMIFS('NWC1'!AF:AF,'NWC1'!$C:$C,$C29)-SUMIFS(ADJ!AH:AH,ADJ!$E:$E,$C29) -> 0 | AG29: =SUMIFS('NWC1'!AG:AG,'NWC1'!$C:$C,$C29)-SUMIFS(ADJ!AI:AI,ADJ!$E:$E,$C29) -> 0 | AH29: =SUMIFS('NWC1'!AH:AH,'NWC1'!$C:$C,$C29)-SUMIFS(ADJ!AJ:AJ,ADJ!$E:$E,$C29) -> 0 | AI29: =SUMIFS('NWC1'!AI:AI,'NWC1'!$C:$C,$C29)-SUMIFS(ADJ!AK:AK,ADJ!$E:$E,$C29) -> 0 | AK29: =P29 -> 1.21938 | AL29: =AB29 -> 67.84569 | AM29: =AI29 -> 0 | AO29: =IFERROR(AVERAGE(AG29:AI29),0) -> 0 | AP29: =IFERROR(AVERAGE(AD29:AI29),0) -> 22.61523 | AQ29: =IFERROR(AVERAGE(AA29:AI29),0) -> 30.15364 | AR29: =IFERROR(AVERAGE(X29:AI29),0) -> 22.920075
C30: Due to Exodus | E30: =SUMIFS('NWC1'!E:E,'NWC1'!$C:$C,$C30)-SUMIFS(ADJ!G:G,ADJ!$E:$E,$C30) -> 15 | F30: =SUMIFS('NWC1'!F:F,'NWC1'!$C:$C,$C30)-SUMIFS(ADJ!H:H,ADJ!$E:$E,$C30) -> 15 | G30: =SUMIFS('NWC1'!G:G,'NWC1'!$C:$C,$C30)-SUMIFS(ADJ!I:I,ADJ!$E:$E,$C30) -> 15 | H30: =SUMIFS('NWC1'!H:H,'NWC1'!$C:$C,$C30)-SUMIFS(ADJ!J:J,ADJ!$E:$E,$C30) -> 15 | I30: =SUMIFS('NWC1'!I:I,'NWC1'!$C:$C,$C30)-SUMIFS(ADJ!K:K,ADJ!$E:$E,$C30) -> 15 | J30: =SUMIFS('NWC1'!J:J,'NWC1'!$C:$C,$C30)-SUMIFS(ADJ!L:L,ADJ!$E:$E,$C30) -> 15 | K30: =SUMIFS('NWC1'!K:K,'NWC1'!$C:$C,$C30)-SUMIFS(ADJ!M:M,ADJ!$E:$E,$C30) -> 15 | L30: =SUMIFS('NWC1'!L:L,'NWC1'!$C:$C,$C30)-SUMIFS(ADJ!N:N,ADJ!$E:$E,$C30) -> 0 | M30: =SUMIFS('NWC1'!M:M,'NWC1'!$C:$C,$C30)-SUMIFS(ADJ!O:O,ADJ!$E:$E,$C30) -> 0 | N30: =SUMIFS('NWC1'!N:N,'NWC1'!$C:$C,$C30)-SUMIFS(ADJ!P:P,ADJ!$E:$E,$C30) -> 0 | O30: =SUMIFS('NWC1'!O:O,'NWC1'!$C:$C,$C30)-SUMIFS(ADJ!Q:Q,ADJ!$E:$E,$C30) -> 0 | P30: =SUMIFS('NWC1'!P:P,'NWC1'!$C:$C,$C30)-SUMIFS(ADJ!R:R,ADJ!$E:$E,$C30) -> 0 | Q30: =SUMIFS('NWC1'!Q:Q,'NWC1'!$C:$C,$C30)-SUMIFS(ADJ!S:S,ADJ!$E:$E,$C30) -> 0 | R30: =SUMIFS('NWC1'!R:R,'NWC1'!$C:$C,$C30)-SUMIFS(ADJ!T:T,ADJ!$E:$E,$C30) -> 0 | S30: =SUMIFS('NWC1'!S:S,'NWC1'!$C:$C,$C30)-SUMIFS(ADJ!U:U,ADJ!$E:$E,$C30) -> 0 | T30: =SUMIFS('NWC1'!T:T,'NWC1'!$C:$C,$C30)-SUMIFS(ADJ!V:V,ADJ!$E:$E,$C30) -> 0 | U30: =SUMIFS('NWC1'!U:U,'NWC1'!$C:$C,$C30)-SUMIFS(ADJ!W:W,ADJ!$E:$E,$C30) -> 0 | V30: =SUMIFS('NWC1'!V:V,'NWC1'!$C:$C,$C30)-SUMIFS(ADJ!X:X,ADJ!$E:$E,$C30) -> 0 | W30: =SUMIFS('NWC1'!W:W,'NWC1'!$C:$C,$C30)-SUMIFS(ADJ!Y:Y,ADJ!$E:$E,$C30) -> 0 | X30: =SUMIFS('NWC1'!X:X,'NWC1'!$C:$C,$C30)-SUMIFS(ADJ!Z:Z,ADJ!$E:$E,$C30) -> 0 | Y30: =SUMIFS('NWC1'!Y:Y,'NWC1'!$C:$C,$C30)-SUMIFS(ADJ!AA:AA,ADJ!$E:$E,$C30) -> 0 | Z30: =SUMIFS('NWC1'!Z:Z,'NWC1'!$C:$C,$C30)-SUMIFS(ADJ!AB:AB,ADJ!$E:$E,$C30) -> 0 | AA30: =SUMIFS('NWC1'!AA:AA,'NWC1'!$C:$C,$C30)-SUMIFS(ADJ!AC:AC,ADJ!$E:$E,$C30) -> 0 | AB30: =SUMIFS('NWC1'!AB:AB,'NWC1'!$C:$C,$C30)-SUMIFS(ADJ!AD:AD,ADJ!$E:$E,$C30) -> 0 | AC30: =SUMIFS('NWC1'!AC:AC,'NWC1'!$C:$C,$C30)-SUMIFS(ADJ!AE:AE,ADJ!$E:$E,$C30) -> 0 | AD30: =SUMIFS('NWC1'!AD:AD,'NWC1'!$C:$C,$C30)-SUMIFS(ADJ!AF:AF,ADJ!$E:$E,$C30) -> 0 | AE30: =SUMIFS('NWC1'!AE:AE,'NWC1'!$C:$C,$C30)-SUMIFS(ADJ!AG:AG,ADJ!$E:$E,$C30) -> 0 | AF30: =SUMIFS('NWC1'!AF:AF,'NWC1'!$C:$C,$C30)-SUMIFS(ADJ!AH:AH,ADJ!$E:$E,$C30) -> 0 | AG30: =SUMIFS('NWC1'!AG:AG,'NWC1'!$C:$C,$C30)-SUMIFS(ADJ!AI:AI,ADJ!$E:$E,$C30) -> 0 | AH30: =SUMIFS('NWC1'!AH:AH,'NWC1'!$C:$C,$C30)-SUMIFS(ADJ!AJ:AJ,ADJ!$E:$E,$C30) -> 0 | AI30: =SUMIFS('NWC1'!AI:AI,'NWC1'!$C:$C,$C30)-SUMIFS(ADJ!AK:AK,ADJ!$E:$E,$C30) -> 0 | AK30: =P30 -> 0 | AL30: =AB30 -> 0 | AM30: =AI30 -> 0 | AO30: =IFERROR(AVERAGE(AG30:AI30),0) -> 0 | AP30: =IFERROR(AVERAGE(AD30:AI30),0) -> 0 | AQ30: =IFERROR(AVERAGE(AA30:AI30),0) -> 0 | AR30: =IFERROR(AVERAGE(X30:AI30),0) -> 0
C31: Other payables | E31: =SUM(E27:E30) -> 15 | F31: =SUM(F27:F30) -> 15 | G31: =SUM(G27:G30) -> 15 | H31: =SUM(H27:H30) -> 15 | I31: =SUM(I27:I30) -> 15 | J31: =SUM(J27:J30) -> 15 | K31: =SUM(K27:K30) -> 15 | L31: =SUM(L27:L30) -> 0 | ... AI31: =SUM(AI27:AI30) -> 16.235 | AK31: =SUM(AK27:AK30) -> 1.21938 | AL31: =SUM(AL27:AL30) -> 83.50069 | AM31: =SUM(AM27:AM30) -> 16.235 | AO31: =SUM(AO27:AO30) -> 16.041667 | AP31: =SUM(AP27:AP30) -> 38.463563 | AQ31: =SUM(AQ27:AQ30) -> 45.937529 | AR31: =SUM(AR27:AR30) -> 38.671742
C33: Unearned Revenue | E33: =SUMIFS('NWC1'!E:E,'NWC1'!$C:$C,$C33)-SUMIFS(ADJ!G:G,ADJ!$E:$E,$C33) -> 1166.1135 | F33: =SUMIFS('NWC1'!F:F,'NWC1'!$C:$C,$C33)-SUMIFS(ADJ!H:H,ADJ!$E:$E,$C33) -> 1166.1135 | G33: =SUMIFS('NWC1'!G:G,'NWC1'!$C:$C,$C33)-SUMIFS(ADJ!I:I,ADJ!$E:$E,$C33) -> 1166.1135 | H33: =SUMIFS('NWC1'!H:H,'NWC1'!$C:$C,$C33)-SUMIFS(ADJ!J:J,ADJ!$E:$E,$C33) -> 1166.1135 | I33: =SUMIFS('NWC1'!I:I,'NWC1'!$C:$C,$C33)-SUMIFS(ADJ!K:K,ADJ!$E:$E,$C33) -> 1166.1135 | J33: =SUMIFS('NWC1'!J:J,'NWC1'!$C:$C,$C33)-SUMIFS(ADJ!L:L,ADJ!$E:$E,$C33) -> 1166.1135 | K33: =SUMIFS('NWC1'!K:K,'NWC1'!$C:$C,$C33)-SUMIFS(ADJ!M:M,ADJ!$E:$E,$C33) -> 1166.1135 | L33: =SUMIFS('NWC1'!L:L,'NWC1'!$C:$C,$C33)-SUMIFS(ADJ!N:N,ADJ!$E:$E,$C33) -> 1166.1135 | M33: =SUMIFS('NWC1'!M:M,'NWC1'!$C:$C,$C33)-SUMIFS(ADJ!O:O,ADJ!$E:$E,$C33) -> 1166.1135 | N33: =SUMIFS('NWC1'!N:N,'NWC1'!$C:$C,$C33)-SUMIFS(ADJ!P:P,ADJ!$E:$E,$C33) -> 1166.1135 | O33: =SUMIFS('NWC1'!O:O,'NWC1'!$C:$C,$C33)-SUMIFS(ADJ!Q:Q,ADJ!$E:$E,$C33) -> 1166.1135 | P33: =SUMIFS('NWC1'!P:P,'NWC1'!$C:$C,$C33)-SUMIFS(ADJ!R:R,ADJ!$E:$E,$C33) -> 1112.584 | Q33: =SUMIFS('NWC1'!Q:Q,'NWC1'!$C:$C,$C33)-SUMIFS(ADJ!S:S,ADJ!$E:$E,$C33) -> 1112.584 | R33: =SUMIFS('NWC1'!R:R,'NWC1'!$C:$C,$C33)-SUMIFS(ADJ!T:T,ADJ!$E:$E,$C33) -> 1112.584 | S33: =SUMIFS('NWC1'!S:S,'NWC1'!$C:$C,$C33)-SUMIFS(ADJ!U:U,ADJ!$E:$E,$C33) -> 1000.846 | T33: =SUMIFS('NWC1'!T:T,'NWC1'!$C:$C,$C33)-SUMIFS(ADJ!V:V,ADJ!$E:$E,$C33) -> 1000.846 | U33: =SUMIFS('NWC1'!U:U,'NWC1'!$C:$C,$C33)-SUMIFS(ADJ!W:W,ADJ!$E:$E,$C33) -> 1000.846 | V33: =SUMIFS('NWC1'!V:V,'NWC1'!$C:$C,$C33)-SUMIFS(ADJ!X:X,ADJ!$E:$E,$C33) -> 1000.846 | W33: =SUMIFS('NWC1'!W:W,'NWC1'!$C:$C,$C33)-SUMIFS(ADJ!Y:Y,ADJ!$E:$E,$C33) -> 933.346 | X33: =SUMIFS('NWC1'!X:X,'NWC1'!$C:$C,$C33)-SUMIFS(ADJ!Z:Z,ADJ!$E:$E,$C33) -> 933.346 | Y33: =SUMIFS('NWC1'!Y:Y,'NWC1'!$C:$C,$C33)-SUMIFS(ADJ!AA:AA,ADJ!$E:$E,$C33) -> 933.346 | Z33: =SUMIFS('NWC1'!Z:Z,'NWC1'!$C:$C,$C33)-SUMIFS(ADJ!AB:AB,ADJ!$E:$E,$C33) -> 933.346 | AA33: =SUMIFS('NWC1'!AA:AA,'NWC1'!$C:$C,$C33)-SUMIFS(ADJ!AC:AC,ADJ!$E:$E,$C33) -> 933.346 | AB33: =SUMIFS('NWC1'!AB:AB,'NWC1'!$C:$C,$C33)-SUMIFS(ADJ!AD:AD,ADJ!$E:$E,$C33) -> 925.17 | AC33: =SUMIFS('NWC1'!AC:AC,'NWC1'!$C:$C,$C33)-SUMIFS(ADJ!AE:AE,ADJ!$E:$E,$C33) -> 925.17 | AD33: =SUMIFS('NWC1'!AD:AD,'NWC1'!$C:$C,$C33)-SUMIFS(ADJ!AF:AF,ADJ!$E:$E,$C33) -> 925.17 | AE33: =SUMIFS('NWC1'!AE:AE,'NWC1'!$C:$C,$C33)-SUMIFS(ADJ!AG:AG,ADJ!$E:$E,$C33) -> 851.17 | AF33: =SUMIFS('NWC1'!AF:AF,'NWC1'!$C:$C,$C33)-SUMIFS(ADJ!AH:AH,ADJ!$E:$E,$C33) -> 851.17 | AG33: =SUMIFS('NWC1'!AG:AG,'NWC1'!$C:$C,$C33)-SUMIFS(ADJ!AI:AI,ADJ!$E:$E,$C33) -> 851.17 | AH33: =SUMIFS('NWC1'!AH:AH,'NWC1'!$C:$C,$C33)-SUMIFS(ADJ!AJ:AJ,ADJ!$E:$E,$C33) -> 851.17 | AI33: =SUMIFS('NWC1'!AI:AI,'NWC1'!$C:$C,$C33)-SUMIFS(ADJ!AK:AK,ADJ!$E:$E,$C33) -> 810.145 | AK33: =P33 -> 1112.584 | AL33: =AB33 -> 925.17 | AM33: =AI33 -> 810.145 | AO33: =IFERROR(AVERAGE(AG33:AI33),0) -> 837.495 | AP33: =IFERROR(AVERAGE(AD33:AI33),0) -> 856.66583 | AQ33: =IFERROR(AVERAGE(AA33:AI33),0) -> 880.409 | AR33: =IFERROR(AVERAGE(X33:AI33),0) -> 893.64325
C34: Unearned revenue | E34: =SUM(E33:E33) -> 1166.1135 | F34: =SUM(F33:F33) -> 1166.1135 | G34: =SUM(G33:G33) -> 1166.1135 | H34: =SUM(H33:H33) -> 1166.1135 | I34: =SUM(I33:I33) -> 1166.1135 | J34: =SUM(J33:J33) -> 1166.1135 | K34: =SUM(K33:K33) -> 1166.1135 | L34: =SUM(L33:L33) -> 1166.1135 | ... AI34: =SUM(AI33:AI33) -> 810.145 | AK34: =SUM(AK33:AK33) -> 1112.584 | AL34: =SUM(AL33:AL33) -> 925.17 | AM34: =SUM(AM33:AM33) -> 810.145 | AO34: =SUM(AO33:AO33) -> 837.495 | AP34: =SUM(AP33:AP33) -> 856.66583 | AQ34: =SUM(AQ33:AQ33) -> 880.409 | AR34: =SUM(AR33:AR33) -> 893.64325
C36: Accrued Bonuses | E36: =SUMIFS('NWC1'!E:E,'NWC1'!$C:$C,$C36)-SUMIFS(ADJ!G:G,ADJ!$E:$E,$C36) -> 48.5 | F36: =SUMIFS('NWC1'!F:F,'NWC1'!$C:$C,$C36)-SUMIFS(ADJ!H:H,ADJ!$E:$E,$C36) -> 97 | G36: =SUMIFS('NWC1'!G:G,'NWC1'!$C:$C,$C36)-SUMIFS(ADJ!I:I,ADJ!$E:$E,$C36) -> 145.5 | H36: =SUMIFS('NWC1'!H:H,'NWC1'!$C:$C,$C36)-SUMIFS(ADJ!J:J,ADJ!$E:$E,$C36) -> 194 | I36: =SUMIFS('NWC1'!I:I,'NWC1'!$C:$C,$C36)-SUMIFS(ADJ!K:K,ADJ!$E:$E,$C36) -> 242.5 | J36: =SUMIFS('NWC1'!J:J,'NWC1'!$C:$C,$C36)-SUMIFS(ADJ!L:L,ADJ!$E:$E,$C36) -> 291 | K36: =SUMIFS('NWC1'!K:K,'NWC1'!$C:$C,$C36)-SUMIFS(ADJ!M:M,ADJ!$E:$E,$C36) -> 339.5 | L36: =SUMIFS('NWC1'!L:L,'NWC1'!$C:$C,$C36)-SUMIFS(ADJ!N:N,ADJ!$E:$E,$C36) -> 388 | M36: =SUMIFS('NWC1'!M:M,'NWC1'!$C:$C,$C36)-SUMIFS(ADJ!O:O,ADJ!$E:$E,$C36) -> 436.5 | N36: =SUMIFS('NWC1'!N:N,'NWC1'!$C:$C,$C36)-SUMIFS(ADJ!P:P,ADJ!$E:$E,$C36) -> 485 | O36: =SUMIFS('NWC1'!O:O,'NWC1'!$C:$C,$C36)-SUMIFS(ADJ!Q:Q,ADJ!$E:$E,$C36) -> 533.5 | P36: =SUMIFS('NWC1'!P:P,'NWC1'!$C:$C,$C36)-SUMIFS(ADJ!R:R,ADJ!$E:$E,$C36) -> 0 | Q36: =SUMIFS('NWC1'!Q:Q,'NWC1'!$C:$C,$C36)-SUMIFS(ADJ!S:S,ADJ!$E:$E,$C36) -> 51.25 | R36: =SUMIFS('NWC1'!R:R,'NWC1'!$C:$C,$C36)-SUMIFS(ADJ!T:T,ADJ!$E:$E,$C36) -> 102.5 | S36: =SUMIFS('NWC1'!S:S,'NWC1'!$C:$C,$C36)-SUMIFS(ADJ!U:U,ADJ!$E:$E,$C36) -> 153.75 | T36: =SUMIFS('NWC1'!T:T,'NWC1'!$C:$C,$C36)-SUMIFS(ADJ!V:V,ADJ!$E:$E,$C36) -> 205 | U36: =SUMIFS('NWC1'!U:U,'NWC1'!$C:$C,$C36)-SUMIFS(ADJ!W:W,ADJ!$E:$E,$C36) -> 256.25 | V36: =SUMIFS('NWC1'!V:V,'NWC1'!$C:$C,$C36)-SUMIFS(ADJ!X:X,ADJ!$E:$E,$C36) -> 307.5 | W36: =SUMIFS('NWC1'!W:W,'NWC1'!$C:$C,$C36)-SUMIFS(ADJ!Y:Y,ADJ!$E:$E,$C36) -> 358.75 | X36: =SUMIFS('NWC1'!X:X,'NWC1'!$C:$C,$C36)-SUMIFS(ADJ!Z:Z,ADJ!$E:$E,$C36) -> 410 | Y36: =SUMIFS('NWC1'!Y:Y,'NWC1'!$C:$C,$C36)-SUMIFS(ADJ!AA:AA,ADJ!$E:$E,$C36) -> 461.25 | Z36: =SUMIFS('NWC1'!Z:Z,'NWC1'!$C:$C,$C36)-SUMIFS(ADJ!AB:AB,ADJ!$E:$E,$C36) -> 0 | AA36: =SUMIFS('NWC1'!AA:AA,'NWC1'!$C:$C,$C36)-SUMIFS(ADJ!AC:AC,ADJ!$E:$E,$C36) -> 0 | AB36: =SUMIFS('NWC1'!AB:AB,'NWC1'!$C:$C,$C36)-SUMIFS(ADJ!AD:AD,ADJ!$E:$E,$C36) -> 0 | AC36: =SUMIFS('NWC1'!AC:AC,'NWC1'!$C:$C,$C36)-SUMIFS(ADJ!AE:AE,ADJ!$E:$E,$C36) -> 0 | AD36: =SUMIFS('NWC1'!AD:AD,'NWC1'!$C:$C,$C36)-SUMIFS(ADJ!AF:AF,ADJ!$E:$E,$C36) -> 102.5 | AE36: =SUMIFS('NWC1'!AE:AE,'NWC1'!$C:$C,$C36)-SUMIFS(ADJ!AG:AG,ADJ!$E:$E,$C36) -> 153.75 | AF36: =SUMIFS('NWC1'!AF:AF,'NWC1'!$C:$C,$C36)-SUMIFS(ADJ!AH:AH,ADJ!$E:$E,$C36) -> 205 | AG36: =SUMIFS('NWC1'!AG:AG,'NWC1'!$C:$C,$C36)-SUMIFS(ADJ!AI:AI,ADJ!$E:$E,$C36) -> 256.25 | AH36: =SUMIFS('NWC1'!AH:AH,'NWC1'!$C:$C,$C36)-SUMIFS(ADJ!AJ:AJ,ADJ!$E:$E,$C36) -> 307.5 | AI36: =SUMIFS('NWC1'!AI:AI,'NWC1'!$C:$C,$C36)-SUMIFS(ADJ!AK:AK,ADJ!$E:$E,$C36) -> 358.75 | AK36: =P36 -> 0 | AL36: =AB36 -> 0 | AM36: =AI36 -> 358.75 | AO36: =IFERROR(AVERAGE(AG36:AI36),0) -> 307.5 | AP36: =IFERROR(AVERAGE(AD36:AI36),0) -> 230.625 | AQ36: =IFERROR(AVERAGE(AA36:AI36),0) -> 153.75 | AR36: =IFERROR(AVERAGE(X36:AI36),0) -> 187.91667
C37: Pension Payable | E37: =SUMIFS('NWC1'!E:E,'NWC1'!$C:$C,$C37)-SUMIFS(ADJ!G:G,ADJ!$E:$E,$C37) -> 103.44607 | F37: =SUMIFS('NWC1'!F:F,'NWC1'!$C:$C,$C37)-SUMIFS(ADJ!H:H,ADJ!$E:$E,$C37) -> 103.44607 | G37: =SUMIFS('NWC1'!G:G,'NWC1'!$C:$C,$C37)-SUMIFS(ADJ!I:I,ADJ!$E:$E,$C37) -> 103.44607 | H37: =SUMIFS('NWC1'!H:H,'NWC1'!$C:$C,$C37)-SUMIFS(ADJ!J:J,ADJ!$E:$E,$C37) -> 103.44607 | I37: =SUMIFS('NWC1'!I:I,'NWC1'!$C:$C,$C37)-SUMIFS(ADJ!K:K,ADJ!$E:$E,$C37) -> 0 | J37: =SUMIFS('NWC1'!J:J,'NWC1'!$C:$C,$C37)-SUMIFS(ADJ!L:L,ADJ!$E:$E,$C37) -> 0 | K37: =SUMIFS('NWC1'!K:K,'NWC1'!$C:$C,$C37)-SUMIFS(ADJ!M:M,ADJ!$E:$E,$C37) -> 0 | L37: =SUMIFS('NWC1'!L:L,'NWC1'!$C:$C,$C37)-SUMIFS(ADJ!N:N,ADJ!$E:$E,$C37) -> 0 | M37: =SUMIFS('NWC1'!M:M,'NWC1'!$C:$C,$C37)-SUMIFS(ADJ!O:O,ADJ!$E:$E,$C37) -> 0 | N37: =SUMIFS('NWC1'!N:N,'NWC1'!$C:$C,$C37)-SUMIFS(ADJ!P:P,ADJ!$E:$E,$C37) -> 0 | O37: =SUMIFS('NWC1'!O:O,'NWC1'!$C:$C,$C37)-SUMIFS(ADJ!Q:Q,ADJ!$E:$E,$C37) -> 0 | P37: =SUMIFS('NWC1'!P:P,'NWC1'!$C:$C,$C37)-SUMIFS(ADJ!R:R,ADJ!$E:$E,$C37) -> 91.93914 | Q37: =SUMIFS('NWC1'!Q:Q,'NWC1'!$C:$C,$C37)-SUMIFS(ADJ!S:S,ADJ!$E:$E,$C37) -> 91.93914 | R37: =SUMIFS('NWC1'!R:R,'NWC1'!$C:$C,$C37)-SUMIFS(ADJ!T:T,ADJ!$E:$E,$C37) -> 91.93914 | S37: =SUMIFS('NWC1'!S:S,'NWC1'!$C:$C,$C37)-SUMIFS(ADJ!U:U,ADJ!$E:$E,$C37) -> 91.93914 | T37: =SUMIFS('NWC1'!T:T,'NWC1'!$C:$C,$C37)-SUMIFS(ADJ!V:V,ADJ!$E:$E,$C37) -> 91.93914 | U37: =SUMIFS('NWC1'!U:U,'NWC1'!$C:$C,$C37)-SUMIFS(ADJ!W:W,ADJ!$E:$E,$C37) -> 0 | V37: =SUMIFS('NWC1'!V:V,'NWC1'!$C:$C,$C37)-SUMIFS(ADJ!X:X,ADJ!$E:$E,$C37) -> 0 | W37: =SUMIFS('NWC1'!W:W,'NWC1'!$C:$C,$C37)-SUMIFS(ADJ!Y:Y,ADJ!$E:$E,$C37) -> 0 | X37: =SUMIFS('NWC1'!X:X,'NWC1'!$C:$C,$C37)-SUMIFS(ADJ!Z:Z,ADJ!$E:$E,$C37) -> 0 | Y37: =SUMIFS('NWC1'!Y:Y,'NWC1'!$C:$C,$C37)-SUMIFS(ADJ!AA:AA,ADJ!$E:$E,$C37) -> 0 | Z37: =SUMIFS('NWC1'!Z:Z,'NWC1'!$C:$C,$C37)-SUMIFS(ADJ!AB:AB,ADJ!$E:$E,$C37) -> 0 | AA37: =SUMIFS('NWC1'!AA:AA,'NWC1'!$C:$C,$C37)-SUMIFS(ADJ!AC:AC,ADJ!$E:$E,$C37) -> 0 | AB37: =SUMIFS('NWC1'!AB:AB,'NWC1'!$C:$C,$C37)-SUMIFS(ADJ!AD:AD,ADJ!$E:$E,$C37) -> 87.32589 | AC37: =SUMIFS('NWC1'!AC:AC,'NWC1'!$C:$C,$C37)-SUMIFS(ADJ!AE:AE,ADJ!$E:$E,$C37) -> 87.32589 | AD37: =SUMIFS('NWC1'!AD:AD,'NWC1'!$C:$C,$C37)-SUMIFS(ADJ!AF:AF,ADJ!$E:$E,$C37) -> 87.32589 | AE37: =SUMIFS('NWC1'!AE:AE,'NWC1'!$C:$C,$C37)-SUMIFS(ADJ!AG:AG,ADJ!$E:$E,$C37) -> 87.32589 | AF37: =SUMIFS('NWC1'!AF:AF,'NWC1'!$C:$C,$C37)-SUMIFS(ADJ!AH:AH,ADJ!$E:$E,$C37) -> 0 | AG37: =SUMIFS('NWC1'!AG:AG,'NWC1'!$C:$C,$C37)-SUMIFS(ADJ!AI:AI,ADJ!$E:$E,$C37) -> 0 | AH37: =SUMIFS('NWC1'!AH:AH,'NWC1'!$C:$C,$C37)-SUMIFS(ADJ!AJ:AJ,ADJ!$E:$E,$C37) -> 0 | AI37: =SUMIFS('NWC1'!AI:AI,'NWC1'!$C:$C,$C37)-SUMIFS(ADJ!AK:AK,ADJ!$E:$E,$C37) -> 0 | AK37: =P37 -> 91.93914 | AL37: =AB37 -> 87.32589 | AM37: =AI37 -> 0 | AO37: =IFERROR(AVERAGE(AG37:AI37),0) -> 0 | AP37: =IFERROR(AVERAGE(AD37:AI37),0) -> 29.10863 | AQ37: =IFERROR(AVERAGE(AA37:AI37),0) -> 38.811507 | AR37: =IFERROR(AVERAGE(X37:AI37),0) -> 29.10863
C38: 401k contributions due | E38: =SUMIFS('NWC1'!E:E,'NWC1'!$C:$C,$C38)-SUMIFS(ADJ!G:G,ADJ!$E:$E,$C38) -> 8.05888 | F38: =SUMIFS('NWC1'!F:F,'NWC1'!$C:$C,$C38)-SUMIFS(ADJ!H:H,ADJ!$E:$E,$C38) -> 8.84102 | G38: =SUMIFS('NWC1'!G:G,'NWC1'!$C:$C,$C38)-SUMIFS(ADJ!I:I,ADJ!$E:$E,$C38) -> 8.84102 | H38: =SUMIFS('NWC1'!H:H,'NWC1'!$C:$C,$C38)-SUMIFS(ADJ!J:J,ADJ!$E:$E,$C38) -> 8.88102 | I38: =SUMIFS('NWC1'!I:I,'NWC1'!$C:$C,$C38)-SUMIFS(ADJ!K:K,ADJ!$E:$E,$C38) -> 8.75602 | J38: =SUMIFS('NWC1'!J:J,'NWC1'!$C:$C,$C38)-SUMIFS(ADJ!L:L,ADJ!$E:$E,$C38) -> 8.75602 | K38: =SUMIFS('NWC1'!K:K,'NWC1'!$C:$C,$C38)-SUMIFS(ADJ!M:M,ADJ!$E:$E,$C38) -> 8.28408 | L38: =SUMIFS('NWC1'!L:L,'NWC1'!$C:$C,$C38)-SUMIFS(ADJ!N:N,ADJ!$E:$E,$C38) -> 8.28408 | M38: =SUMIFS('NWC1'!M:M,'NWC1'!$C:$C,$C38)-SUMIFS(ADJ!O:O,ADJ!$E:$E,$C38) -> 6.29658 | N38: =SUMIFS('NWC1'!N:N,'NWC1'!$C:$C,$C38)-SUMIFS(ADJ!P:P,ADJ!$E:$E,$C38) -> 9.04258 | O38: =SUMIFS('NWC1'!O:O,'NWC1'!$C:$C,$C38)-SUMIFS(ADJ!Q:Q,ADJ!$E:$E,$C38) -> 9.04258 | P38: =SUMIFS('NWC1'!P:P,'NWC1'!$C:$C,$C38)-SUMIFS(ADJ!R:R,ADJ!$E:$E,$C38) -> 34.04452 | Q38: =SUMIFS('NWC1'!Q:Q,'NWC1'!$C:$C,$C38)-SUMIFS(ADJ!S:S,ADJ!$E:$E,$C38) -> 9.04258 | R38: =SUMIFS('NWC1'!R:R,'NWC1'!$C:$C,$C38)-SUMIFS(ADJ!T:T,ADJ!$E:$E,$C38) -> 9.26258 | S38: =SUMIFS('NWC1'!S:S,'NWC1'!$C:$C,$C38)-SUMIFS(ADJ!U:U,ADJ!$E:$E,$C38) -> 9.26258 | T38: =SUMIFS('NWC1'!T:T,'NWC1'!$C:$C,$C38)-SUMIFS(ADJ!V:V,ADJ!$E:$E,$C38) -> 9.27011 | U38: =SUMIFS('NWC1'!U:U,'NWC1'!$C:$C,$C38)-SUMIFS(ADJ!W:W,ADJ!$E:$E,$C38) -> 9.27011 | V38: =SUMIFS('NWC1'!V:V,'NWC1'!$C:$C,$C38)-SUMIFS(ADJ!X:X,ADJ!$E:$E,$C38) -> 9.26258 | W38: =SUMIFS('NWC1'!W:W,'NWC1'!$C:$C,$C38)-SUMIFS(ADJ!Y:Y,ADJ!$E:$E,$C38) -> 9.27011 | X38: =SUMIFS('NWC1'!X:X,'NWC1'!$C:$C,$C38)-SUMIFS(ADJ!Z:Z,ADJ!$E:$E,$C38) -> 9.27011 | Y38: =SUMIFS('NWC1'!Y:Y,'NWC1'!$C:$C,$C38)-SUMIFS(ADJ!AA:AA,ADJ!$E:$E,$C38) -> 9.27011 | Z38: =SUMIFS('NWC1'!Z:Z,'NWC1'!$C:$C,$C38)-SUMIFS(ADJ!AB:AB,ADJ!$E:$E,$C38) -> 9.39784 | AA38: =SUMIFS('NWC1'!AA:AA,'NWC1'!$C:$C,$C38)-SUMIFS(ADJ!AC:AC,ADJ!$E:$E,$C38) -> 7.64716 | AB38: =SUMIFS('NWC1'!AB:AB,'NWC1'!$C:$C,$C38)-SUMIFS(ADJ!AD:AD,ADJ!$E:$E,$C38) -> 7.98016 | AC38: =SUMIFS('NWC1'!AC:AC,'NWC1'!$C:$C,$C38)-SUMIFS(ADJ!AE:AE,ADJ!$E:$E,$C38) -> 8.00942 | AD38: =SUMIFS('NWC1'!AD:AD,'NWC1'!$C:$C,$C38)-SUMIFS(ADJ!AF:AF,ADJ!$E:$E,$C38) -> 8.00942 | AE38: =SUMIFS('NWC1'!AE:AE,'NWC1'!$C:$C,$C38)-SUMIFS(ADJ!AG:AG,ADJ!$E:$E,$C38) -> 17.01345 | AF38: =SUMIFS('NWC1'!AF:AF,'NWC1'!$C:$C,$C38)-SUMIFS(ADJ!AH:AH,ADJ!$E:$E,$C38) -> 8.50942 | AG38: =SUMIFS('NWC1'!AG:AG,'NWC1'!$C:$C,$C38)-SUMIFS(ADJ!AI:AI,ADJ!$E:$E,$C38) -> 8.38672 | AH38: =SUMIFS('NWC1'!AH:AH,'NWC1'!$C:$C,$C38)-SUMIFS(ADJ!AJ:AJ,ADJ!$E:$E,$C38) -> 8.38672 | AI38: =SUMIFS('NWC1'!AI:AI,'NWC1'!$C:$C,$C38)-SUMIFS(ADJ!AK:AK,ADJ!$E:$E,$C38) -> 0 | AK38: =P38 -> 34.04452 | AL38: =AB38 -> 7.98016 | AM38: =AI38 -> 0 | AO38: =IFERROR(AVERAGE(AG38:AI38),0) -> 5.5911467 | AP38: =IFERROR(AVERAGE(AD38:AI38),0) -> 8.3842883 | AQ38: =IFERROR(AVERAGE(AA38:AI38),0) -> 8.21583 | AR38: =IFERROR(AVERAGE(X38:AI38),0) -> 8.4900442
C39: Payroll liabilities | E39: =SUM(E36:E38) -> 160.00495 | F39: =SUM(F36:F38) -> 209.28709 | G39: =SUM(G36:G38) -> 257.78709 | H39: =SUM(H36:H38) -> 306.32709 | I39: =SUM(I36:I38) -> 251.25602 | J39: =SUM(J36:J38) -> 299.75602 | K39: =SUM(K36:K38) -> 347.78408 | L39: =SUM(L36:L38) -> 396.28408 | ... AI39: =SUM(AI36:AI38) -> 358.75 | AK39: =SUM(AK36:AK38) -> 125.98366 | AL39: =SUM(AL36:AL38) -> 95.30605 | AM39: =SUM(AM36:AM38) -> 358.75 | AO39: =SUM(AO36:AO38) -> 313.09115 | AP39: =SUM(AP36:AP38) -> 268.11792 | AQ39: =SUM(AQ36:AQ38) -> 200.77734 | AR39: =SUM(AR36:AR38) -> 225.51534
C41: Zeldis American Express | E41: =SUMIFS('NWC1'!E:E,'NWC1'!$C:$C,$C41)-SUMIFS(ADJ!G:G,ADJ!$E:$E,$C41) -> 4.99889 | F41: =SUMIFS('NWC1'!F:F,'NWC1'!$C:$C,$C41)-SUMIFS(ADJ!H:H,ADJ!$E:$E,$C41) -> 11.54903 | G41: =SUMIFS('NWC1'!G:G,'NWC1'!$C:$C,$C41)-SUMIFS(ADJ!I:I,ADJ!$E:$E,$C41) -> 0.10635 | H41: =SUMIFS('NWC1'!H:H,'NWC1'!$C:$C,$C41)-SUMIFS(ADJ!J:J,ADJ!$E:$E,$C41) -> 5.72126 | I41: =SUMIFS('NWC1'!I:I,'NWC1'!$C:$C,$C41)-SUMIFS(ADJ!K:K,ADJ!$E:$E,$C41) -> 1.63473 | J41: =SUMIFS('NWC1'!J:J,'NWC1'!$C:$C,$C41)-SUMIFS(ADJ!L:L,ADJ!$E:$E,$C41) -> 1.62597 | K41: =SUMIFS('NWC1'!K:K,'NWC1'!$C:$C,$C41)-SUMIFS(ADJ!M:M,ADJ!$E:$E,$C41) -> 2.94612 | L41: =SUMIFS('NWC1'!L:L,'NWC1'!$C:$C,$C41)-SUMIFS(ADJ!N:N,ADJ!$E:$E,$C41) -> 1.34899 | M41: =SUMIFS('NWC1'!M:M,'NWC1'!$C:$C,$C41)-SUMIFS(ADJ!O:O,ADJ!$E:$E,$C41) -> 0.2138 | N41: =SUMIFS('NWC1'!N:N,'NWC1'!$C:$C,$C41)-SUMIFS(ADJ!P:P,ADJ!$E:$E,$C41) -> 0.66918 | O41: =SUMIFS('NWC1'!O:O,'NWC1'!$C:$C,$C41)-SUMIFS(ADJ!Q:Q,ADJ!$E:$E,$C41) -> 5.42513 | P41: =SUMIFS('NWC1'!P:P,'NWC1'!$C:$C,$C41)-SUMIFS(ADJ!R:R,ADJ!$E:$E,$C41) -> 5.60014 | Q41: =SUMIFS('NWC1'!Q:Q,'NWC1'!$C:$C,$C41)-SUMIFS(ADJ!S:S,ADJ!$E:$E,$C41) -> 4.88868 | R41: =SUMIFS('NWC1'!R:R,'NWC1'!$C:$C,$C41)-SUMIFS(ADJ!T:T,ADJ!$E:$E,$C41) -> 1.1119 | S41: =SUMIFS('NWC1'!S:S,'NWC1'!$C:$C,$C41)-SUMIFS(ADJ!U:U,ADJ!$E:$E,$C41) -> 5.43933 | T41: =SUMIFS('NWC1'!T:T,'NWC1'!$C:$C,$C41)-SUMIFS(ADJ!V:V,ADJ!$E:$E,$C41) -> 3.84379 | U41: =SUMIFS('NWC1'!U:U,'NWC1'!$C:$C,$C41)-SUMIFS(ADJ!W:W,ADJ!$E:$E,$C41) -> 0.43464 | V41: =SUMIFS('NWC1'!V:V,'NWC1'!$C:$C,$C41)-SUMIFS(ADJ!X:X,ADJ!$E:$E,$C41) -> 5.49789 | W41: =SUMIFS('NWC1'!W:W,'NWC1'!$C:$C,$C41)-SUMIFS(ADJ!Y:Y,ADJ!$E:$E,$C41) -> 4.19833 | X41: =SUMIFS('NWC1'!X:X,'NWC1'!$C:$C,$C41)-SUMIFS(ADJ!Z:Z,ADJ!$E:$E,$C41) -> 4.02806 | Y41: =SUMIFS('NWC1'!Y:Y,'NWC1'!$C:$C,$C41)-SUMIFS(ADJ!AA:AA,ADJ!$E:$E,$C41) -> 0 | Z41: =SUMIFS('NWC1'!Z:Z,'NWC1'!$C:$C,$C41)-SUMIFS(ADJ!AB:AB,ADJ!$E:$E,$C41) -> 3.46022 | AA41: =SUMIFS('NWC1'!AA:AA,'NWC1'!$C:$C,$C41)-SUMIFS(ADJ!AC:AC,ADJ!$E:$E,$C41) -> 4.39943 | AB41: =SUMIFS('NWC1'!AB:AB,'NWC1'!$C:$C,$C41)-SUMIFS(ADJ!AD:AD,ADJ!$E:$E,$C41) -> 3.90425 | AC41: =SUMIFS('NWC1'!AC:AC,'NWC1'!$C:$C,$C41)-SUMIFS(ADJ!AE:AE,ADJ!$E:$E,$C41) -> 3.98306 | AD41: =SUMIFS('NWC1'!AD:AD,'NWC1'!$C:$C,$C41)-SUMIFS(ADJ!AF:AF,ADJ!$E:$E,$C41) -> 2.30298 | AE41: =SUMIFS('NWC1'!AE:AE,'NWC1'!$C:$C,$C41)-SUMIFS(ADJ!AG:AG,ADJ!$E:$E,$C41) -> 3.40988 | AF41: =SUMIFS('NWC1'!AF:AF,'NWC1'!$C:$C,$C41)-SUMIFS(ADJ!AH:AH,ADJ!$E:$E,$C41) -> 5.76356 | AG41: =SUMIFS('NWC1'!AG:AG,'NWC1'!$C:$C,$C41)-SUMIFS(ADJ!AI:AI,ADJ!$E:$E,$C41) -> 3.06282 | AH41: =SUMIFS('NWC1'!AH:AH,'NWC1'!$C:$C,$C41)-SUMIFS(ADJ!AJ:AJ,ADJ!$E:$E,$C41) -> 3.19919 | AI41: =SUMIFS('NWC1'!AI:AI,'NWC1'!$C:$C,$C41)-SUMIFS(ADJ!AK:AK,ADJ!$E:$E,$C41) -> 4.85422 | AK41: =P41 -> 5.60014 | AL41: =AB41 -> 3.90425 | AM41: =AI41 -> 4.85422 | AO41: =IFERROR(AVERAGE(AG41:AI41),0) -> 3.70541 | AP41: =IFERROR(AVERAGE(AD41:AI41),0) -> 3.7654417 | AQ41: =IFERROR(AVERAGE(AA41:AI41),0) -> 3.8754878 | AR41: =IFERROR(AVERAGE(X41:AI41),0) -> 3.5306392
C42: Credit cards payable | E42: =SUM(E41:E41) -> 4.99889 | F42: =SUM(F41:F41) -> 11.54903 | G42: =SUM(G41:G41) -> 0.10635 | H42: =SUM(H41:H41) -> 5.72126 | I42: =SUM(I41:I41) -> 1.63473 | J42: =SUM(J41:J41) -> 1.62597 | K42: =SUM(K41:K41) -> 2.94612 | L42: =SUM(L41:L41) -> 1.34899 | ... AI42: =SUM(AI41:AI41) -> 4.85422 | AK42: =SUM(AK41:AK41) -> 5.60014 | AL42: =SUM(AL41:AL41) -> 3.90425 | AM42: =SUM(AM41:AM41) -> 4.85422 | AO42: =SUM(AO41:AO41) -> 3.70541 | AP42: =SUM(AP41:AP41) -> 3.7654417 | AQ42: =SUM(AQ41:AQ41) -> 3.8754878 | AR42: =SUM(AR41:AR41) -> 3.5306392
C43: Total current liabilities | E43: =E25+E31+E34+E42+E39 -> 1449.096 | F43: =F25+F31+F34+F42+F39 -> 1527.233 | G43: =G25+G31+G34+G42+G39 -> 1615.998 | H43: =H25+H31+H34+H42+H39 -> 1559.4235 | I43: =I25+I31+I34+I42+I39 -> 1550.2368 | J43: =J25+J31+J34+J42+J39 -> 1604.0057 | K43: =K25+K31+K34+K42+K39 -> 1719.6744 | L43: =L25+L31+L34+L42+L39 -> 1691.659 | ... AI43: =AI25+AI31+AI34+AI42+AI39 -> 1285.7402 | AK43: =AK25+AK31+AK34+AK42+AK39 -> 1245.3872 | AL43: =AL25+AL31+AL34+AL42+AL39 -> 1174.2542 | AM43: =AM25+AM31+AM34+AM42+AM39 -> 1285.7402 | AO43: =AO25+AO31+AO34+AO42+AO39 -> 1289.1953 | AP43: =AP25+AP31+AP34+AP42+AP39 -> 1299.7499 | AQ43: =AQ25+AQ31+AQ34+AQ42+AQ39 -> 1249.9551 | AR43: =AR25+AR31+AR34+AR42+AR39 -> 1293.13
C44: Net working capital, adjusted | E44: =E22-E43 -> -1150.6342 | F44: =F22-F43 -> -1178.9677 | G44: =G22-G43 -> -849.39523 | H44: =H22-H43 -> -1030.0432 | I44: =I22-I43 -> -1090.4855 | J44: =J22-J43 -> -965.6264 | K44: =K22-K43 -> -967.74691 | L44: =L22-L43 -> -319.88095 | ... AI44: =AI22-AI43 -> -510.68569 | AK44: =AK22-AK43 -> -613.15866 | AL44: =AL22-AL43 -> -572.06273 | AM44: =AM22-AM43 -> -510.68569 | AO44: =AO22-AO43 -> -546.07045 | AP44: =AP22-AP43 -> -568.64279 | AQ44: =AQ22-AQ43 -> -551.88982 | AR44: =AR22-AR43 -> -572.74682
C45: Adjusted NWC as % of TTM Net Revenue | E45: =IFERROR(E44/E56%,0) -> -595.79148 | F45: =IFERROR(F44/F56%,0) -> -189.37096 | G45: =IFERROR(G44/G56%,0) -> -62.714436 | H45: =IFERROR(H44/H56%,0) -> -57.713892 | I45: =IFERROR(I44/I56%,0) -> -45.282756 | J45: =IFERROR(J44/J56%,0) -> -33.424238 | K45: =IFERROR(K44/K56%,0) -> -27.051165 | L45: =IFERROR(L44/L56%,0) -> -6.6024699 | ... AI45: =IFERROR(AI44/AI56%,0) -> -6.9543358 | AK45: =P45 -> -8.0178483 | AL45: =AB45 -> -8.4390578 | AM45: =AI45 -> -6.9543358 | AO45: =IFERROR(AVERAGE(AG45:AI45),0) -> -7.6580013 | AP45: =IFERROR(AVERAGE(AD45:AI45),0) -> -8.0970831 | AQ45: =IFERROR(AVERAGE(AA45:AI45),0) -> -7.9341693 | AR45: =IFERROR(AVERAGE(X45:AI45),0) -> -8.2724778
C47: DSO, adjusted | E47: =IFERROR((E10/E57)*E$55,0) -> 47.848416 | F47: =IFERROR((F10/F57)*F$55,0) -> 25.113268 | G47: =IFERROR((G10/G57)*G$55,0) -> 31.410889 | H47: =IFERROR((H10/H57)*H$55,0) -> 38.102652 | I47: =IFERROR((I10/I57)*I$55,0) -> 22.84008 | J47: =IFERROR((J10/J57)*J$55,0) -> 39.80334 | K47: =IFERROR((K10/K57)*K$55,0) -> 33.841551 | L47: =IFERROR((L10/L57)*L$55,0) -> 32.462349 | ... AI47: =IFERROR((AI10/AI57)*AI$55,0) -> 56.461083 | AK47: =IFERROR((AK10/AK57)*AK$55,0) -> 30.397139 | AL47: =IFERROR((AL10/AL57)*AL$55,0) -> 32.193762 | AM47: =IFERROR((AM10/AM57)*AM$55,0) -> 38.310312 | AO47: =IFERROR(AVERAGE(AG47:AI47),0) -> 51.966469 | AP47: =IFERROR(AVERAGE(AD47:AI47),0) -> 45.333312 | AQ47: =IFERROR(AVERAGE(AA47:AI47),0) -> 43.295743 | AR47: =IFERROR(AVERAGE(X47:AI47),0) -> 39.597423
C48: DIO, adjusted | E48: =IFERROR(AVERAGE(E18:E18)/E59*E55,0) -> 0.056644213 | F48: =IFERROR(AVERAGE(E18:F18)/F59*F55,0) -> 0.048389344 | G48: =IFERROR(AVERAGE(F18:G18)/G59*G55,0) -> 0.039284019 | H48: =IFERROR(AVERAGE(G18:H18)/H59*H55,0) -> 0.064679173 | I48: =IFERROR(AVERAGE(H18:I18)/I59*I55,0) -> 0.053431911 | J48: =IFERROR(AVERAGE(I18:J18)/J59*J55,0) -> 0.05037058 | K48: =IFERROR(AVERAGE(J18:K18)/K59*K55,0) -> 0.038466951 | L48: =IFERROR(AVERAGE(K18:L18)/L59*L55,0) -> 0.032421125 | M48: =IFERROR(AVERAGE(L18:M18)/M59*M55,0) -> 0.056053217 | ... AI48: =IFERROR(AVERAGE(AH18:AI18)/AI59*AI55,0) -> 0.5584504 | AK48: =IFERROR(AVERAGE(AK18:AK18)/AK59*AK55,0) -> 0.041783619 | AL48: =IFERROR(AVERAGE(AK18:AL18)/AL59*AL55,0) -> 0.30580829 | AM48: =IFERROR(AVERAGE(AL18:AM18)/AM59*AM55,0) -> 0.53766621 | AO48: =IFERROR(AVERAGE(AG48:AI48),0) -> 0.54954568 | AP48: =IFERROR(AVERAGE(AD48:AI48),0) -> 0.58934799 | AQ48: =IFERROR(AVERAGE(AA48:AI48),0) -> 0.56630801 | AR48: =IFERROR(AVERAGE(X48:AI48),0) -> 0.51534623
C49: DPO, adjusted | E49: =IFERROR((E25/E59)*E$55,0) -> 15.731247 | F49: =IFERROR((F25/F59)*F$55,0) -> 16.349467 | G49: =IFERROR((G25/G59)*G$55,0) -> 18.751137 | H49: =IFERROR((H25/H59)*H$55,0) -> 10.793711 | I49: =IFERROR((I25/I59)*I$55,0) -> 14.671003 | J49: =IFERROR((J25/J59)*J$55,0) -> 14.458426 | K49: =IFERROR((K25/K59)*K$55,0) -> 18.625684 | L49: =IFERROR((L25/L59)*L$55,0) -> 11.764053 | ... AI49: =IFERROR((AI25/AI59)*AI$55,0) -> 12.460613 | AK49: =IFERROR((AK25/AK59)*AK$55,0) -> 0 | AL49: =IFERROR((AL25/AL59)*AL$55,0) -> 8.7413086 | AM49: =IFERROR((AM25/AM59)*AM$55,0) -> 11.996859 | AO49: =IFERROR(AVERAGE(AG49:AI49),0) -> 15.270617 | AP49: =IFERROR(AVERAGE(AD49:AI49),0) -> 17.148904 | AQ49: =IFERROR(AVERAGE(AA49:AI49),0) -> 15.554841 | AR49: =IFERROR(AVERAGE(X49:AI49),0) -> 16.675024
C52: Check to Recast NWC1 | E52: =+'NWC1'!E73-E44 -> 0 | F52: =+'NWC1'!F73-F44 -> 0 | G52: =+'NWC1'!G73-G44 -> 0 | H52: =+'NWC1'!H73-H44 -> 0 | I52: =+'NWC1'!I73-I44 -> 0 | J52: =+'NWC1'!J73-J44 -> 0 | K52: =+'NWC1'!K73-K44 -> 0 | L52: =+'NWC1'!L73-L44 -> 0 | ... AI52: =+'NWC1'!AI73-AI44 -> 0 | AK52: =+'NWC1'!AK73-AK44 -> 0 | AL52: =+'NWC1'!AL73-AL44 -> 0 | AM52: =+'NWC1'!AM73-AM44 -> 0 | AO52: =+'NWC1'!AO73-AO44 -> 0 | AP52: =+'NWC1'!AP73-AP44 -> 0 | AQ52: =+'NWC1'!AQ73-AQ44 -> 0 | AR52: =+'NWC1'!AR73-AR44 -> 0
C55: Days | E55: 31 | F55: =F8-E8 -> 31 | G55: =G8-F8 -> 30 | H55: =H8-G8 -> 31 | I55: =I8-H8 -> 31 | J55: =J8-I8 -> 30 | K55: =K8-J8 -> 31 | L55: =L8-K8 -> 30 | M55: =M8-L8 -> 31 | ... AI55: =AI8-AH8 -> 31 | AK55: 365 | AL55: =AL8-P8 -> 365 | AM55: =AM8-W8 -> 365
C56: TTM Net Revenue | E56: =SUM(E57:E57) -> 193.127 | F56: =SUM(E57:F57) -> 622.5705 | G56: =SUM(E57:G57) -> 1354.3855 | H56: =SUM(E57:H57) -> 1784.7405 | I56: =SUM(E57:I57) -> 2408.1695 | J56: =SUM(E57:J57) -> 2889.0005 | K56: =SUM(E57:K57) -> 3577.4685 | L56: =SUM(E57:L57) -> 4844.868 | M56: =SUM(E57:M57) -> 6121.044 | N56: =SUM(E57:N57) -> 6359.7455 | O56: =SUM(E57:O57) -> 6910.6386 | P56: =SUM(E57:P57) -> 7647.4216 | Q56: =SUM(F57:Q57) -> 7876.3386 | R56: =SUM(G57:R57) -> 7972.5451 | S56: =SUM(H57:S57) -> 7612.0781 | T56: =SUM(I57:T57) -> 7563.3571 | U56: =SUM(J57:U57) -> 7477.1071 | V56: =SUM(K57:V57) -> 7353.1801 | W56: =SUM(L57:W57) -> 7030.3261 | ... AI56: =SUM(X57:AI57) -> 7343.4143 | AK56: =P56 -> 7647.4216 | AL56: =AB56 -> 6778.7512 | AM56: =AI56 -> 7343.4143
C57: Net revenue (per RPL1) | E57: =+'RPL1'!E10 -> 193.127 | F57: =+'RPL1'!F10 -> 429.4435 | G57: =+'RPL1'!G10 -> 731.815 | H57: =+'RPL1'!H10 -> 430.355 | I57: =+'RPL1'!I10 -> 623.429 | J57: =+'RPL1'!J10 -> 480.831 | K57: =+'RPL1'!K10 -> 688.468 | L57: =+'RPL1'!L10 -> 1267.3995 | ... AI57: =+'RPL1'!AI10 -> 423.188 | AK57: =+'RPL1'!AK10 -> 7647.4216 | AL57: =+'RPL1'!AL10 -> 6778.7512 | AM57: =+'RPL1'!AM10 -> 7343.4143
C58: Opex (Per RPL1) | E58: ='RPL1'!E23 -> 501.62028 | F58: ='RPL1'!F23 -> 536.03161 | G58: ='RPL1'!G23 -> 567.48325 | H58: ='RPL1'!H23 -> 466.99545 | I58: ='RPL1'!I23 -> 514.57303 | J58: ='RPL1'!J23 -> 518.7814 | K58: ='RPL1'!K23 -> 580.92054 | L58: ='RPL1'!L23 -> 592.93061 | ... AI58: ='RPL1'!AI23 -> 525.39962 | AK58: ='RPL1'!AK23 -> 6505.5479 | AL58: ='RPL1'!AL23 -> 5546.7039 | AM58: ='RPL1'!AM23 -> 5646.9072
C59: Opex less payroll (Per RPL1) | E59: ='RPL1'!E23-'RPL1'!E17 -> 202.92982 | F59: ='RPL1'!F23-'RPL1'!F17 -> 237.54817 | G59: ='RPL1'!G23-'RPL1'!G17 -> 283.16858 | H59: ='RPL1'!H23-'RPL1'!H17 -> 190.30639 | I59: ='RPL1'!I23-'RPL1'!I17 -> 245.6008 | J59: ='RPL1'!J23-'RPL1'!J17 -> 252.12336 | K59: ='RPL1'!K23-'RPL1'!K17 -> 312.61953 | L59: ='RPL1'!L23-'RPL1'!L17 -> 326.19473 | ... AI59: ='RPL1'!AI23-'RPL1'!AI17 -> 238.22549 | AK59: ='RPL1'!AK23-'RPL1'!AK17 -> 3079.4317 | AL59: ='RPL1'!AL23-'RPL1'!AL17 -> 2771.466 | AM59: ='RPL1'!AM23-'RPL1'!AM17 -> 2913.3406
X61: =X8 -> 45626 | Y61: =Y8 -> 45657 | Z61: =Z8 -> 45688 | AA61: =AA8 -> 45716 | AB61: =AB8 -> 45747 | AC61: =AC8 -> 45777 | AD61: =AD8 -> 45808 | AE61: =AE8 -> 45838 | ... AI61: =AI8 -> 45961
W62: Accounts receivable, net | X62: =X10 -> 917.839 | Y62: =Y10 -> 1105.536 | Z62: =Z10 -> 329.661 | AA62: =AA10 -> 727.5975 | AB62: =AB10 -> 597.9 | AC62: =AC10 -> 557.573 | AD62: =AD10 -> 512 | AE62: =AE10 -> 996.3901 | ... AI62: =AI10 -> 770.763
W63: Other receivables | X63: =X18 -> 2.99152 | Y63: =Y18 -> 2.99152 | Z63: =Z18 -> 2.99152 | AA63: =AA18 -> 4.29152 | AB63: =AB18 -> 4.29152 | AC63: =AC18 -> 4.29152 | AD63: =AD18 -> 4.29152 | AE63: =AE18 -> 4.29152 | ... AI63: =AI18 -> 4.29152
W64: Prepaid expenses | X64: =X21 -> 0 | Y64: =Y21 -> 0 | Z64: =Z21 -> 0 | AA64: =AA21 -> 0 | AB64: =AB21 -> 0 | AC64: =AC21 -> 0 | AD64: =AD21 -> 0 | AE64: =AE21 -> 0 | ... AI64: =AI21 -> 0
W65: Accounts payable | X65: =-X25 -> -169.122 | Y65: =-Y25 -> -118.87129 | Z65: =-Z25 -> -222.6332 | AA65: =-AA25 -> -96.1504 | AB65: =-AB25 -> -66.37326 | AC65: =-AC25 -> -111.65542 | AD65: =-AD25 -> -144.52427 | AE65: =-AE25 -> -237.55036 | ... AI65: =-AI25 -> -95.75599
W66: Other payables | X66: =-X31 -> -16.87438 | Y66: =-Y31 -> -16.87438 | Z66: =-Z31 -> -16.87438 | AA66: =-AA31 -> -15.655 | AB66: =-AB31 -> -83.50069 | AC66: =-AC31 -> -83.50069 | AD66: =-AD31 -> -83.50069 | AE66: =-AE31 -> -83.50069 | ... AI66: =-AI31 -> -16.235
W67: Unearned revenue | X67: =-X34 -> -933.346 | Y67: =-Y34 -> -933.346 | Z67: =-Z34 -> -933.346 | AA67: =-AA34 -> -933.346 | AB67: =-AB34 -> -925.17 | AC67: =-AC34 -> -925.17 | AD67: =-AD34 -> -925.17 | AE67: =-AE34 -> -851.17 | ... AI67: =-AI34 -> -810.145
W68: Payroll liabilities | X68: =-X39 -> -419.27011 | Y68: =-Y39 -> -470.52011 | Z68: =-Z39 -> -9.39784 | AA68: =-AA39 -> -7.64716 | AB68: =-AB39 -> -95.30605 | AC68: =-AC39 -> -95.33531 | AD68: =-AD39 -> -197.83531 | AE68: =-AE39 -> -258.08934 | ... AI68: =-AI39 -> -358.75
W69: Credit cards payable | X69: =-X42 -> -4.02806 | Y69: =-Y42 -> 0 | Z69: =-Z42 -> -3.46022 | AA69: =-AA42 -> -4.39943 | AB69: =-AB42 -> -3.90425 | AC69: =-AC42 -> -3.98306 | AD69: =-AD42 -> -2.30298 | AE69: =-AE42 -> -3.40988 | ... AI69: =-AI42 -> -4.85422
W70: Adjusted NWC | X70: =SUM(X62:X69) -> -621.81003 | Y70: =SUM(Y62:Y69) -> -431.08426 | Z70: =SUM(Z62:Z69) -> -853.05912 | AA70: =SUM(AA62:AA69) -> -325.30897 | AB70: =SUM(AB62:AB69) -> -572.06273 | AC70: =SUM(AC62:AC69) -> -657.77996 | AD70: =SUM(AD62:AD69) -> -837.04173 | AE70: =SUM(AE62:AE69) -> -433.03865 | ... AI70: =SUM(AI62:AI69) -> -510.68569
W72: Check | X72: =X44-X70 -> 0 | Y72: =Y44-Y70 -> 0 | Z72: =Z44-Z70 -> 0 | AA72: =AA44-AA70 -> 0 | AB72: =AB44-AB70 -> 0 | AC72: =AC44-AC70 -> 0 | AD72: =AD44-AD70 -> 0 | AE72: =AE44-AE70 -> 0 | ... AI72: =AI44-AI70 -> 0

Sheet DDL
A1: =IF(ROUND(SUM(E29:AN31),1)<>0,"NO","Yes") -> Yes | C1: Project X
A2: =IF(COUNTIF(E29:AN31,">0.5")+COUNTIF(E29:AN31,"<-0.5")<1,"Yes","No") -> Yes | C2: CLIENT
A3: =2-COUNTIF(A1:A2,"Yes") -> 0 | C3: ($ in 000s)
C4: Debt and Debt-Like Items
C7: Debt and Debt-Like Items | E7: FY24 | Q7: FY25 | AC7: FY26
C8: =C3 -> ($ in 000s) | D8: Ref | E8: =TB!K1 -> 45046 | F8: =TB!L1 -> 45077 | G8: =TB!M1 -> 45107 | H8: =TB!N1 -> 45138 | I8: =TB!O1 -> 45169 | J8: =TB!P1 -> 45199 | K8: =TB!Q1 -> 45230 | L8: =TB!R1 -> 45260 | ... AI8: =TB!AO1 -> 45961 | AK8: =P8 -> 45382 | AL8: =AB8 -> 45747 | AM8: =AI8 -> 45961
C9: Reported Indebtedness:
C10: Current Debt:
C11: Total current debt | E11: 0 | F11: 0 | G11: 0 | H11: 0 | I11: 0 | J11: 0 | K11: 0 | L11: 0 | M11: 0 | N11: 0 | O11: 0 | P11: 0 | Q11: 0 | R11: 0 | S11: 0 | T11: 0 | U11: 0 | V11: 0 | W11: 0 | X11: 0 | Y11: 0 | Z11: 0 | AA11: 0 | AB11: 0 | AC11: 0 | AD11: 0 | AE11: 0 | AF11: 0 | AG11: 0 | AH11: 0 | AI11: 0 | AK11: =P11 -> 0 | AL11: =AB11 -> 0 | AM11: =AI11 -> 0
C13: Long term Debt:
C14: Total long-term liabilities | E14: 0 | F14: 0 | G14: 0 | H14: 0 | I14: 0 | J14: 0 | K14: 0 | L14: 0 | M14: 0 | N14: 0 | O14: 0 | P14: 0 | Q14: 0 | R14: 0 | S14: 0 | T14: 0 | U14: 0 | V14: 0 | W14: 0 | X14: 0 | Y14: 0 | Z14: 0 | AA14: 0 | AB14: 0 | AC14: 0 | AD14: 0 | AE14: 0 | AF14: 0 | AG14: 0 | AH14: 0 | AI14: 0 | AK14: =P14 -> 0 | AL14: =AB14 -> 0 | AM14: =AI14 -> 0
C15: Reported Indebtedness | E15: =E11+E14 -> 0 | F15: =F11+F14 -> 0 | G15: =G11+G14 -> 0 | H15: =H11+H14 -> 0 | I15: =I11+I14 -> 0 | J15: =J11+J14 -> 0 | K15: =K11+K14 -> 0 | L15: =L11+L14 -> 0 | ... AI15: =AI11+AI14 -> 0 | AK15: =AK11+AK14 -> 0 | AL15: =AL11+AL14 -> 0 | AM15: =AM11+AM14 -> 0
C17: Other debt-like items:
AK18: =P18 -> 0 | AL18: =AB18 -> 0 | AM18: =AI18 -> 0
AK19: =P19 -> 0 | AL19: =AB19 -> 0 | AM19: =AI19 -> 0
AK20: =P20 -> 0 | AL20: =AB20 -> 0 | AM20: =AI20 -> 0
AK21: =P21 -> 0 | AL21: =AB21 -> 0 | AM21: =AI21 -> 0
C22: Total Other Debt-Like Items | E22: =SUM(E18:E21) -> 0 | F22: =SUM(F18:F21) -> 0 | G22: =SUM(G18:G21) -> 0 | H22: =SUM(H18:H21) -> 0 | I22: =SUM(I18:I21) -> 0 | J22: =SUM(J18:J21) -> 0 | K22: =SUM(K18:K21) -> 0 | L22: =SUM(L18:L21) -> 0 | ... AI22: =SUM(AI18:AI21) -> 0 | AK22: =SUM(AK18:AK21) -> 0 | AL22: =SUM(AL18:AL21) -> 0 | AM22: =SUM(AM18:AM21) -> 0
C23: Total debt and debt-like | E23: =E15+E22 -> 0 | F23: =F15+F22 -> 0 | G23: =G15+G22 -> 0 | H23: =H15+H22 -> 0 | I23: =I15+I22 -> 0 | J23: =J15+J22 -> 0 | K23: =K15+K22 -> 0 | L23: =L15+L22 -> 0 | ... AI23: =AI15+AI22 -> 0 | AK23: =AK15+AK22 -> 0 | AL23: =AL15+AL22 -> 0 | AM23: =AM15+AM22 -> 0
C25: Cash and cash equivalents | E25: =+'NWC1'!E51 -> -1634.4889 | F25: =+'NWC1'!F51 -> -1515.8343 | G25: =+'NWC1'!G51 -> -1285.8186 | H25: =+'NWC1'!H51 -> -1744.6673 | I25: =+'NWC1'!I51 -> -1893.5656 | J25: =+'NWC1'!J51 -> -1712.3811 | K25: =+'NWC1'!K51 -> -1802.049 | L25: =+'NWC1'!L51 -> -1828.552 | ... AI25: =+'NWC1'!AI51 -> -1764.0835 | AK25: =P25 -> -2467.1372 | AL25: =AB25 -> -2857.098 | AM25: =AI25 -> -1764.0835
C26: Net Debt / (Cash) | E26: =SUM(E23:E25) -> -1634.4889 | F26: =SUM(F23:F25) -> -1515.8343 | G26: =SUM(G23:G25) -> -1285.8186 | H26: =SUM(H23:H25) -> -1744.6673 | I26: =SUM(I23:I25) -> -1893.5656 | J26: =SUM(J23:J25) -> -1712.3811 | K26: =SUM(K23:K25) -> -1802.049 | L26: =SUM(L23:L25) -> -1828.552 | ... AI26: =SUM(AI23:AI25) -> -1764.0835 | AK26: =SUM(AK23:AK25) -> -2467.1372 | AL26: =SUM(AL23:AL25) -> -2857.098 | AM26: =SUM(AM23:AM25) -> -1764.0835
C29: Check current debt
C30: Check long-term liabilities | E30: =SUM('BS1'!E27:E27)-E14 -> 0 | F30: =SUM('BS1'!F27:F27)-F14 -> 0 | G30: =SUM('BS1'!G27:G27)-G14 -> 0 | H30: =SUM('BS1'!H27:H27)-H14 -> 0 | I30: =SUM('BS1'!I27:I27)-I14 -> 0 | J30: =SUM('BS1'!J27:J27)-J14 -> 0 | K30: =SUM('BS1'!K27:K27)-K14 -> 0 | L30: =SUM('BS1'!L27:L27)-L14 -> 0 | ... AI30: =SUM('BS1'!AI27:AI27)-AI14 -> 0 | AK30: =SUM('BS1'!AK27:AK27)-AK14 -> 0 | AL30: =SUM('BS1'!AL27:AL27)-AL14 -> 0 | AM30: =SUM('BS1'!AM27:AM27)-AM14 -> 0
C31: Check cash | E31: =+'NWC1'!E51-E25 -> 0 | F31: =+'NWC1'!F51-F25 -> 0 | G31: =+'NWC1'!G51-G25 -> 0 | H31: =+'NWC1'!H51-H25 -> 0 | I31: =+'NWC1'!I51-I25 -> 0 | J31: =+'NWC1'!J51-J25 -> 0 | K31: =+'NWC1'!K51-K25 -> 0 | L31: =+'NWC1'!L51-L25 -> 0 | ... AI31: =+'NWC1'!AI51-AI25 -> 0 | AK31: =+'NWC1'!AK51-AK25 -> 0 | AL31: =+'NWC1'!AL51-AL25 -> 0 | AM31: =+'NWC1'!AM51-AM25 -> 0

Sheet NWC_Metrics
A1: =IF(ROUND(SUM(E47:AS51),1)<>0,"NO","Yes") -> Yes | C1: Project X
A2: =IF(COUNTIF(E47:AS51,">0.5")+COUNTIF(E47:AS51,"<-0.5")<1,"Yes","No") -> Yes | C2: CLIENT
A3: =2-COUNTIF(A1:A2,"Yes") -> 0 | C3: ($ in 000s)
C4: Net Working Capital Ratio Analysis
E6: =TEXT(E8,"mmmm") -> April | F6: =TEXT(F8,"mmmm") -> May | G6: =TEXT(G8,"mmmm") -> June | H6: =TEXT(H8,"mmmm") -> July | I6: =TEXT(I8,"mmmm") -> August | J6: =TEXT(J8,"mmmm") -> September | K6: =TEXT(K8,"mmmm") -> October | L6: =TEXT(L8,"mmmm") -> November | ... AI6: =TEXT(AI8,"mmmm") -> October
C7: =C4 -> Net Working Capital Ratio Analysis | E7: FY24 | Q7: FY25 | AC7: FY26 | AO7: Averages
C8: =C3 -> ($ in 000s) | D8: Ref | E8: =TB!K1 -> 45046 | F8: =TB!L1 -> 45077 | G8: =TB!M1 -> 45107 | H8: =TB!N1 -> 45138 | I8: =TB!O1 -> 45169 | J8: =TB!P1 -> 45199 | K8: =TB!Q1 -> 45230 | L8: =TB!R1 -> 45260 | ... AI8: =TB!AO1 -> 45961 | AK8: =+P8 -> 45382 | AL8: =+AB8 -> 45747 | AM8: =+AI8 -> 45961 | AO8: 3m | AP8: 6m | AQ8: 9m | AR8: 12m
C9: Days | E9: 31 | F9: =_xlfn.DAYS(F8,E8) -> 31 | G9: =_xlfn.DAYS(G8,F8) -> 30 | H9: =_xlfn.DAYS(H8,G8) -> 31 | I9: =_xlfn.DAYS(I8,H8) -> 31 | J9: =_xlfn.DAYS(J8,I8) -> 30 | K9: =_xlfn.DAYS(K8,J8) -> 31 | L9: =_xlfn.DAYS(L8,K8) -> 30 | M9: =_xlfn.DAYS(M8,L8) -> 31 | ... AI9: =_xlfn.DAYS(AI8,AH8) -> 31 | AK9: 365 | AL9: =AL8-P8 -> 365 | AM9: =AM8-W8 -> 365 | AO9: =AVERAGE(AG9:AI9) -> 30.666667 | AP9: =AVERAGE(AD9:AI9) -> 30.666667 | AQ9: =AVERAGE(AA9:AI9) -> 30.333333 | AR9: =AVERAGE(X9:AI9) -> 30.416667
